Workbook

Sheet Dashboard
A1: VSOL IT ASSET MANAGEMENT DASHBOARD | AB1: {=_xlfn._xlws.SORT(_xlfn.UNIQUE(_xlfn._xlws.FILTER(IFERROR(Detail!$AJ$2:$AJ$532,""),IFERROR(Detail!$AJ$2:$AJ$532,"")<>"")))} -> 0
A2: =CONCATENATE("Last Updated: ", TEXT(NOW(),"DD/MM/YYYY HH:MM")) -> Last Updated: 24/08/2026 09:24 | AB2: Ali Mustafa
AB3: Bùi Quốc Thái
A4: ASSET OVERVIEW (HCM & HN) | AB4: Bùi Tuấn Huy
A5: Total Devices | C5: In Use | E5: In Stock | G5: Damaged | J5: Lost | L5: Sold | AB5: Chu Văn Toàn | AC5: =IFERROR(_xlfn.XLOOKUP(B24,Detail!$AJ$2:$AJ$532,Detail!$AK$2:$AK$532,""),"") -> linhptt
A6: =COUNTIFS(Detail!B2:B532,"<>",Detail!G2:G532,"HCM")+COUNTIFS(Detail!B2:B532,"<>",Detail!G2:G532,"HN") -> 364 | C6: =COUNTIFS(Detail!C2:C532,"In Use",Detail!G2:G532,"HCM")+COUNTIFS(Detail!C2:C532,"In Use",Detail!G2:G532,"HN") -> 153 | E6: =COUNTIFS(Detail!C2:C532,"In Stock",Detail!G2:G532,"HCM")+COUNTIFS(Detail!C2:C532,"In Stock",Detail!G2:G532,"HN") -> 153 | G6: =COUNTIFS(Detail!C2:C532,"Damaged",Detail!G2:G532,"HCM")+COUNTIFS(Detail!C2:C532,"Damaged",Detail!G2:G532,"HN") -> 52 | J6: =COUNTIFS(Detail!C2:C532,"Lost",Detail!G2:G532,"HCM")+COUNTIFS(Detail!C2:C532,"Lost",Detail!G2:G532,"HN") -> 2 | L6: =COUNTIF(Detail!C:C,"Sold") -> 2 | AB6: Đặng Hồng Phong
AB7: Đặng Thành Thái
A8: DEVICES BY TYPE (HCM & HN) | J8: DEVICES BY LOCATION | AB8: Đào Đức Dũng
A9: Device Type | B9: Quantity | C9: In Use | D9: In Stock | E9: Damaged | F9: Lost | G9: Sold | H9: Warranty | J9: Location | K9: Quantity | L9: In Use | M9: In Stock | N9: Damaged | O9: Lost | P9: Sold | AB9: Đào Duy Thoại
A10: LAPTOP | B10: =COUNTIFS(Detail!B2:B532,"LAPTOP",Detail!G2:G532,"HCM")+COUNTIFS(Detail!B2:B532,"LAPTOP",Detail!G2:G532,"HN") -> 109 | C10: =COUNTIFS(Detail!B2:B532,"LAPTOP",Detail!C2:C532,"In Use",Detail!G2:G532,"HCM")+COUNTIFS(Detail!B2:B532,"LAPTOP",Detail!C2:C532,"In Use",Detail!G2:G532,"HN") -> 47 | D10: =COUNTIFS(Detail!B2:B532,"LAPTOP",Detail!C2:C532,"In Stock",Detail!G2:G532,"HCM")+COUNTIFS(Detail!B2:B532,"LAPTOP",Detail!C2:C532,"In Stock",Detail!G2:G532,"HN") -> 52 | E10: =COUNTIFS(Detail!B2:B532,"LAPTOP",Detail!C2:C532,"Damaged",Detail!G2:G532,"HCM")+COUNTIFS(Detail!B2:B532,"LAPTOP",Detail!C2:C532,"Damaged",Detail!G2:G532,"HN") -> 4 | F10: =COUNTIFS(Detail!$B$2:$B$532,$A10,Detail!$C$2:$C$532,F$9,Detail!$G$2:$G$532,"HCM")+COUNTIFS(Detail!$B$2:$B$532,$A10,Detail!$C$2:$C$532,F$9,Detail!$G$2:$G$532,"HN") -> 2 | G10: =COUNTIFS(Detail!$B$2:$B$532,$A10,Detail!$C$2:$C$532,G$9,Detail!$G$2:$G$532,"HCM")+COUNTIFS(Detail!$B$2:$B$532,$A10,Detail!$C$2:$C$532,G$9,Detail!$G$2:$G$532,"HN") -> 2 | H10: =COUNTIFS(Detail!$B$2:$B$532,$A10,Detail!$C$2:$C$532,H$9,Detail!$G$2:$G$532,"HCM")+COUNTIFS(Detail!$B$2:$B$532,$A10,Detail!$C$2:$C$532,H$9,Detail!$G$2:$G$532,"HN") -> 2 | J10: HCM | K10: =COUNTIF(Detail!G:G,"HCM") -> 355 | L10: =COUNTIFS(Detail!G:G,"HCM",Detail!C:C,"In Use") -> 152 | M10: =COUNTIFS(Detail!G:G,"HCM",Detail!C:C,"In Stock") -> 145 | N10: =COUNTIFS(Detail!G:G,"HCM",Detail!C:C,"Damaged") -> 52 | O10: =COUNTIFS(Detail!G:G,"HCM",Detail!C:C,"Lost") -> 2 | P10: =COUNTIFS(Detail!G:G,"HCM",Detail!C:C,"Sold") -> 2 | AB10: Đào Xuân Tùng
A11: MONITOR | B11: =COUNTIFS(Detail!B2:B532,"MONITOR",Detail!G2:G532,"HCM")+COUNTIFS(Detail!B2:B532,"MONITOR",Detail!G2:G532,"HN") -> 68 | C11: =COUNTIFS(Detail!B2:B532,"MONITOR",Detail!C2:C532,"In Use",Detail!G2:G532,"HCM")+COUNTIFS(Detail!B2:B532,"MONITOR",Detail!C2:C532,"In Use",Detail!G2:G532,"HN") -> 46 | D11: =COUNTIFS(Detail!B2:B532,"MONITOR",Detail!C2:C532,"In Stock",Detail!G2:G532,"HCM")+COUNTIFS(Detail!B2:B532,"MONITOR",Detail!C2:C532,"In Stock",Detail!G2:G532,"HN") -> 21 | E11: =COUNTIFS(Detail!B2:B532,"MONITOR",Detail!C2:C532,"Damaged",Detail!G2:G532,"HCM")+COUNTIFS(Detail!B2:B532,"MONITOR",Detail!C2:C532,"Damaged",Detail!G2:G532,"HN") -> 1 | F11: =COUNTIFS(Detail!$B$2:$B$532,$A11,Detail!$C$2:$C$532,F$9,Detail!$G$2:$G$532,"HCM")+COUNTIFS(Detail!$B$2:$B$532,$A11,Detail!$C$2:$C$532,F$9,Detail!$G$2:$G$532,"HN") -> 0 | G11: =COUNTIFS(Detail!$B$2:$B$532,$A11,Detail!$C$2:$C$532,G$9,Detail!$G$2:$G$532,"HCM")+COUNTIFS(Detail!$B$2:$B$532,$A11,Detail!$C$2:$C$532,G$9,Detail!$G$2:$G$532,"HN") -> 0 | H11: =COUNTIFS(Detail!$B$2:$B$532,$A11,Detail!$C$2:$C$532,H$9,Detail!$G$2:$G$532,"HCM")+COUNTIFS(Detail!$B$2:$B$532,$A11,Detail!$C$2:$C$532,H$9,Detail!$G$2:$G$532,"HN") -> 0 | J11: HN | K11: =COUNTIF(Detail!G:G,"HN") -> 9 | L11: =COUNTIFS(Detail!G:G,"HN",Detail!C:C,"In Use") -> 1 | M11: =COUNTIFS(Detail!G:G,"HN",Detail!C:C,"In Stock") -> 8 | N11: =COUNTIFS(Detail!G:G,"HN",Detail!C:C,"Damaged") -> 0 | O11: =COUNTIFS(Detail!G:G,"HN",Detail!C:C,"Lost") -> 0 | P11: =COUNTIFS(Detail!G:G,"HN",Detail!C:C,"Sold") -> 0 | AB11: Đinh Hiểu Văn
A12: MOUSE | B12: =COUNTIFS(Detail!B2:B532,"MOUSE",Detail!G2:G532,"HCM")+COUNTIFS(Detail!B2:B532,"MOUSE",Detail!G2:G532,"HN") -> 109 | C12: =COUNTIFS(Detail!B2:B532,"MOUSE",Detail!C2:C532,"In Use",Detail!G2:G532,"HCM")+COUNTIFS(Detail!B2:B532,"MOUSE",Detail!C2:C532,"In Use",Detail!G2:G532,"HN") -> 24 | D12: =COUNTIFS(Detail!B2:B532,"MOUSE",Detail!C2:C532,"In Stock",Detail!G2:G532,"HCM")+COUNTIFS(Detail!B2:B532,"MOUSE",Detail!C2:C532,"In Stock",Detail!G2:G532,"HN") -> 47 | E12: =COUNTIFS(Detail!B2:B532,"MOUSE",Detail!C2:C532,"Damaged",Detail!G2:G532,"HCM")+COUNTIFS(Detail!B2:B532,"MOUSE",Detail!C2:C532,"Damaged",Detail!G2:G532,"HN") -> 38 | F12: =COUNTIFS(Detail!$B$2:$B$532,$A12,Detail!$C$2:$C$532,F$9,Detail!$G$2:$G$532,"HCM")+COUNTIFS(Detail!$B$2:$B$532,$A12,Detail!$C$2:$C$532,F$9,Detail!$G$2:$G$532,"HN") -> 0 | G12: =COUNTIFS(Detail!$B$2:$B$532,$A12,Detail!$C$2:$C$532,G$9,Detail!$G$2:$G$532,"HCM")+COUNTIFS(Detail!$B$2:$B$532,$A12,Detail!$C$2:$C$532,G$9,Detail!$G$2:$G$532,"HN") -> 0 | H12: =COUNTIFS(Detail!$B$2:$B$532,$A12,Detail!$C$2:$C$532,H$9,Detail!$G$2:$G$532,"HCM")+COUNTIFS(Detail!$B$2:$B$532,$A12,Detail!$C$2:$C$532,H$9,Detail!$G$2:$G$532,"HN") -> 0 | J12: TOTAL | K12: =K10+K11 -> 364 | L12: =L10+L11 -> 153 | M12: =M10+M11 -> 153 | N12: =N10+N11 -> 52 | O12: =O10+O11 -> 2 | P12: =P10+P11 -> 2 | AB12: Đinh Vũ Tiến
A13: IPAD | B13: =COUNTIFS(Detail!B2:B532,"IPAD",Detail!G2:G532,"HCM")+COUNTIFS(Detail!B2:B532,"IPAD",Detail!G2:G532,"HN") -> 4 | C13: =COUNTIFS(Detail!B2:B532,"IPAD",Detail!C2:C532,"In Use",Detail!G2:G532,"HCM")+COUNTIFS(Detail!B2:B532,"IPAD",Detail!C2:C532,"In Use",Detail!G2:G532,"HN") -> 4 | D13: =COUNTIFS(Detail!B2:B532,"IPAD",Detail!C2:C532,"In Stock",Detail!G2:G532,"HCM")+COUNTIFS(Detail!B2:B532,"IPAD",Detail!C2:C532,"In Stock",Detail!G2:G532,"HN") -> 0 | E13: =COUNTIFS(Detail!B2:B532,"IPAD",Detail!C2:C532,"Damaged",Detail!G2:G532,"HCM")+COUNTIFS(Detail!B2:B532,"IPAD",Detail!C2:C532,"Damaged",Detail!G2:G532,"HN") -> 0 | F13: =COUNTIFS(Detail!$B$2:$B$532,$A13,Detail!$C$2:$C$532,F$9,Detail!$G$2:$G$532,"HCM")+COUNTIFS(Detail!$B$2:$B$532,$A13,Detail!$C$2:$C$532,F$9,Detail!$G$2:$G$532,"HN") -> 0 | G13: =COUNTIFS(Detail!$B$2:$B$532,$A13,Detail!$C$2:$C$532,G$9,Detail!$G$2:$G$532,"HCM")+COUNTIFS(Detail!$B$2:$B$532,$A13,Detail!$C$2:$C$532,G$9,Detail!$G$2:$G$532,"HN") -> 0 | H13: =COUNTIFS(Detail!$B$2:$B$532,$A13,Detail!$C$2:$C$532,H$9,Detail!$G$2:$G$532,"HCM")+COUNTIFS(Detail!$B$2:$B$532,$A13,Detail!$C$2:$C$532,H$9,Detail!$G$2:$G$532,"HN") -> 0 | AB13: Đỗ Anh Tuấn
A14: SMARTPHONE | B14: =COUNTIFS(Detail!B2:B532,"SMARTPHONE",Detail!G2:G532,"HCM")+COUNTIFS(Detail!B2:B532,"SMARTPHONE",Detail!G2:G532,"HN") -> 4 | C14: =COUNTIFS(Detail!B2:B532,"SMARTPHONE",Detail!C2:C532,"In Use",Detail!G2:G532,"HCM")+COUNTIFS(Detail!B2:B532,"SMARTPHONE",Detail!C2:C532,"In Use",Detail!G2:G532,"HN") -> 2 | D14: =COUNTIFS(Detail!B2:B532,"SMARTPHONE",Detail!C2:C532,"In Stock",Detail!G2:G532,"HCM")+COUNTIFS(Detail!B2:B532,"SMARTPHONE",Detail!C2:C532,"In Stock",Detail!G2:G532,"HN") -> 2 | E14: =COUNTIFS(Detail!B2:B532,"SMARTPHONE",Detail!C2:C532,"Damaged",Detail!G2:G532,"HCM")+COUNTIFS(Detail!B2:B532,"SMARTPHONE",Detail!C2:C532,"Damaged",Detail!G2:G532,"HN") -> 0 | F14: =COUNTIFS(Detail!$B$2:$B$532,$A14,Detail!$C$2:$C$532,F$9,Detail!$G$2:$G$532,"HCM")+COUNTIFS(Detail!$B$2:$B$532,$A14,Detail!$C$2:$C$532,F$9,Detail!$G$2:$G$532,"HN") -> 0 | G14: =COUNTIFS(Detail!$B$2:$B$532,$A14,Detail!$C$2:$C$532,G$9,Detail!$G$2:$G$532,"HCM")+COUNTIFS(Detail!$B$2:$B$532,$A14,Detail!$C$2:$C$532,G$9,Detail!$G$2:$G$532,"HN") -> 0 | H14: =COUNTIFS(Detail!$B$2:$B$532,$A14,Detail!$C$2:$C$532,H$9,Detail!$G$2:$G$532,"HCM")+COUNTIFS(Detail!$B$2:$B$532,$A14,Detail!$C$2:$C$532,H$9,Detail!$G$2:$G$532,"HN") -> 0 | AB14: Đoàn Hà Mi
A15: CABLE | B15: =COUNTIFS(Detail!B2:B532,"CABLE",Detail!G2:G532,"HCM")+COUNTIFS(Detail!B2:B532,"CABLE",Detail!G2:G532,"HN") -> 58 | C15: =COUNTIFS(Detail!B2:B532,"CABLE",Detail!C2:C532,"In Use",Detail!G2:G532,"HCM")+COUNTIFS(Detail!B2:B532,"CABLE",Detail!C2:C532,"In Use",Detail!G2:G532,"HN") -> 23 | D15: =COUNTIFS(Detail!B2:B532,"CABLE",Detail!C2:C532,"In Stock",Detail!G2:G532,"HCM")+COUNTIFS(Detail!B2:B532,"CABLE",Detail!C2:C532,"In Stock",Detail!G2:G532,"HN") -> 30 | E15: =COUNTIFS(Detail!B2:B532,"CABLE",Detail!C2:C532,"Damaged",Detail!G2:G532,"HCM")+COUNTIFS(Detail!B2:B532,"CABLE",Detail!C2:C532,"Damaged",Detail!G2:G532,"HN") -> 5 | F15: =COUNTIFS(Detail!$B$2:$B$532,$A15,Detail!$C$2:$C$532,F$9,Detail!$G$2:$G$532,"HCM")+COUNTIFS(Detail!$B$2:$B$532,$A15,Detail!$C$2:$C$532,F$9,Detail!$G$2:$G$532,"HN") -> 0 | G15: =COUNTIFS(Detail!$B$2:$B$532,$A15,Detail!$C$2:$C$532,G$9,Detail!$G$2:$G$532,"HCM")+COUNTIFS(Detail!$B$2:$B$532,$A15,Detail!$C$2:$C$532,G$9,Detail!$G$2:$G$532,"HN") -> 0 | H15: =COUNTIFS(Detail!$B$2:$B$532,$A15,Detail!$C$2:$C$532,H$9,Detail!$G$2:$G$532,"HCM")+COUNTIFS(Detail!$B$2:$B$532,$A15,Detail!$C$2:$C$532,H$9,Detail!$G$2:$G$532,"HN") -> 0 | J15: DEVICES BY BUSINESS UNIT (HCM & HN) | AB15: Đoàn Hải Nam
A16: SSD | B16: =COUNTIFS(Detail!B2:B532,"SSD",Detail!G2:G532,"HCM")+COUNTIFS(Detail!B2:B532,"SSD",Detail!G2:G532,"HN") -> 4 | C16: =COUNTIFS(Detail!B2:B532,"SSD",Detail!C2:C532,"In Use",Detail!G2:G532,"HCM")+COUNTIFS(Detail!B2:B532,"SSD",Detail!C2:C532,"In Use",Detail!G2:G532,"HN") -> 2 | D16: =COUNTIFS(Detail!B2:B532,"SSD",Detail!C2:C532,"In Stock",Detail!G2:G532,"HCM")+COUNTIFS(Detail!B2:B532,"SSD",Detail!C2:C532,"In Stock",Detail!G2:G532,"HN") -> 0 | E16: =COUNTIFS(Detail!B2:B532,"SSD",Detail!C2:C532,"Damaged",Detail!G2:G532,"HCM")+COUNTIFS(Detail!B2:B532,"SSD",Detail!C2:C532,"Damaged",Detail!G2:G532,"HN") -> 2 | F16: =COUNTIFS(Detail!$B$2:$B$532,$A16,Detail!$C$2:$C$532,F$9,Detail!$G$2:$G$532,"HCM")+COUNTIFS(Detail!$B$2:$B$532,$A16,Detail!$C$2:$C$532,F$9,Detail!$G$2:$G$532,"HN") -> 0 | G16: =COUNTIFS(Detail!$B$2:$B$532,$A16,Detail!$C$2:$C$532,G$9,Detail!$G$2:$G$532,"HCM")+COUNTIFS(Detail!$B$2:$B$532,$A16,Detail!$C$2:$C$532,G$9,Detail!$G$2:$G$532,"HN") -> 0 | H16: =COUNTIFS(Detail!$B$2:$B$532,$A16,Detail!$C$2:$C$532,H$9,Detail!$G$2:$G$532,"HCM")+COUNTIFS(Detail!$B$2:$B$532,$A16,Detail!$C$2:$C$532,H$9,Detail!$G$2:$G$532,"HN") -> 0 | J16: Business Unit | K16: Quantity | L16: In Use | M16: In Stock | N16: Damaged | O16: Lost | P16: Sold | AB16: Đoàn Nhật Duẩn
A17: RAM | B17: =COUNTIFS(Detail!B2:B532,"RAM",Detail!G2:G532,"HCM")+COUNTIFS(Detail!B2:B532,"RAM",Detail!G2:G532,"HN") -> 2 | C17: =COUNTIFS(Detail!B2:B532,"RAM",Detail!C2:C532,"In Use",Detail!G2:G532,"HCM")+COUNTIFS(Detail!B2:B532,"RAM",Detail!C2:C532,"In Use",Detail!G2:G532,"HN") -> 0 | D17: =COUNTIFS(Detail!B2:B532,"RAM",Detail!C2:C532,"In Stock",Detail!G2:G532,"HCM")+COUNTIFS(Detail!B2:B532,"RAM",Detail!C2:C532,"In Stock",Detail!G2:G532,"HN") -> 0 | E17: =COUNTIFS(Detail!B2:B532,"RAM",Detail!C2:C532,"Damaged",Detail!G2:G532,"HCM")+COUNTIFS(Detail!B2:B532,"RAM",Detail!C2:C532,"Damaged",Detail!G2:G532,"HN") -> 2 | F17: =COUNTIFS(Detail!$B$2:$B$532,$A17,Detail!$C$2:$C$532,F$9,Detail!$G$2:$G$532,"HCM")+COUNTIFS(Detail!$B$2:$B$532,$A17,Detail!$C$2:$C$532,F$9,Detail!$G$2:$G$532,"HN") -> 0 | G17: =COUNTIFS(Detail!$B$2:$B$532,$A17,Detail!$C$2:$C$532,G$9,Detail!$G$2:$G$532,"HCM")+COUNTIFS(Detail!$B$2:$B$532,$A17,Detail!$C$2:$C$532,G$9,Detail!$G$2:$G$532,"HN") -> 0 | H17: =COUNTIFS(Detail!$B$2:$B$532,$A17,Detail!$C$2:$C$532,H$9,Detail!$G$2:$G$532,"HCM")+COUNTIFS(Detail!$B$2:$B$532,$A17,Detail!$C$2:$C$532,H$9,Detail!$G$2:$G$532,"HN") -> 0 | J17: Project | K17: =COUNTIFS(Detail!D:D,"Project",Detail!G:G,"HCM")+COUNTIFS(Detail!D:D,"Project",Detail!G:G,"HN") -> 89 | L17: =COUNTIFS(Detail!D:D,"Project",Detail!C:C,"In Use",Detail!G:G,"HCM")+COUNTIFS(Detail!D:D,"Project",Detail!C:C,"In Use",Detail!G:G,"HN") -> 84 | M17: =COUNTIFS(Detail!D:D,"Project",Detail!C:C,"In Stock",Detail!G:G,"HCM")+COUNTIFS(Detail!D:D,"Project",Detail!C:C,"In Stock",Detail!G:G,"HN") -> 1 | N17: =COUNTIFS(Detail!D:D,"Project",Detail!C:C,"Damaged",Detail!G:G,"HCM")+COUNTIFS(Detail!D:D,"Project",Detail!C:C,"Damaged",Detail!G:G,"HN") -> 4 | O17: =COUNTIFS(Detail!D:D,"Project",Detail!C:C,"Lost",Detail!G:G,"HCM")+COUNTIFS(Detail!D:D,"Project",Detail!C:C,"Lost",Detail!G:G,"HN") -> 0 | P17: =COUNTIFS(Detail!D:D,"Project",Detail!C:C,"Sold",Detail!G:G,"HCM")+COUNTIFS(Detail!D:D,"Project",Detail!C:C,"Sold",Detail!G:G,"HN") -> 0 | AB17: Dương Phạm Thành Công
A18: CPU | B18: =COUNTIFS(Detail!B2:B532,"CPU",Detail!G2:G532,"HCM")+COUNTIFS(Detail!B2:B532,"CPU",Detail!G2:G532,"HN") -> 2 | C18: =COUNTIFS(Detail!B2:B532,"CPU",Detail!C2:C532,"In Use",Detail!G2:G532,"HCM")+COUNTIFS(Detail!B2:B532,"CPU",Detail!C2:C532,"In Use",Detail!G2:G532,"HN") -> 2 | D18: =COUNTIFS(Detail!B2:B532,"CPU",Detail!C2:C532,"In Stock",Detail!G2:G532,"HCM")+COUNTIFS(Detail!B2:B532,"CPU",Detail!C2:C532,"In Stock",Detail!G2:G532,"HN") -> 0 | E18: =COUNTIFS(Detail!B2:B532,"CPU",Detail!C2:C532,"Damaged",Detail!G2:G532,"HCM")+COUNTIFS(Detail!B2:B532,"CPU",Detail!C2:C532,"Damaged",Detail!G2:G532,"HN") -> 0 | F18: =COUNTIFS(Detail!$B$2:$B$532,$A18,Detail!$C$2:$C$532,F$9,Detail!$G$2:$G$532,"HCM")+COUNTIFS(Detail!$B$2:$B$532,$A18,Detail!$C$2:$C$532,F$9,Detail!$G$2:$G$532,"HN") -> 0 | G18: =COUNTIFS(Detail!$B$2:$B$532,$A18,Detail!$C$2:$C$532,G$9,Detail!$G$2:$G$532,"HCM")+COUNTIFS(Detail!$B$2:$B$532,$A18,Detail!$C$2:$C$532,G$9,Detail!$G$2:$G$532,"HN") -> 0 | H18: =COUNTIFS(Detail!$B$2:$B$532,$A18,Detail!$C$2:$C$532,H$9,Detail!$G$2:$G$532,"HCM")+COUNTIFS(Detail!$B$2:$B$532,$A18,Detail!$C$2:$C$532,H$9,Detail!$G$2:$G$532,"HN") -> 0 | J18: BO | K18: =COUNTIFS(Detail!D:D,"BO",Detail!G:G,"HCM")+COUNTIFS(Detail!D:D,"BO",Detail!G:G,"HN") -> 30 | L18: =COUNTIFS(Detail!D:D,"BO",Detail!C:C,"In Use",Detail!G:G,"HCM")+COUNTIFS(Detail!D:D,"BO",Detail!C:C,"In Use",Detail!G:G,"HN") -> 25 | M18: =COUNTIFS(Detail!D:D,"BO",Detail!C:C,"In Stock",Detail!G:G,"HCM")+COUNTIFS(Detail!D:D,"BO",Detail!C:C,"In Stock",Detail!G:G,"HN") -> 5 | N18: =COUNTIFS(Detail!D:D,"BO",Detail!C:C,"Damaged",Detail!G:G,"HCM")+COUNTIFS(Detail!D:D,"BO",Detail!C:C,"Damaged",Detail!G:G,"HN") -> 0 | O18: =COUNTIFS(Detail!D:D,"BO",Detail!C:C,"Lost",Detail!G:G,"HCM")+COUNTIFS(Detail!D:D,"BO",Detail!C:C,"Lost",Detail!G:G,"HN") -> 0 | P18: =COUNTIFS(Detail!D:D,"BO",Detail!C:C,"Sold",Detail!G:G,"HCM")+COUNTIFS(Detail!D:D,"BO",Detail!C:C,"Sold",Detail!G:G,"HN") -> 0 | AB18: Gary Robert Charles Mckinnon
A19: ROUTER | B19: =COUNTIFS(Detail!B2:B532,"ROUTER",Detail!G2:G532,"HCM")+COUNTIFS(Detail!B2:B532,"ROUTER",Detail!G2:G532,"HN") -> 3 | C19: =COUNTIFS(Detail!B2:B532,"ROUTER",Detail!C2:C532,"In Use",Detail!G2:G532,"HCM")+COUNTIFS(Detail!B2:B532,"ROUTER",Detail!C2:C532,"In Use",Detail!G2:G532,"HN") -> 2 | D19: =COUNTIFS(Detail!B2:B532,"ROUTER",Detail!C2:C532,"In Stock",Detail!G2:G532,"HCM")+COUNTIFS(Detail!B2:B532,"ROUTER",Detail!C2:C532,"In Stock",Detail!G2:G532,"HN") -> 1 | E19: =COUNTIFS(Detail!B2:B532,"ROUTER",Detail!C2:C532,"Damaged",Detail!G2:G532,"HCM")+COUNTIFS(Detail!B2:B532,"ROUTER",Detail!C2:C532,"Damaged",Detail!G2:G532,"HN") -> 0 | F19: =COUNTIFS(Detail!$B$2:$B$532,$A19,Detail!$C$2:$C$532,F$9,Detail!$G$2:$G$532,"HCM")+COUNTIFS(Detail!$B$2:$B$532,$A19,Detail!$C$2:$C$532,F$9,Detail!$G$2:$G$532,"HN") -> 0 | G19: =COUNTIFS(Detail!$B$2:$B$532,$A19,Detail!$C$2:$C$532,G$9,Detail!$G$2:$G$532,"HCM")+COUNTIFS(Detail!$B$2:$B$532,$A19,Detail!$C$2:$C$532,G$9,Detail!$G$2:$G$532,"HN") -> 0 | H19: =COUNTIFS(Detail!$B$2:$B$532,$A19,Detail!$C$2:$C$532,H$9,Detail!$G$2:$G$532,"HCM")+COUNTIFS(Detail!$B$2:$B$532,$A19,Detail!$C$2:$C$532,H$9,Detail!$G$2:$G$532,"HN") -> 0 | J19: CTD | K19: =COUNTIFS(Detail!D:D,"CTD",Detail!G:G,"HCM")+COUNTIFS(Detail!D:D,"CTD",Detail!G:G,"HN") -> 20 | L19: =COUNTIFS(Detail!D:D,"CTD",Detail!C:C,"In Use",Detail!G:G,"HCM")+COUNTIFS(Detail!D:D,"CTD",Detail!C:C,"In Use",Detail!G:G,"HN") -> 20 | M19: =COUNTIFS(Detail!D:D,"CTD",Detail!C:C,"In Stock",Detail!G:G,"HCM")+COUNTIFS(Detail!D:D,"CTD",Detail!C:C,"In Stock",Detail!G:G,"HN") -> 0 | N19: =COUNTIFS(Detail!D:D,"CTD",Detail!C:C,"Damaged",Detail!G:G,"HCM")+COUNTIFS(Detail!D:D,"CTD",Detail!C:C,"Damaged",Detail!G:G,"HN") -> 0 | O19: =COUNTIFS(Detail!D:D,"CTD",Detail!C:C,"Lost",Detail!G:G,"HCM")+COUNTIFS(Detail!D:D,"CTD",Detail!C:C,"Lost",Detail!G:G,"HN") -> 0 | P19: =COUNTIFS(Detail!D:D,"CTD",Detail!C:C,"Sold",Detail!G:G,"HCM")+COUNTIFS(Detail!D:D,"CTD",Detail!C:C,"Sold",Detail!G:G,"HN") -> 0 | AB19: Hà Quốc Nguyên
A20: PRINTER | B20: =COUNTIFS(Detail!B2:B532,"PRINTER",Detail!G2:G532,"HCM")+COUNTIFS(Detail!B2:B532,"PRINTER",Detail!G2:G532,"HN") -> 1 | C20: =COUNTIFS(Detail!B2:B532,"PRINTER",Detail!C2:C532,"In Use",Detail!G2:G532,"HCM")+COUNTIFS(Detail!B2:B532,"PRINTER",Detail!C2:C532,"In Use",Detail!G2:G532,"HN") -> 1 | D20: =COUNTIFS(Detail!B2:B532,"PRINTER",Detail!C2:C532,"In Stock",Detail!G2:G532,"HCM")+COUNTIFS(Detail!B2:B532,"PRINTER",Detail!C2:C532,"In Stock",Detail!G2:G532,"HN") -> 0 | E20: =COUNTIFS(Detail!B2:B532,"PRINTER",Detail!C2:C532,"Damaged",Detail!G2:G532,"HCM")+COUNTIFS(Detail!B2:B532,"PRINTER",Detail!C2:C532,"Damaged",Detail!G2:G532,"HN") -> 0 | F20: =COUNTIFS(Detail!$B$2:$B$532,$A20,Detail!$C$2:$C$532,F$9,Detail!$G$2:$G$532,"HCM")+COUNTIFS(Detail!$B$2:$B$532,$A20,Detail!$C$2:$C$532,F$9,Detail!$G$2:$G$532,"HN") -> 0 | G20: =COUNTIFS(Detail!$B$2:$B$532,$A20,Detail!$C$2:$C$532,G$9,Detail!$G$2:$G$532,"HCM")+COUNTIFS(Detail!$B$2:$B$532,$A20,Detail!$C$2:$C$532,G$9,Detail!$G$2:$G$532,"HN") -> 0 | H20: =COUNTIFS(Detail!$B$2:$B$532,$A20,Detail!$C$2:$C$532,H$9,Detail!$G$2:$G$532,"HCM")+COUNTIFS(Detail!$B$2:$B$532,$A20,Detail!$C$2:$C$532,H$9,Detail!$G$2:$G$532,"HN") -> 0 | J20: AM | K20: =COUNTIFS(Detail!D:D,"AM",Detail!G:G,"HCM")+COUNTIFS(Detail!D:D,"AM",Detail!G:G,"HN") -> 3 | L20: =COUNTIFS(Detail!D:D,"AM",Detail!C:C,"In Use",Detail!G:G,"HCM")+COUNTIFS(Detail!D:D,"AM",Detail!C:C,"In Use",Detail!G:G,"HN") -> 3 | M20: =COUNTIFS(Detail!D:D,"AM",Detail!C:C,"In Stock",Detail!G:G,"HCM")+COUNTIFS(Detail!D:D,"AM",Detail!C:C,"In Stock",Detail!G:G,"HN") -> 0 | N20: =COUNTIFS(Detail!D:D,"AM",Detail!C:C,"Damaged",Detail!G:G,"HCM")+COUNTIFS(Detail!D:D,"AM",Detail!C:C,"Damaged",Detail!G:G,"HN") -> 0 | O20: =COUNTIFS(Detail!D:D,"AM",Detail!C:C,"Lost",Detail!G:G,"HCM")+COUNTIFS(Detail!D:D,"AM",Detail!C:C,"Lost",Detail!G:G,"HN") -> 0 | P20: =COUNTIFS(Detail!D:D,"AM",Detail!C:C,"Sold",Detail!G:G,"HCM")+COUNTIFS(Detail!D:D,"AM",Detail!C:C,"Sold",Detail!G:G,"HN") -> 0 | AB20: Hồ Ngọc Danh
A21: SPEAKER | B21: =COUNTIFS(Detail!B2:B532,"SPEAKER",Detail!G2:G532,"HCM")+COUNTIFS(Detail!B2:B532,"SPEAKER",Detail!G2:G532,"HN") -> 0 | C21: =COUNTIFS(Detail!B2:B532,"SPEAKER",Detail!C2:C532,"In Use",Detail!G2:G532,"HCM")+COUNTIFS(Detail!B2:B532,"SPEAKER",Detail!C2:C532,"In Use",Detail!G2:G532,"HN") -> 0 | D21: =COUNTIFS(Detail!B2:B532,"SPEAKER",Detail!C2:C532,"In Stock",Detail!G2:G532,"HCM")+COUNTIFS(Detail!B2:B532,"SPEAKER",Detail!C2:C532,"In Stock",Detail!G2:G532,"HN") -> 0 | E21: =COUNTIFS(Detail!B2:B532,"SPEAKER",Detail!C2:C532,"Damaged",Detail!G2:G532,"HCM")+COUNTIFS(Detail!B2:B532,"SPEAKER",Detail!C2:C532,"Damaged",Detail!G2:G532,"HN") -> 0 | F21: =COUNTIFS(Detail!$B$2:$B$532,$A21,Detail!$C$2:$C$532,F$9,Detail!$G$2:$G$532,"HCM")+COUNTIFS(Detail!$B$2:$B$532,$A21,Detail!$C$2:$C$532,F$9,Detail!$G$2:$G$532,"HN") -> 0 | G21: =COUNTIFS(Detail!$B$2:$B$532,$A21,Detail!$C$2:$C$532,G$9,Detail!$G$2:$G$532,"HCM")+COUNTIFS(Detail!$B$2:$B$532,$A21,Detail!$C$2:$C$532,G$9,Detail!$G$2:$G$532,"HN") -> 0 | H21: =COUNTIFS(Detail!$B$2:$B$532,$A21,Detail!$C$2:$C$532,H$9,Detail!$G$2:$G$532,"HCM")+COUNTIFS(Detail!$B$2:$B$532,$A21,Detail!$C$2:$C$532,H$9,Detail!$G$2:$G$532,"HN") -> 0 | J21: Undirect IT Staff | K21: =COUNTIFS(Detail!D:D,"Undirect IT Staff",Detail!G:G,"HCM")+COUNTIFS(Detail!D:D,"Undirect IT Staff",Detail!G:G,"HN") -> 22 | L21: =COUNTIFS(Detail!D:D,"Undirect IT Staff",Detail!C:C,"In Use",Detail!G:G,"HCM")+COUNTIFS(Detail!D:D,"Undirect IT Staff",Detail!C:C,"In Use",Detail!G:G,"HN") -> 17 | M21: =COUNTIFS(Detail!D:D,"Undirect IT Staff",Detail!C:C,"In Stock",Detail!G:G,"HCM")+COUNTIFS(Detail!D:D,"Undirect IT Staff",Detail!C:C,"In Stock",Detail!G:G,"HN") -> 3 | N21: =COUNTIFS(Detail!D:D,"Undirect IT Staff",Detail!C:C,"Damaged",Detail!G:G,"HCM")+COUNTIFS(Detail!D:D,"Undirect IT Staff",Detail!C:C,"Damaged",Detail!G:G,"HN") -> 2 | O21: =COUNTIFS(Detail!D:D,"Undirect IT Staff",Detail!C:C,"Lost",Detail!G:G,"HCM")+COUNTIFS(Detail!D:D,"Undirect IT Staff",Detail!C:C,"Lost",Detail!G:G,"HN") -> 0 | P21: =COUNTIFS(Detail!D:D,"Undirect IT Staff",Detail!C:C,"Sold",Detail!G:G,"HCM")+COUNTIFS(Detail!D:D,"Undirect IT Staff",Detail!C:C,"Sold",Detail!G:G,"HN") -> 0 | AB21: Hoàng Anh Dũng
AB22: Hoàng Thị Trang
A23: EMPLOYEE ASSET LOOKUP (HCM & HN) | J23: LAPTOP DETAILS BY CHIP & STORAGE (HCM & HN) | AB23: Huỳnh Nguyên Phương
A24: Select Employee: | B24: Phạm Thị Trúc Linh | J24: By Chip | AB24: Huỳnh Quốc Quân
J25: Chip | K25: Quantity | L25: In Use | M25: In Stock | N25: Damaged | O25: Lost | P25: Sold | AB25: Huỳnh Thúy Diễm
A26: Old Label | B26: Label | C26: Type | D26: Description | E26: Serial Number | F26: Location | G26: Status | J26: M1 | K26: =COUNTIFS(Detail!B:B,"LAPTOP",Detail!L:L,"M1",Detail!G:G,"HCM")+COUNTIFS(Detail!B:B,"LAPTOP",Detail!L:L,"M1",Detail!G:G,"HN") -> 14 | L26: =COUNTIFS(Detail!B:B,"LAPTOP",Detail!L:L,"M1",Detail!C:C,"In Use",Detail!G:G,"HCM")+COUNTIFS(Detail!B:B,"LAPTOP",Detail!L:L,"M1",Detail!C:C,"In Use",Detail!G:G,"HN") -> 5 | M26: =COUNTIFS(Detail!B:B,"LAPTOP",Detail!L:L,"M1",Detail!C:C,"In Stock",Detail!G:G,"HCM")+COUNTIFS(Detail!B:B,"LAPTOP",Detail!L:L,"M1",Detail!C:C,"In Stock",Detail!G:G,"HN") -> 8 | N26: =COUNTIFS(Detail!B:B,"LAPTOP",Detail!L:L,"M1",Detail!C:C,"Damaged",Detail!G:G,"HCM")+COUNTIFS(Detail!B:B,"LAPTOP",Detail!L:L,"M1",Detail!C:C,"Damaged",Detail!G:G,"HN") -> 1 | O26: =COUNTIFS(Detail!B:B,"LAPTOP",Detail!L:L,"M1",Detail!C:C,"Lost",Detail!G:G,"HCM")+COUNTIFS(Detail!B:B,"LAPTOP",Detail!L:L,"M1",Detail!C:C,"Lost",Detail!G:G,"HN") -> 0 | P26: =COUNTIFS(Detail!B:B,"LAPTOP",Detail!L:L,"M1",Detail!C:C,"Sold",Detail!G:G,"HCM")+COUNTIFS(Detail!B:B,"LAPTOP",Detail!L:L,"M1",Detail!C:C,"Sold",Detail!G:G,"HN") -> 0 | AB26: IPL Meeting Room
A27: {=IF(B24="","Select an employee",IFERROR(_xlfn._xlws.FILTER(_xlfn.HSTACK(IF(Detail!$H$2:$H$532=0,"",Detail!$H$2:$H$532),Detail!$I$2:$I$532,Detail!$B$2:$B$532,IF(Detail!$K$2:$K$532=0,"",Detail!$K$2:$K$532),IF(Detail!$P$2:$P$532=0,"",Detail!$P$2:$P$532),Detail!$G$2:$G$532,Detail!$C$2:$C$532),(Detail!$AK$2:$AK$532=$AC$5)*(Detail!$C$2:$C$532="In Use")*((Detail!$G$2:$G$532="HCM")+(Detail!$G$2:$G$532="HN")),"No assets found"),"No assets found"))} | B27: LAP0062 | C27: LAPTOP | D27: Macbook Pro M2 16GB | 256GB | E27: YQX1W3H610 | F27: HCM | G27: In Use | J27: M2 | K27: =COUNTIFS(Detail!B:B,"LAPTOP",Detail!L:L,"M2",Detail!G:G,"HCM")+COUNTIFS(Detail!B:B,"LAPTOP",Detail!L:L,"M2",Detail!G:G,"HN") -> 5 | L27: =COUNTIFS(Detail!B:B,"LAPTOP",Detail!L:L,"M2",Detail!C:C,"In Use",Detail!G:G,"HCM")+COUNTIFS(Detail!B:B,"LAPTOP",Detail!L:L,"M2",Detail!C:C,"In Use",Detail!G:G,"HN") -> 5 | M27: =COUNTIFS(Detail!B:B,"LAPTOP",Detail!L:L,"M2",Detail!C:C,"In Stock",Detail!G:G,"HCM")+COUNTIFS(Detail!B:B,"LAPTOP",Detail!L:L,"M2",Detail!C:C,"In Stock",Detail!G:G,"HN") -> 0 | N27: =COUNTIFS(Detail!B:B,"LAPTOP",Detail!L:L,"M2",Detail!C:C,"Damaged",Detail!G:G,"HCM")+COUNTIFS(Detail!B:B,"LAPTOP",Detail!L:L,"M2",Detail!C:C,"Damaged",Detail!G:G,"HN") -> 0 | O27: =COUNTIFS(Detail!B:B,"LAPTOP",Detail!L:L,"M2",Detail!C:C,"Lost",Detail!G:G,"HCM")+COUNTIFS(Detail!B:B,"LAPTOP",Detail!L:L,"M2",Detail!C:C,"Lost",Detail!G:G,"HN") -> 0 | P27: =COUNTIFS(Detail!B:B,"LAPTOP",Detail!L:L,"M2",Detail!C:C,"Sold",Detail!G:G,"HCM")+COUNTIFS(Detail!B:B,"LAPTOP",Detail!L:L,"M2",Detail!C:C,"Sold",Detail!G:G,"HN") -> 0 | AB27: IT Dept CTD
B28: MOU0021 | C28: MOUSE | D28: Logitech M221 | E28: 2445ZEW5H0K8 | F28: HCM | G28: In Use | J28: M3 | K28: =COUNTIFS(Detail!B:B,"LAPTOP",Detail!L:L,"M3",Detail!G:G,"HCM")+COUNTIFS(Detail!B:B,"LAPTOP",Detail!L:L,"M3",Detail!G:G,"HN") -> 3 | L28: =COUNTIFS(Detail!B:B,"LAPTOP",Detail!L:L,"M3",Detail!C:C,"In Use",Detail!G:G,"HCM")+COUNTIFS(Detail!B:B,"LAPTOP",Detail!L:L,"M3",Detail!C:C,"In Use",Detail!G:G,"HN") -> 2 | M28: =COUNTIFS(Detail!B:B,"LAPTOP",Detail!L:L,"M3",Detail!C:C,"In Stock",Detail!G:G,"HCM")+COUNTIFS(Detail!B:B,"LAPTOP",Detail!L:L,"M3",Detail!C:C,"In Stock",Detail!G:G,"HN") -> 1 | N28: =COUNTIFS(Detail!B:B,"LAPTOP",Detail!L:L,"M3",Detail!C:C,"Damaged",Detail!G:G,"HCM")+COUNTIFS(Detail!B:B,"LAPTOP",Detail!L:L,"M3",Detail!C:C,"Damaged",Detail!G:G,"HN") -> 0 | O28: =COUNTIFS(Detail!B:B,"LAPTOP",Detail!L:L,"M3",Detail!C:C,"Lost",Detail!G:G,"HCM")+COUNTIFS(Detail!B:B,"LAPTOP",Detail!L:L,"M3",Detail!C:C,"Lost",Detail!G:G,"HN") -> 0 | P28: =COUNTIFS(Detail!B:B,"LAPTOP",Detail!L:L,"M3",Detail!C:C,"Sold",Detail!G:G,"HCM")+COUNTIFS(Detail!B:B,"LAPTOP",Detail!L:L,"M3",Detail!C:C,"Sold",Detail!G:G,"HN") -> 0 | AB28: Ivan
A29: MON16276 | B29: MON0052 | C29: MONITOR | D29: Dell P2425H 24 inches | E29: 8BF2L34 | F29: HCM | G29: In Use | J29: M4 | K29: =COUNTIFS(Detail!B:B,"LAPTOP",Detail!L:L,"M4",Detail!G:G,"HCM")+COUNTIFS(Detail!B:B,"LAPTOP",Detail!L:L,"M4",Detail!G:G,"HN") -> 20 | L29: =COUNTIFS(Detail!B:B,"LAPTOP",Detail!L:L,"M4",Detail!C:C,"In Use",Detail!G:G,"HCM")+COUNTIFS(Detail!B:B,"LAPTOP",Detail!L:L,"M4",Detail!C:C,"In Use",Detail!G:G,"HN") -> 17 | M29: =COUNTIFS(Detail!B:B,"LAPTOP",Detail!L:L,"M4",Detail!C:C,"In Stock",Detail!G:G,"HCM")+COUNTIFS(Detail!B:B,"LAPTOP",Detail!L:L,"M4",Detail!C:C,"In Stock",Detail!G:G,"HN") -> 1 | N29: =COUNTIFS(Detail!B:B,"LAPTOP",Detail!L:L,"M4",Detail!C:C,"Damaged",Detail!G:G,"HCM")+COUNTIFS(Detail!B:B,"LAPTOP",Detail!L:L,"M4",Detail!C:C,"Damaged",Detail!G:G,"HN") -> 0 | O29: =COUNTIFS(Detail!B:B,"LAPTOP",Detail!L:L,"M4",Detail!C:C,"Lost",Detail!G:G,"HCM")+COUNTIFS(Detail!B:B,"LAPTOP",Detail!L:L,"M4",Detail!C:C,"Lost",Detail!G:G,"HN") -> 0 | P29: =COUNTIFS(Detail!B:B,"LAPTOP",Detail!L:L,"M4",Detail!C:C,"Sold",Detail!G:G,"HCM")+COUNTIFS(Detail!B:B,"LAPTOP",Detail!L:L,"M4",Detail!C:C,"Sold",Detail!G:G,"HN") -> 0 | AB29: Khổng Gia Bình
B30: CAB0066 | C30: CABLE | D30: Ugreen USB-C multifunction adapter | F30: HCM | G30: In Use | J30: i5 | K30: =COUNTIFS(Detail!B:B,"LAPTOP",Detail!L:L,"i5",Detail!G:G,"HCM")+COUNTIFS(Detail!B:B,"LAPTOP",Detail!L:L,"i5",Detail!G:G,"HN") -> 50 | L30: =COUNTIFS(Detail!B:B,"LAPTOP",Detail!L:L,"i5",Detail!C:C,"In Use",Detail!G:G,"HCM")+COUNTIFS(Detail!B:B,"LAPTOP",Detail!L:L,"i5",Detail!C:C,"In Use",Detail!G:G,"HN") -> 12 | M30: =COUNTIFS(Detail!B:B,"LAPTOP",Detail!L:L,"i5",Detail!C:C,"In Stock",Detail!G:G,"HCM")+COUNTIFS(Detail!B:B,"LAPTOP",Detail!L:L,"i5",Detail!C:C,"In Stock",Detail!G:G,"HN") -> 32 | N30: =COUNTIFS(Detail!B:B,"LAPTOP",Detail!L:L,"i5",Detail!C:C,"Damaged",Detail!G:G,"HCM")+COUNTIFS(Detail!B:B,"LAPTOP",Detail!L:L,"i5",Detail!C:C,"Damaged",Detail!G:G,"HN") -> 3 | O30: =COUNTIFS(Detail!B:B,"LAPTOP",Detail!L:L,"i5",Detail!C:C,"Lost",Detail!G:G,"HCM")+COUNTIFS(Detail!B:B,"LAPTOP",Detail!L:L,"i5",Detail!C:C,"Lost",Detail!G:G,"HN") -> 2 | P30: =COUNTIFS(Detail!B:B,"LAPTOP",Detail!L:L,"i5",Detail!C:C,"Sold",Detail!G:G,"HCM")+COUNTIFS(Detail!B:B,"LAPTOP",Detail!L:L,"i5",Detail!C:C,"Sold",Detail!G:G,"HN") -> 1 | AB30: Kiết Văn
J31: i7 | K31: =COUNTIFS(Detail!B:B,"LAPTOP",Detail!L:L,"i7",Detail!G:G,"HCM")+COUNTIFS(Detail!B:B,"LAPTOP",Detail!L:L,"i7",Detail!G:G,"HN") -> 17 | L31: =COUNTIFS(Detail!B:B,"LAPTOP",Detail!L:L,"i7",Detail!C:C,"In Use",Detail!G:G,"HCM")+COUNTIFS(Detail!B:B,"LAPTOP",Detail!L:L,"i7",Detail!C:C,"In Use",Detail!G:G,"HN") -> 6 | M31: =COUNTIFS(Detail!B:B,"LAPTOP",Detail!L:L,"i7",Detail!C:C,"In Stock",Detail!G:G,"HCM")+COUNTIFS(Detail!B:B,"LAPTOP",Detail!L:L,"i7",Detail!C:C,"In Stock",Detail!G:G,"HN") -> 10 | N31: =COUNTIFS(Detail!B:B,"LAPTOP",Detail!L:L,"i7",Detail!C:C,"Damaged",Detail!G:G,"HCM")+COUNTIFS(Detail!B:B,"LAPTOP",Detail!L:L,"i7",Detail!C:C,"Damaged",Detail!G:G,"HN") -> 0 | O31: =COUNTIFS(Detail!B:B,"LAPTOP",Detail!L:L,"i7",Detail!C:C,"Lost",Detail!G:G,"HCM")+COUNTIFS(Detail!B:B,"LAPTOP",Detail!L:L,"i7",Detail!C:C,"Lost",Detail!G:G,"HN") -> 0 | P31: =COUNTIFS(Detail!B:B,"LAPTOP",Detail!L:L,"i7",Detail!C:C,"Sold",Detail!G:G,"HCM")+COUNTIFS(Detail!B:B,"LAPTOP",Detail!L:L,"i7",Detail!C:C,"Sold",Detail!G:G,"HN") -> 1 | AB31: Lại Thế Cường
J32: By Storage | AB32: Lê Cao Long Nhật
J33: Storage | K33: Quantity | L33: In Use | M33: In Stock | N33: Damaged | O33: Lost | P33: Sold | AB33: Lê Nam Hưng
J34: 256GB | K34: =COUNTIFS(Detail!B:B,"LAPTOP",Detail!M:M,"*256GB*",Detail!G:G,"HCM")+COUNTIFS(Detail!B:B,"LAPTOP",Detail!M:M,"*256GB*",Detail!G:G,"HN") -> 69 | L34: =COUNTIFS(Detail!B:B,"LAPTOP",Detail!M:M,"*256GB*",Detail!C:C,"In Use",Detail!G:G,"HCM")+COUNTIFS(Detail!B:B,"LAPTOP",Detail!M:M,"*256GB*",Detail!C:C,"In Use",Detail!G:G,"HN") -> 22 | M34: =COUNTIFS(Detail!B:B,"LAPTOP",Detail!M:M,"*256GB*",Detail!C:C,"In Stock",Detail!G:G,"HCM")+COUNTIFS(Detail!B:B,"LAPTOP",Detail!M:M,"*256GB*",Detail!C:C,"In Stock",Detail!G:G,"HN") -> 40 | N34: =COUNTIFS(Detail!B:B,"LAPTOP",Detail!M:M,"*256GB*",Detail!C:C,"Damaged",Detail!G:G,"HCM")+COUNTIFS(Detail!B:B,"LAPTOP",Detail!M:M,"*256GB*",Detail!C:C,"Damaged",Detail!G:G,"HN") -> 4 | O34: =COUNTIFS(Detail!B:B,"LAPTOP",Detail!M:M,"*256GB*",Detail!C:C,"Lost",Detail!G:G,"HCM")+COUNTIFS(Detail!B:B,"LAPTOP",Detail!M:M,"*256GB*",Detail!C:C,"Lost",Detail!G:G,"HN") -> 2 | P34: =COUNTIFS(Detail!B:B,"LAPTOP",Detail!M:M,"*256GB*",Detail!C:C,"Sold",Detail!G:G,"HCM")+COUNTIFS(Detail!B:B,"LAPTOP",Detail!M:M,"*256GB*",Detail!C:C,"Sold",Detail!G:G,"HN") -> 1 | AB34: Lê Nhựt Thịnh
J35: 512GB | K35: =COUNTIFS(Detail!B:B,"LAPTOP",Detail!M:M,"*512GB*",Detail!G:G,"HCM")+COUNTIFS(Detail!B:B,"LAPTOP",Detail!M:M,"*512GB*",Detail!G:G,"HN") -> 38 | L35: =COUNTIFS(Detail!B:B,"LAPTOP",Detail!M:M,"*512GB*",Detail!C:C,"In Use",Detail!G:G,"HCM")+COUNTIFS(Detail!B:B,"LAPTOP",Detail!M:M,"*512GB*",Detail!C:C,"In Use",Detail!G:G,"HN") -> 24 | M35: =COUNTIFS(Detail!B:B,"LAPTOP",Detail!M:M,"*512GB*",Detail!C:C,"In Stock",Detail!G:G,"HCM")+COUNTIFS(Detail!B:B,"LAPTOP",Detail!M:M,"*512GB*",Detail!C:C,"In Stock",Detail!G:G,"HN") -> 11 | N35: =COUNTIFS(Detail!B:B,"LAPTOP",Detail!M:M,"*512GB*",Detail!C:C,"Damaged",Detail!G:G,"HCM")+COUNTIFS(Detail!B:B,"LAPTOP",Detail!M:M,"*512GB*",Detail!C:C,"Damaged",Detail!G:G,"HN") -> 0 | O35: =COUNTIFS(Detail!B:B,"LAPTOP",Detail!M:M,"*512GB*",Detail!C:C,"Lost",Detail!G:G,"HCM")+COUNTIFS(Detail!B:B,"LAPTOP",Detail!M:M,"*512GB*",Detail!C:C,"Lost",Detail!G:G,"HN") -> 0 | P35: =COUNTIFS(Detail!B:B,"LAPTOP",Detail!M:M,"*512GB*",Detail!C:C,"Sold",Detail!G:G,"HCM")+COUNTIFS(Detail!B:B,"LAPTOP",Detail!M:M,"*512GB*",Detail!C:C,"Sold",Detail!G:G,"HN") -> 1 | AB35: Lê Quang Hiếu
J36: 1TB | K36: =COUNTIFS(Detail!B:B,"LAPTOP",Detail!M:M,"*1TB*",Detail!G:G,"HCM")+COUNTIFS(Detail!B:B,"LAPTOP",Detail!M:M,"*1TB*",Detail!G:G,"HN") -> 2 | L36: =COUNTIFS(Detail!B:B,"LAPTOP",Detail!M:M,"*1TB*",Detail!C:C,"In Use",Detail!G:G,"HCM")+COUNTIFS(Detail!B:B,"LAPTOP",Detail!M:M,"*1TB*",Detail!C:C,"In Use",Detail!G:G,"HN") -> 1 | M36: =COUNTIFS(Detail!B:B,"LAPTOP",Detail!M:M,"*1TB*",Detail!C:C,"In Stock",Detail!G:G,"HCM")+COUNTIFS(Detail!B:B,"LAPTOP",Detail!M:M,"*1TB*",Detail!C:C,"In Stock",Detail!G:G,"HN") -> 1 | N36: =COUNTIFS(Detail!B:B,"LAPTOP",Detail!M:M,"*1TB*",Detail!C:C,"Damaged",Detail!G:G,"HCM")+COUNTIFS(Detail!B:B,"LAPTOP",Detail!M:M,"*1TB*",Detail!C:C,"Damaged",Detail!G:G,"HN") -> 0 | O36: =COUNTIFS(Detail!B:B,"LAPTOP",Detail!M:M,"*1TB*",Detail!C:C,"Lost",Detail!G:G,"HCM")+COUNTIFS(Detail!B:B,"LAPTOP",Detail!M:M,"*1TB*",Detail!C:C,"Lost",Detail!G:G,"HN") -> 0 | P36: =COUNTIFS(Detail!B:B,"LAPTOP",Detail!M:M,"*1TB*",Detail!C:C,"Sold",Detail!G:G,"HCM")+COUNTIFS(Detail!B:B,"LAPTOP",Detail!M:M,"*1TB*",Detail!C:C,"Sold",Detail!G:G,"HN") -> 0 | AB36: Lê Quý Vân Anh
J37: By Business Unit | AB37: Lê Thị Kim Anh
J38: Business Unit | K38: Quantity | L38: In Use | M38: In Stock | N38: Damaged | O38: Lost | P38: Sold | AB38: Lương Minh Hoàng
J39: Project | K39: =COUNTIFS(Detail!B:B,"LAPTOP",Detail!D:D,"Project",Detail!G:G,"HCM")+COUNTIFS(Detail!B:B,"LAPTOP",Detail!D:D,"Project",Detail!G:G,"HN") -> 25 | L39: =COUNTIFS(Detail!B:B,"LAPTOP",Detail!D:D,"Project",Detail!C:C,"In Use",Detail!G:G,"HCM")+COUNTIFS(Detail!B:B,"LAPTOP",Detail!D:D,"Project",Detail!C:C,"In Use",Detail!G:G,"HN") -> 25 | M39: =COUNTIFS(Detail!B:B,"LAPTOP",Detail!D:D,"Project",Detail!C:C,"In Stock",Detail!G:G,"HCM")+COUNTIFS(Detail!B:B,"LAPTOP",Detail!D:D,"Project",Detail!C:C,"In Stock",Detail!G:G,"HN") -> 0 | N39: =COUNTIFS(Detail!B:B,"LAPTOP",Detail!D:D,"Project",Detail!C:C,"Damaged",Detail!G:G,"HCM")+COUNTIFS(Detail!B:B,"LAPTOP",Detail!D:D,"Project",Detail!C:C,"Damaged",Detail!G:G,"HN") -> 0 | O39: =COUNTIFS(Detail!B:B,"LAPTOP",Detail!D:D,"Project",Detail!C:C,"Lost",Detail!G:G,"HCM")+COUNTIFS(Detail!B:B,"LAPTOP",Detail!D:D,"Project",Detail!C:C,"Lost",Detail!G:G,"HN") -> 0 | P39: =COUNTIFS(Detail!B:B,"LAPTOP",Detail!D:D,"Project",Detail!C:C,"Sold",Detail!G:G,"HCM")+COUNTIFS(Detail!B:B,"LAPTOP",Detail!D:D,"Project",Detail!C:C,"Sold",Detail!G:G,"HN") -> 0 | AB39: Mai Thị Cẩm Hà
J40: BO | K40: =COUNTIFS(Detail!B:B,"LAPTOP",Detail!D:D,"BO",Detail!G:G,"HCM")+COUNTIFS(Detail!B:B,"LAPTOP",Detail!D:D,"BO",Detail!G:G,"HN") -> 12 | L40: =COUNTIFS(Detail!B:B,"LAPTOP",Detail!D:D,"BO",Detail!C:C,"In Use",Detail!G:G,"HCM")+COUNTIFS(Detail!B:B,"LAPTOP",Detail!D:D,"BO",Detail!C:C,"In Use",Detail!G:G,"HN") -> 9 | M40: =COUNTIFS(Detail!B:B,"LAPTOP",Detail!D:D,"BO",Detail!C:C,"In Stock",Detail!G:G,"HCM")+COUNTIFS(Detail!B:B,"LAPTOP",Detail!D:D,"BO",Detail!C:C,"In Stock",Detail!G:G,"HN") -> 3 | N40: =COUNTIFS(Detail!B:B,"LAPTOP",Detail!D:D,"BO",Detail!C:C,"Damaged",Detail!G:G,"HCM")+COUNTIFS(Detail!B:B,"LAPTOP",Detail!D:D,"BO",Detail!C:C,"Damaged",Detail!G:G,"HN") -> 0 | O40: =COUNTIFS(Detail!B:B,"LAPTOP",Detail!D:D,"BO",Detail!C:C,"Lost",Detail!G:G,"HCM")+COUNTIFS(Detail!B:B,"LAPTOP",Detail!D:D,"BO",Detail!C:C,"Lost",Detail!G:G,"HN") -> 0 | P40: =COUNTIFS(Detail!B:B,"LAPTOP",Detail!D:D,"BO",Detail!C:C,"Sold",Detail!G:G,"HCM")+COUNTIFS(Detail!B:B,"LAPTOP",Detail!D:D,"BO",Detail!C:C,"Sold",Detail!G:G,"HN") -> 0 | AB40: Ngô Khánh Vy
J41: CTD | K41: =COUNTIFS(Detail!B:B,"LAPTOP",Detail!D:D,"CTD",Detail!G:G,"HCM")+COUNTIFS(Detail!B:B,"LAPTOP",Detail!D:D,"CTD",Detail!G:G,"HN") -> 7 | L41: =COUNTIFS(Detail!B:B,"LAPTOP",Detail!D:D,"CTD",Detail!C:C,"In Use",Detail!G:G,"HCM")+COUNTIFS(Detail!B:B,"LAPTOP",Detail!D:D,"CTD",Detail!C:C,"In Use",Detail!G:G,"HN") -> 7 | M41: =COUNTIFS(Detail!B:B,"LAPTOP",Detail!D:D,"CTD",Detail!C:C,"In Stock",Detail!G:G,"HCM")+COUNTIFS(Detail!B:B,"LAPTOP",Detail!D:D,"CTD",Detail!C:C,"In Stock",Detail!G:G,"HN") -> 0 | N41: =COUNTIFS(Detail!B:B,"LAPTOP",Detail!D:D,"CTD",Detail!C:C,"Damaged",Detail!G:G,"HCM")+COUNTIFS(Detail!B:B,"LAPTOP",Detail!D:D,"CTD",Detail!C:C,"Damaged",Detail!G:G,"HN") -> 0 | O41: =COUNTIFS(Detail!B:B,"LAPTOP",Detail!D:D,"CTD",Detail!C:C,"Lost",Detail!G:G,"HCM")+COUNTIFS(Detail!B:B,"LAPTOP",Detail!D:D,"CTD",Detail!C:C,"Lost",Detail!G:G,"HN") -> 0 | P41: =COUNTIFS(Detail!B:B,"LAPTOP",Detail!D:D,"CTD",Detail!C:C,"Sold",Detail!G:G,"HCM")+COUNTIFS(Detail!B:B,"LAPTOP",Detail!D:D,"CTD",Detail!C:C,"Sold",Detail!G:G,"HN") -> 0 | AB41: Nguyễn Anh Tuấn
J42: AM | K42: =COUNTIFS(Detail!B:B,"LAPTOP",Detail!D:D,"AM",Detail!G:G,"HCM")+COUNTIFS(Detail!B:B,"LAPTOP",Detail!D:D,"AM",Detail!G:G,"HN") -> 1 | L42: =COUNTIFS(Detail!B:B,"LAPTOP",Detail!D:D,"AM",Detail!C:C,"In Use",Detail!G:G,"HCM")+COUNTIFS(Detail!B:B,"LAPTOP",Detail!D:D,"AM",Detail!C:C,"In Use",Detail!G:G,"HN") -> 1 | M42: =COUNTIFS(Detail!B:B,"LAPTOP",Detail!D:D,"AM",Detail!C:C,"In Stock",Detail!G:G,"HCM")+COUNTIFS(Detail!B:B,"LAPTOP",Detail!D:D,"AM",Detail!C:C,"In Stock",Detail!G:G,"HN") -> 0 | N42: =COUNTIFS(Detail!B:B,"LAPTOP",Detail!D:D,"AM",Detail!C:C,"Damaged",Detail!G:G,"HCM")+COUNTIFS(Detail!B:B,"LAPTOP",Detail!D:D,"AM",Detail!C:C,"Damaged",Detail!G:G,"HN") -> 0 | O42: =COUNTIFS(Detail!B:B,"LAPTOP",Detail!D:D,"AM",Detail!C:C,"Lost",Detail!G:G,"HCM")+COUNTIFS(Detail!B:B,"LAPTOP",Detail!D:D,"AM",Detail!C:C,"Lost",Detail!G:G,"HN") -> 0 | P42: =COUNTIFS(Detail!B:B,"LAPTOP",Detail!D:D,"AM",Detail!C:C,"Sold",Detail!G:G,"HCM")+COUNTIFS(Detail!B:B,"LAPTOP",Detail!D:D,"AM",Detail!C:C,"Sold",Detail!G:G,"HN") -> 0 | AB42: Nguyễn Cao Bách
J43: Undirect IT Staff | K43: =COUNTIFS(Detail!B:B,"LAPTOP",Detail!D:D,"Undirect IT Staff",Detail!G:G,"HCM")+COUNTIFS(Detail!B:B,"LAPTOP",Detail!D:D,"Undirect IT Staff",Detail!G:G,"HN") -> 7 | L43: =COUNTIFS(Detail!B:B,"LAPTOP",Detail!D:D,"Undirect IT Staff",Detail!C:C,"In Use",Detail!G:G,"HCM")+COUNTIFS(Detail!B:B,"LAPTOP",Detail!D:D,"Undirect IT Staff",Detail!C:C,"In Use",Detail!G:G,"HN") -> 5 | M43: =COUNTIFS(Detail!B:B,"LAPTOP",Detail!D:D,"Undirect IT Staff",Detail!C:C,"In Stock",Detail!G:G,"HCM")+COUNTIFS(Detail!B:B,"LAPTOP",Detail!D:D,"Undirect IT Staff",Detail!C:C,"In Stock",Detail!G:G,"HN") -> 2 | N43: =COUNTIFS(Detail!B:B,"LAPTOP",Detail!D:D,"Undirect IT Staff",Detail!C:C,"Damaged",Detail!G:G,"HCM")+COUNTIFS(Detail!B:B,"LAPTOP",Detail!D:D,"Undirect IT Staff",Detail!C:C,"Damaged",Detail!G:G,"HN") -> 0 | O43: =COUNTIFS(Detail!B:B,"LAPTOP",Detail!D:D,"Undirect IT Staff",Detail!C:C,"Lost",Detail!G:G,"HCM")+COUNTIFS(Detail!B:B,"LAPTOP",Detail!D:D,"Undirect IT Staff",Detail!C:C,"Lost",Detail!G:G,"HN") -> 0 | P43: =COUNTIFS(Detail!B:B,"LAPTOP",Detail!D:D,"Undirect IT Staff",Detail!C:C,"Sold",Detail!G:G,"HCM")+COUNTIFS(Detail!B:B,"LAPTOP",Detail!D:D,"Undirect IT Staff",Detail!C:C,"Sold",Detail!G:G,"HN") -> 0 | AB43: Nguyễn Công Bảo
AB44: Nguyễn Đình Thái
J45: ="License Win 11 Pro Assignment ("&COUNTIFS(Detail!$B:$B,"LAPTOP",Detail!$O:$O,TRUE)&"/25)" -> License Win 11 Pro Assignment (23/25) | AB45: Nguyễn Duy Mạnh
J46: Old Label | K46: Label | L46: Employee | M46: Location | N46: Status | AB46: Nguyễn Hải Đăng
J47: {=IFERROR(_xlfn._xlws.FILTER(_xlfn.HSTACK(IF(Detail!$H$2:$H$532=0,"",Detail!$H$2:$H$532),Detail!$I$2:$I$532,IF(ISERROR(Detail!$AJ$2:$AJ$532),"",Detail!$AJ$2:$AJ$532),Detail!$G$2:$G$532,Detail!$C$2:$C$532),(Detail!$B$2:$B$532="LAPTOP")*(Detail!$O$2:$O$532=TRUE)*((Detail!$C$2:$C$532="In Use")+(Detail!$C$2:$C$532="In Stock"))),"No data found")} | K47: LAP0002 | M47: HCM | N47: In Stock | AB47: Nguyễn Hồ Quốc Thịnh
K48: LAP0008 | L48: Nguyễn Thanh Lê | M48: IPL | N48: In Use | AB48: Nguyễn Hồ Xuân Hương
K49: LAP0009 | M49: HCM | N49: In Stock | AB49: Nguyễn Hoài Nam
J50: LAP60663 | K50: LAP0015 | M50: HCM | N50: In Stock | AB50: Nguyễn Hoàng Tâm
J51: LAP15265 | K51: LAP0024 | L51: Văn Tiến Đạt | M51: IPL | N51: In Use | AB51: Nguyễn Huỳnh Thanh Phong
K52: LAP0032 | M52: HCM | N52: In Stock | AB52: Nguyễn Lâm Khánh Quỳnh
K53: LAP0033 | M53: HCM | N53: In Stock | AB53: Nguyễn Lê Thanh Trúc
J54: LAP16385 | K54: LAP0034 | L54: Bùi Tuấn Huy | M54: HCM | N54: In Use | AB54: Nguyễn Minh Hùng
K55: LAP0036 | M55: HCM | N55: In Stock | AB55: Nguyễn Minh Thy
K56: LAP0037 | M56: HCM | N56: In Stock | AB56: Nguyễn Mỹ Duyên
K57: LAP0041 | L57: Võ Lê Nguyên Khang | M57: HCM | N57: In Use | AB57: Nguyễn Ngọc Châu Sang
K58: LAP0043 | L58: Trần Hải Trình | M58: IPL | N58: In Use | AB58: Nguyễn Ngọc Lân
J59: LAP15378 | K59: LAP0046 | L59: Nguyễn Nhã Minh | M59: HCM | N59: In Use | AB59: Nguyễn Ngọc Nhiên
K60: LAP0050 | M60: HCM | N60: In Stock | AB60: Nguyễn Ngọc Trinh
K61: LAP0051 | L61: Trương Thanh Đông | M61: IPL | N61: In Use | AB61: Nguyễn Nhã Minh
K62: LAP0057 | M62: HCM | N62: In Stock | AB62: Nguyễn Quang Hoàng
K63: LAP0058 | L63: Nguyễn Ngọc Nhiên | M63: HCM | N63: In Use | AB63: Nguyễn Quốc Bảo
J64: LAP14138 | K64: LAP0059 | M64: HCM | N64: In Stock | AB64: Nguyễn Quốc Huy
K65: LAP0061 | L65: Nguyễn Công Bảo | M65: IPL | N65: In Use | AB65: Nguyễn Quốc Trung
K66: LAP0065 | L66: Nguyễn Minh Thy | M66: HCM | N66: In Use | AB66: Nguyễn Quý
K67: LAP0074 | L67: Hoàng Thị Trang | M67: HCM | N67: In Use | AB67: Nguyễn Thanh Lê
K68: LAP0090 | L68: Trần Gia Ân | M68: HCM | N68: In Use | AB68: Nguyễn Thành Trung
K69: LAP0149 | L69: Nguyễn Viết Khải | M69: HCM | N69: In Use | AB69: Nguyễn Thị Hoàng Yến
AB70: Nguyễn Thị My Sa
AB71: Nguyễn Thị Thuý Hằng
AB72: Nguyễn Thị Việt Hà
AB73: Nguyễn Thiện Nhân
AB74: Nguyễn Trung Kiên
AB75: Nguyễn Vân Anh
AB76: Nguyễn Văn Bình
AB77: Nguyễn Văn Lân
AB78: Nguyễn Viết Khải
AB79: Nguyễn Việt Trung
AB80: P.Datacenter F9
AB81: Phạm Bằng
... AB104: Vũ Đức Thuận

Sheet Detail
A1: No | B1: Device Name | C1: Condition | D1: Business Unit | E1: Job Family | F1: Project | G1: Location | H1: Old Label | I1: Label | J1: Brand | K1: Description | L1: Chip | M1: Storage | N1: Intune | O1: License Win 11 Pro | P1: SN | Q1: Purchase date | R1: Vendor | S1: Price | T1: Invoice Number | U1: Retrieval Date | V1: Retrieval Reason | W1: Retriever Name | X1: Retriever ID | Y1: Retriever Job Tiitle | Z1: Retriever Dept | AA1: Returner Name | AB1: Returner ID | AC1: Returner Job Tittle | AD1: Returner Dept | AE1: Handover Date | AF1: Handover Staff | AG1: Handover Staff ID | AH1: Handover Staff Job Tiitle | AI1: Handover Staff Dept | AJ1: Employee Name | AK1: Employee ID | AL1: Employee Job Tittle | AM1: Employee Dept | AN1: Line Manager | AO1: Repair Date | AP1: Repair Details | AQ1: Note | AR1: Note 2 | AS1: Form No.
A2: =IF(B2<>"",ROW()-1,"") -> 1 | B2: LAPTOP | C2: In Use | D2: =INDEX(Employee!E:E,MATCH(AK2,Employee!B:B,0)) -> Project | E2: =INDEX(Employee!F:F,MATCH(AK2,Employee!B:B,0)) -> Tech | F2: =INDEX(Employee!G:G,MATCH(AK2,Employee!B:B,0)) -> Venture | G2: HCM | I2: LAP0001 | J2: Apple | K2: Macbook Pro M2 16GB | 256GB | L2: M2 | M2: =RIGHT(K2,5) -> 256GB | N2: TRUE | O2: FALSE | P2: GVXHT9W54J | Q2: 45618 | R2: VNG | S2: 24710000 | AF2: =INDEX(Employee!C:C,MATCH(AG2,Employee!B:B,0)) -> Nguyễn Viết Khải | AG2: khainv | AH2: =INDEX(Employee!D:D,MATCH(AG2,Employee!B:B,0)) -> Lead IT Support Engineer | AI2: =INDEX(Employee!F:F,MATCH(AG2,Employee!B:B,0)) -> Tech | AJ2: =INDEX(Employee!C:C,MATCH(AK2,Employee!B:B,0)) -> Bùi Quốc Thái | AK2: thaibq | AL2: =INDEX(Employee!D:D,MATCH(AK2,Employee!B:B,0)) -> Associate QC Engineer | AM2: =INDEX(Employee!F:F,MATCH(AK2,Employee!B:B,0)) -> Tech | AN2: =INDEX(Employee!H:H,MATCH(AK2,Employee!B:B,0)) -> Nguyễn Khánh Vy
A3: =IF(B3<>"",ROW()-1,"") -> 2 | B3: MONITOR | C3: In Use | D3: =INDEX(Employee!E:E,MATCH(AK3,Employee!B:B,0)) -> Project | E3: =INDEX(Employee!F:F,MATCH(AK3,Employee!B:B,0)) -> Tech | F3: =INDEX(Employee!G:G,MATCH(AK3,Employee!B:B,0)) -> Venture | G3: HCM | H3: MON16273 | I3: MON0001 | J3: Dell | K3: Dell P2425H 24 inches | N3: FALSE | O3: FALSE | P3: 331PK34 | Q3: 45622 | R3: VNG | S3: 4190287 | AF3: =INDEX(Employee!C:C,MATCH(AG3,Employee!B:B,0)) -> Nguyễn Viết Khải | AG3: khainv | AH3: =INDEX(Employee!D:D,MATCH(AG3,Employee!B:B,0)) -> Lead IT Support Engineer | AI3: =INDEX(Employee!F:F,MATCH(AG3,Employee!B:B,0)) -> Tech | AJ3: =INDEX(Employee!C:C,MATCH(AK3,Employee!B:B,0)) -> Bùi Quốc Thái | AK3: thaibq | AL3: =INDEX(Employee!D:D,MATCH(AK3,Employee!B:B,0)) -> Associate QC Engineer | AM3: =INDEX(Employee!F:F,MATCH(AK3,Employee!B:B,0)) -> Tech | AN3: =INDEX(Employee!H:H,MATCH(AK3,Employee!B:B,0)) -> Nguyễn Khánh Vy
A4: =IF(B4<>"",ROW()-1,"") -> 3 | B4: MOUSE | C4: In Use | D4: =INDEX(Employee!E:E,MATCH(AK4,Employee!B:B,0)) -> Project | E4: =INDEX(Employee!F:F,MATCH(AK4,Employee!B:B,0)) -> Tech | F4: =INDEX(Employee!G:G,MATCH(AK4,Employee!B:B,0)) -> Venture | G4: HCM | I4: MOU0001 | J4: Logitech | K4: Logitech M221 | N4: FALSE | O4: FALSE | P4: 2333LZXLJNF8 | Q4: 44462 | R4: VNG | S4: 36364 | AF4: =INDEX(Employee!C:C,MATCH(AG4,Employee!B:B,0)) -> Nguyễn Viết Khải | AG4: khainv | AH4: =INDEX(Employee!D:D,MATCH(AG4,Employee!B:B,0)) -> Lead IT Support Engineer | AI4: =INDEX(Employee!F:F,MATCH(AG4,Employee!B:B,0)) -> Tech | AJ4: =INDEX(Employee!C:C,MATCH(AK4,Employee!B:B,0)) -> Bùi Quốc Thái | AK4: thaibq | AL4: =INDEX(Employee!D:D,MATCH(AK4,Employee!B:B,0)) -> Associate QC Engineer | AM4: =INDEX(Employee!F:F,MATCH(AK4,Employee!B:B,0)) -> Tech | AN4: =INDEX(Employee!H:H,MATCH(AK4,Employee!B:B,0)) -> Nguyễn Khánh Vy
A5: =IF(B5<>"",ROW()-1,"") -> 4 | B5: LAPTOP | C5: In Stock | D5: =INDEX(Employee!E:E,MATCH(AK5,Employee!B:B,0)) -> #N/A | E5: =INDEX(Employee!F:F,MATCH(AK5,Employee!B:B,0)) -> #N/A | F5: =INDEX(Employee!G:G,MATCH(AK5,Employee!B:B,0)) -> #N/A | G5: HCM | I5: LAP0002 | J5: Lenovo | K5: Lenovo Thinkpad X390 i5 16GB | 256GB | L5: i5 | M5: =RIGHT(K5,5) -> 256GB | N5: TRUE | O5: TRUE | P5: PF1FUUQ0 | Q5: 43747 | R5: VNG | S5: 2660800 | AJ5: =INDEX(Employee!C:C,MATCH(AK5,Employee!B:B,0)) -> #N/A | AL5: =INDEX(Employee!D:D,MATCH(AK5,Employee!B:B,0)) -> #N/A | AM5: =INDEX(Employee!F:F,MATCH(AK5,Employee!B:B,0)) -> #N/A | AN5: =INDEX(Employee!H:H,MATCH(AK5,Employee!B:B,0)) -> #N/A
A6: =IF(B6<>"",ROW()-1,"") -> 5 | B6: MOUSE | C6: Damaged | D6: =INDEX(Employee!E:E,MATCH(AK6,Employee!B:B,0)) -> #N/A | E6: =INDEX(Employee!F:F,MATCH(AK6,Employee!B:B,0)) -> #N/A | F6: =INDEX(Employee!G:G,MATCH(AK6,Employee!B:B,0)) -> #N/A | G6: HCM | I6: MOU0002 | J6: Logitech | K6: Logitech M221 | N6: FALSE | O6: FALSE | Q6: 44536 | R6: VNG | S6: 21500 | AF6: =INDEX(Employee!C:C,MATCH(AG6,Employee!B:B,0)) -> Nguyễn Viết Khải | AG6: khainv | AH6: =INDEX(Employee!D:D,MATCH(AG6,Employee!B:B,0)) -> Lead IT Support Engineer | AI6: =INDEX(Employee!F:F,MATCH(AG6,Employee!B:B,0)) -> Tech | AJ6: =INDEX(Employee!C:C,MATCH(AK6,Employee!B:B,0)) -> #N/A | AL6: =INDEX(Employee!D:D,MATCH(AK6,Employee!B:B,0)) -> #N/A | AM6: =INDEX(Employee!F:F,MATCH(AK6,Employee!B:B,0)) -> #N/A | AN6: =INDEX(Employee!H:H,MATCH(AK6,Employee!B:B,0)) -> #N/A
A7: =IF(B7<>"",ROW()-1,"") -> 6 | B7: LAPTOP | C7: In Use | D7: =INDEX(Employee!E:E,MATCH(AK7,Employee!B:B,0)) -> 0 | E7: =INDEX(Employee!F:F,MATCH(AK7,Employee!B:B,0)) -> Tech | F7: =INDEX(Employee!G:G,MATCH(AK7,Employee!B:B,0)) -> 0 | G7: IPL | I7: LAP0003 | J7: Apple | K7: Macbook Pro M1 16GB | 256GB | L7: M1 | M7: =RIGHT(K7,5) -> 256GB | N7: FALSE | O7: FALSE | P7: FVFHW06QQ05N | Q7: 22/07/2022 | R7: VNG | S7: 6683562 | AF7: =INDEX(Employee!C:C,MATCH(AG7,Employee!B:B,0)) -> Nguyễn Viết Khải | AG7: khainv | AH7: =INDEX(Employee!D:D,MATCH(AG7,Employee!B:B,0)) -> Lead IT Support Engineer | AI7: =INDEX(Employee!F:F,MATCH(AG7,Employee!B:B,0)) -> Tech | AJ7: =INDEX(Employee!C:C,MATCH(AK7,Employee!B:B,0)) -> Lê Nhựt Thịnh | AK7: thinhln | AL7: =INDEX(Employee!D:D,MATCH(AK7,Employee!B:B,0)) -> Software Engineer | AM7: =INDEX(Employee!F:F,MATCH(AK7,Employee!B:B,0)) -> Tech | AN7: =INDEX(Employee!H:H,MATCH(AK7,Employee!B:B,0)) -> Trần Triệu Dương (duongtt5)
A8: =IF(B8<>"",ROW()-1,"") -> 7 | B8: LAPTOP | C8: In Stock | D8: =INDEX(Employee!E:E,MATCH(AK8,Employee!B:B,0)) -> #N/A | E8: =INDEX(Employee!F:F,MATCH(AK8,Employee!B:B,0)) -> #N/A | F8: =INDEX(Employee!G:G,MATCH(AK8,Employee!B:B,0)) -> #N/A | G8: HCM | I8: LAP0004 | J8: Apple | K8: Macbook Pro M1 16GB | 256GB | L8: M1 | M8: =RIGHT(K8,5) -> 256GB | N8: TRUE | O8: FALSE | P8: C02HC0JVQ05N | Q8: 44999 | R8: VNG | S8: 3379715 | AF8: =INDEX(Employee!C:C,MATCH(AG8,Employee!B:B,0)) -> Nguyễn Viết Khải | AG8: khainv | AH8: =INDEX(Employee!D:D,MATCH(AG8,Employee!B:B,0)) -> Lead IT Support Engineer | AI8: =INDEX(Employee!F:F,MATCH(AG8,Employee!B:B,0)) -> Tech | AJ8: =INDEX(Employee!C:C,MATCH(AK8,Employee!B:B,0)) -> #N/A | AL8: =INDEX(Employee!D:D,MATCH(AK8,Employee!B:B,0)) -> #N/A | AM8: =INDEX(Employee!F:F,MATCH(AK8,Employee!B:B,0)) -> #N/A | AN8: =INDEX(Employee!H:H,MATCH(AK8,Employee!B:B,0)) -> #N/A | AS8: hieucc2
A9: =IF(B9<>"",ROW()-1,"") -> 8 | B9: MOUSE | C9: Damaged | D9: =INDEX(Employee!E:E,MATCH(AK9,Employee!B:B,0)) -> #N/A | E9: =INDEX(Employee!F:F,MATCH(AK9,Employee!B:B,0)) -> #N/A | F9: =INDEX(Employee!G:G,MATCH(AK9,Employee!B:B,0)) -> #N/A | G9: HCM | I9: MOU0003 | J9: Logitech | K9: Logitech M221 | N9: FALSE | O9: FALSE | P9: 2333LZXH2X68 | Q9: 44621 | R9: VNG | S9: 21000 | AF9: =INDEX(Employee!C:C,MATCH(AG9,Employee!B:B,0)) -> Nguyễn Viết Khải | AG9: khainv | AH9: =INDEX(Employee!D:D,MATCH(AG9,Employee!B:B,0)) -> Lead IT Support Engineer | AI9: =INDEX(Employee!F:F,MATCH(AG9,Employee!B:B,0)) -> Tech | AJ9: =INDEX(Employee!C:C,MATCH(AK9,Employee!B:B,0)) -> #N/A | AL9: =INDEX(Employee!D:D,MATCH(AK9,Employee!B:B,0)) -> #N/A | AM9: =INDEX(Employee!F:F,MATCH(AK9,Employee!B:B,0)) -> #N/A | AN9: =INDEX(Employee!H:H,MATCH(AK9,Employee!B:B,0)) -> #N/A | AS9: hieucc2
A10: =IF(B10<>"",ROW()-1,"") -> 9 | B10: LAPTOP | C10: In Use | D10: =INDEX(Employee!E:E,MATCH(AK10,Employee!B:B,0)) -> Project | E10: =INDEX(Employee!F:F,MATCH(AK10,Employee!B:B,0)) -> Tech | F10: =INDEX(Employee!G:G,MATCH(AK10,Employee!B:B,0)) -> Venture | G10: HCM | I10: LAP0005 | J10: Apple | K10: Macbook Pro M1 16GB | 256GB | L10: M1 | M10: =RIGHT(K10,5) -> 256GB | N10: TRUE | O10: FALSE | P10: C02G12P8Q05N | Q10: 44831 | R10: VNG | S10: 3300000 | AF10: =INDEX(Employee!C:C,MATCH(AG10,Employee!B:B,0)) -> Nguyễn Viết Khải | AG10: khainv | AH10: =INDEX(Employee!D:D,MATCH(AG10,Employee!B:B,0)) -> Lead IT Support Engineer | AI10: =INDEX(Employee!F:F,MATCH(AG10,Employee!B:B,0)) -> Tech | AJ10: =INDEX(Employee!C:C,MATCH(AK10,Employee!B:B,0)) -> Huỳnh Thúy Diễm | AK10: diemht | AL10: =INDEX(Employee!D:D,MATCH(AK10,Employee!B:B,0)) -> Fresher Business Analyst | AM10: =INDEX(Employee!F:F,MATCH(AK10,Employee!B:B,0)) -> Tech | AN10: =INDEX(Employee!H:H,MATCH(AK10,Employee!B:B,0)) -> Nguyễn Khánh Vy
A11: =IF(B11<>"",ROW()-1,"") -> 10 | B11: LAPTOP | C11: In Use | D11: =INDEX(Employee!E:E,MATCH(AK11,Employee!B:B,0)) -> 0 | E11: =INDEX(Employee!F:F,MATCH(AK11,Employee!B:B,0)) -> Tech | F11: =INDEX(Employee!G:G,MATCH(AK11,Employee!B:B,0)) -> 0 | G11: IPL | I11: LAP0006 | J11: Apple | K11: Macbook Pro M1 16GB | 256GB | L11: M1 | M11: =RIGHT(K11,5) -> 256GB | N11: FALSE | O11: FALSE | P11: C02H70QTQ05N | Q11: 44807 | R11: VNG | S11: 3245455 | AF11: =INDEX(Employee!C:C,MATCH(AG11,Employee!B:B,0)) -> Nguyễn Viết Khải | AG11: khainv | AH11: =INDEX(Employee!D:D,MATCH(AG11,Employee!B:B,0)) -> Lead IT Support Engineer | AI11: =INDEX(Employee!F:F,MATCH(AG11,Employee!B:B,0)) -> Tech | AJ11: =INDEX(Employee!C:C,MATCH(AK11,Employee!B:B,0)) -> Nguyễn Ngọc Châu Sang | AK11: sangnnc | AL11: =INDEX(Employee!D:D,MATCH(AK11,Employee!B:B,0)) -> Solutions Architect | AM11: =INDEX(Employee!F:F,MATCH(AK11,Employee!B:B,0)) -> Tech | AN11: =INDEX(Employee!H:H,MATCH(AK11,Employee!B:B,0)) -> Dương Huỳnh Nghĩa (nghiadh)
A12: =IF(B12<>"",ROW()-1,"") -> 11 | B12: LAPTOP | C12: In Stock | D12: =INDEX(Employee!E:E,MATCH(AK12,Employee!B:B,0)) -> #N/A | E12: =INDEX(Employee!F:F,MATCH(AK12,Employee!B:B,0)) -> #N/A | F12: =INDEX(Employee!G:G,MATCH(AK12,Employee!B:B,0)) -> #N/A | G12: HCM | I12: LAP0007 | J12: Lenovo | K12: Lenovo ThinkPad X13 i5 16GB | 256GB | L12: i5 | M12: =RIGHT(K12,5) -> 256GB | N12: TRUE | O12: FALSE | P12: PC1MHDDG | Q12: 44115 | R12: VNG | S12: 2644500 | AF12: =INDEX(Employee!C:C,MATCH(AG12,Employee!B:B,0)) -> Nguyễn Viết Khải | AG12: khainv | AH12: =INDEX(Employee!D:D,MATCH(AG12,Employee!B:B,0)) -> Lead IT Support Engineer | AI12: =INDEX(Employee!F:F,MATCH(AG12,Employee!B:B,0)) -> Tech | AJ12: =INDEX(Employee!C:C,MATCH(AK12,Employee!B:B,0)) -> #N/A | AL12: =INDEX(Employee!D:D,MATCH(AK12,Employee!B:B,0)) -> #N/A | AM12: =INDEX(Employee!F:F,MATCH(AK12,Employee!B:B,0)) -> #N/A | AN12: =INDEX(Employee!H:H,MATCH(AK12,Employee!B:B,0)) -> #N/A
A13: =IF(B13<>"",ROW()-1,"") -> 12 | B13: MOUSE | C13: In Use | D13: =INDEX(Employee!E:E,MATCH(AK13,Employee!B:B,0)) -> 0 | E13: =INDEX(Employee!F:F,MATCH(AK13,Employee!B:B,0)) -> Tech | F13: =INDEX(Employee!G:G,MATCH(AK13,Employee!B:B,0)) -> 0 | G13: IPL | I13: MOU0004 | J13: Logitech | K13: Logitech M221 | N13: FALSE | O13: FALSE | Q13: 44621 | R13: VNG | S13: 21000 | AF13: =INDEX(Employee!C:C,MATCH(AG13,Employee!B:B,0)) -> Nguyễn Viết Khải | AG13: khainv | AH13: =INDEX(Employee!D:D,MATCH(AG13,Employee!B:B,0)) -> Lead IT Support Engineer | AI13: =INDEX(Employee!F:F,MATCH(AG13,Employee!B:B,0)) -> Tech | AJ13: =INDEX(Employee!C:C,MATCH(AK13,Employee!B:B,0)) -> Nguyễn Ngọc Châu Sang | AK13: sangnnc | AL13: =INDEX(Employee!D:D,MATCH(AK13,Employee!B:B,0)) -> Solutions Architect | AM13: =INDEX(Employee!F:F,MATCH(AK13,Employee!B:B,0)) -> Tech | AN13: =INDEX(Employee!H:H,MATCH(AK13,Employee!B:B,0)) -> Dương Huỳnh Nghĩa (nghiadh)
A14: =IF(B14<>"",ROW()-1,"") -> 13 | B14: LAPTOP | C14: In Use | D14: =INDEX(Employee!E:E,MATCH(AK14,Employee!B:B,0)) -> 0 | E14: =INDEX(Employee!F:F,MATCH(AK14,Employee!B:B,0)) -> Tech | F14: =INDEX(Employee!G:G,MATCH(AK14,Employee!B:B,0)) -> 0 | G14: IPL | I14: LAP0008 | J14: Lenovo | K14: Lenovo ThinkPad T14 i5 32GB | 256GB | L14: i5 | M14: =RIGHT(K14,5) -> 256GB | N14: FALSE | O14: TRUE | P14: PF50YJSJ | Q14: 45491 | R14: VNG | S14: 25408445 | AF14: =INDEX(Employee!C:C,MATCH(AG14,Employee!B:B,0)) -> Nguyễn Viết Khải | AG14: khainv | AH14: =INDEX(Employee!D:D,MATCH(AG14,Employee!B:B,0)) -> Lead IT Support Engineer | AI14: =INDEX(Employee!F:F,MATCH(AG14,Employee!B:B,0)) -> Tech | AJ14: =INDEX(Employee!C:C,MATCH(AK14,Employee!B:B,0)) -> Nguyễn Thanh Lê | AK14: lent2 | AL14: =INDEX(Employee!D:D,MATCH(AK14,Employee!B:B,0)) -> Senior GIS Specialist | AM14: =INDEX(Employee!F:F,MATCH(AK14,Employee!B:B,0)) -> Tech | AN14: =INDEX(Employee!H:H,MATCH(AK14,Employee!B:B,0)) -> Dương Huỳnh Nghĩa (nghiadh)
A15: =IF(B15<>"",ROW()-1,"") -> 14 | B15: MOUSE | C15: In Use | D15: =INDEX(Employee!E:E,MATCH(AK15,Employee!B:B,0)) -> Project | E15: =INDEX(Employee!F:F,MATCH(AK15,Employee!B:B,0)) -> Data | F15: =INDEX(Employee!G:G,MATCH(AK15,Employee!B:B,0)) -> Resource Pool | G15: HCM | H15: MOU15343 | I15: MOU0005 | J15: Logitech | K15: Logitech M221 | N15: FALSE | O15: FALSE | P15: 2431ZEB6EG48 | Q15: 44621 | R15: VNG | S15: 21000 | AF15: =INDEX(Employee!C:C,MATCH(AG15,Employee!B:B,0)) -> Nguyễn Viết Khải | AG15: khainv | AH15: =INDEX(Employee!D:D,MATCH(AG15,Employee!B:B,0)) -> Lead IT Support Engineer | AI15: =INDEX(Employee!F:F,MATCH(AG15,Employee!B:B,0)) -> Tech | AJ15: =INDEX(Employee!C:C,MATCH(AK15,Employee!B:B,0)) -> Phạm Bằng | AK15: bangp | AL15: =INDEX(Employee!D:D,MATCH(AK15,Employee!B:B,0)) -> Fresher Data Engineer | AM15: =INDEX(Employee!F:F,MATCH(AK15,Employee!B:B,0)) -> Data | AN15: =INDEX(Employee!H:H,MATCH(AK15,Employee!B:B,0)) -> Đoàn Hải Nam
A16: =IF(B16<>"",ROW()-1,"") -> 15 | B16: LAPTOP | C16: In Stock | D16: =INDEX(Employee!E:E,MATCH(AK16,Employee!B:B,0)) -> #N/A | E16: =INDEX(Employee!F:F,MATCH(AK16,Employee!B:B,0)) -> #N/A | F16: =INDEX(Employee!G:G,MATCH(AK16,Employee!B:B,0)) -> #N/A | G16: HCM | I16: LAP0009 | J16: Lenovo | K16: Lenovo ThinkPad X13 i5 16GB | 256GB | L16: i5 | M16: =RIGHT(K16,5) -> 256GB | N16: TRUE | O16: TRUE | P16: PC1ZJRVM | Q16: 44357 | R16: VNG | S16: 2597900 | AF16: =INDEX(Employee!C:C,MATCH(AG16,Employee!B:B,0)) -> Nguyễn Viết Khải | AG16: khainv | AH16: =INDEX(Employee!D:D,MATCH(AG16,Employee!B:B,0)) -> Lead IT Support Engineer | AI16: =INDEX(Employee!F:F,MATCH(AG16,Employee!B:B,0)) -> Tech | AJ16: =INDEX(Employee!C:C,MATCH(AK16,Employee!B:B,0)) -> #N/A | AL16: =INDEX(Employee!D:D,MATCH(AK16,Employee!B:B,0)) -> #N/A | AM16: =INDEX(Employee!F:F,MATCH(AK16,Employee!B:B,0)) -> #N/A | AN16: =INDEX(Employee!H:H,MATCH(AK16,Employee!B:B,0)) -> #N/A
A17: =IF(B17<>"",ROW()-1,"") -> 16 | B17: MOUSE | C17: Damaged | D17: =INDEX(Employee!E:E,MATCH(AK17,Employee!B:B,0)) -> 0 | E17: =INDEX(Employee!F:F,MATCH(AK17,Employee!B:B,0)) -> Tech | F17: =INDEX(Employee!G:G,MATCH(AK17,Employee!B:B,0)) -> 0 | G17: HCM | H17: MOU15235 | I17: MOU0006 | J17: Logitech | K17: Logitech M221 | N17: FALSE | O17: FALSE | Q17: 44621 | R17: VNG | S17: 21000 | AF17: =INDEX(Employee!C:C,MATCH(AG17,Employee!B:B,0)) -> Nguyễn Viết Khải | AG17: khainv | AH17: =INDEX(Employee!D:D,MATCH(AG17,Employee!B:B,0)) -> Lead IT Support Engineer | AI17: =INDEX(Employee!F:F,MATCH(AG17,Employee!B:B,0)) -> Tech | AJ17: =INDEX(Employee!C:C,MATCH(AK17,Employee!B:B,0)) -> Nguyễn Thanh Lê | AK17: lent2 | AL17: =INDEX(Employee!D:D,MATCH(AK17,Employee!B:B,0)) -> Senior GIS Specialist | AM17: =INDEX(Employee!F:F,MATCH(AK17,Employee!B:B,0)) -> Tech | AN17: =INDEX(Employee!H:H,MATCH(AK17,Employee!B:B,0)) -> Dương Huỳnh Nghĩa (nghiadh)
A18: =IF(B18<>"",ROW()-1,"") -> 17 | B18: LAPTOP | C18: In Use | D18: =INDEX(Employee!E:E,MATCH(AK18,Employee!B:B,0)) -> 0 | E18: =INDEX(Employee!F:F,MATCH(AK18,Employee!B:B,0)) -> Tech | F18: =INDEX(Employee!G:G,MATCH(AK18,Employee!B:B,0)) -> 0 | G18: IPL | I18: LAP0010 | J18: Apple | K18: Macbook Pro M2 16GB | 512GB | L18: M2 | M18: =RIGHT(K18,5) -> 512GB | N18: FALSE | O18: FALSE | P18: DDJ4HW2P2C | Q18: 45252 | R18: VNG | S18: 24710000 | AF18: =INDEX(Employee!C:C,MATCH(AG18,Employee!B:B,0)) -> Nguyễn Viết Khải | AG18: khainv | AH18: =INDEX(Employee!D:D,MATCH(AG18,Employee!B:B,0)) -> Lead IT Support Engineer | AI18: =INDEX(Employee!F:F,MATCH(AG18,Employee!B:B,0)) -> Tech | AJ18: =INDEX(Employee!C:C,MATCH(AK18,Employee!B:B,0)) -> Đào Xuân Tùng | AK18: tungdx2 | AL18: =INDEX(Employee!D:D,MATCH(AK18,Employee!B:B,0)) -> Software Engineer | AM18: =INDEX(Employee!F:F,MATCH(AK18,Employee!B:B,0)) -> Tech | AN18: =INDEX(Employee!H:H,MATCH(AK18,Employee!B:B,0)) -> Trần Triệu Dương (duongtt5)
A19: =IF(B19<>"",ROW()-1,"") -> 18 | B19: MOUSE | C19: Damaged | D19: =INDEX(Employee!E:E,MATCH(AK19,Employee!B:B,0)) -> 0 | E19: =INDEX(Employee!F:F,MATCH(AK19,Employee!B:B,0)) -> OP | F19: =INDEX(Employee!G:G,MATCH(AK19,Employee!B:B,0)) -> 0 | G19: HCM | I19: MOU0007 | J19: Logitech | K19: Logitech M221 | N19: FALSE | O19: FALSE | P19: 2212LZM7T1A8 | Q19: 44621 | R19: VNG | S19: 21000 | AF19: =INDEX(Employee!C:C,MATCH(AG19,Employee!B:B,0)) -> Nguyễn Viết Khải | AG19: khainv | AH19: =INDEX(Employee!D:D,MATCH(AG19,Employee!B:B,0)) -> Lead IT Support Engineer | AI19: =INDEX(Employee!F:F,MATCH(AG19,Employee!B:B,0)) -> Tech | AJ19: =INDEX(Employee!C:C,MATCH(AK19,Employee!B:B,0)) -> Hà Quốc Nguyên | AK19: nguyenhq | AL19: =INDEX(Employee!D:D,MATCH(AK19,Employee!B:B,0)) -> Technical Support Engineer | AM19: =INDEX(Employee!F:F,MATCH(AK19,Employee!B:B,0)) -> OP | AN19: =INDEX(Employee!H:H,MATCH(AK19,Employee!B:B,0)) -> Chu Văn Toàn (ToanCV)
A20: =IF(B20<>"",ROW()-1,"") -> 19 | B20: LAPTOP | C20: In Use | D20: =INDEX(Employee!E:E,MATCH(AK20,Employee!B:B,0)) -> Project | E20: =INDEX(Employee!F:F,MATCH(AK20,Employee!B:B,0)) -> Tech | F20: =INDEX(Employee!G:G,MATCH(AK20,Employee!B:B,0)) -> Resource Pool | G20: HCM | I20: LAP0011 | J20: Lenovo | K20: Lenovo ThinkPad T490 i5 16GB | 256GB | L20: i5 | M20: =RIGHT(K20,5) -> 256GB | N20: TRUE | O20: FALSE | P20: PF2B20VE | Q20: 44043 | R20: VNG | S20: 2565000 | AF20: =INDEX(Employee!C:C,MATCH(AG20,Employee!B:B,0)) -> Nguyễn Viết Khải | AG20: khainv | AH20: =INDEX(Employee!D:D,MATCH(AG20,Employee!B:B,0)) -> Lead IT Support Engineer | AI20: =INDEX(Employee!F:F,MATCH(AG20,Employee!B:B,0)) -> Tech | AJ20: =INDEX(Employee!C:C,MATCH(AK20,Employee!B:B,0)) -> Huỳnh Nguyên Phương | AK20: phuonghn | AL20: =INDEX(Employee!D:D,MATCH(AK20,Employee!B:B,0)) -> Hardware Designer | AM20: =INDEX(Employee!F:F,MATCH(AK20,Employee!B:B,0)) -> Tech | AN20: =INDEX(Employee!H:H,MATCH(AK20,Employee!B:B,0)) -> Đoàn Hải Nam
A21: =IF(B21<>"",ROW()-1,"") -> 20 | B21: LAPTOP | C21: Damaged | D21: =INDEX(Employee!E:E,MATCH(AK21,Employee!B:B,0)) -> #N/A | E21: =INDEX(Employee!F:F,MATCH(AK21,Employee!B:B,0)) -> #N/A | F21: =INDEX(Employee!G:G,MATCH(AK21,Employee!B:B,0)) -> #N/A | G21: HCM | I21: LAP0012 | J21: Lenovo | K21: Lenovo ThinkPad T14 i5 16GB | 256GB | L21: i5 | M21: =RIGHT(K21,5) -> 256GB | N21: TRUE | O21: FALSE | P21: PF2GP2ZD | Q21: 44204 | R21: VNG | S21: 2534220 | AF21: =INDEX(Employee!C:C,MATCH(AG21,Employee!B:B,0)) -> Nguyễn Viết Khải | AG21: khainv | AH21: =INDEX(Employee!D:D,MATCH(AG21,Employee!B:B,0)) -> Lead IT Support Engineer | AI21: =INDEX(Employee!F:F,MATCH(AG21,Employee!B:B,0)) -> Tech | AJ21: =INDEX(Employee!C:C,MATCH(AK21,Employee!B:B,0)) -> #N/A | AL21: =INDEX(Employee!D:D,MATCH(AK21,Employee!B:B,0)) -> #N/A | AM21: =INDEX(Employee!F:F,MATCH(AK21,Employee!B:B,0)) -> #N/A | AN21: =INDEX(Employee!H:H,MATCH(AK21,Employee!B:B,0)) -> #N/A | AQ21: Lỗi MainBoard +Màn Hình chớp
A22: =IF(B22<>"",ROW()-1,"") -> 21 | B22: MOUSE | C22: In Use | D22: =INDEX(Employee!E:E,MATCH(AK22,Employee!B:B,0)) -> 0 | E22: =INDEX(Employee!F:F,MATCH(AK22,Employee!B:B,0)) -> Tech | F22: =INDEX(Employee!G:G,MATCH(AK22,Employee!B:B,0)) -> 0 | G22: IPL | I22: MOU0008 | J22: Logitech | K22: Logitech M221 | N22: FALSE | O22: FALSE | Q22: 44699 | R22: VNG | S22: 20900 | AF22: =INDEX(Employee!C:C,MATCH(AG22,Employee!B:B,0)) -> Nguyễn Viết Khải | AG22: khainv | AH22: =INDEX(Employee!D:D,MATCH(AG22,Employee!B:B,0)) -> Lead IT Support Engineer | AI22: =INDEX(Employee!F:F,MATCH(AG22,Employee!B:B,0)) -> Tech | AJ22: =INDEX(Employee!C:C,MATCH(AK22,Employee!B:B,0)) -> Đào Xuân Tùng | AK22: tungdx2 | AL22: =INDEX(Employee!D:D,MATCH(AK22,Employee!B:B,0)) -> Software Engineer | AM22: =INDEX(Employee!F:F,MATCH(AK22,Employee!B:B,0)) -> Tech | AN22: =INDEX(Employee!H:H,MATCH(AK22,Employee!B:B,0)) -> Trần Triệu Dương (duongtt5)
A23: =IF(B23<>"",ROW()-1,"") -> 22 | B23: LAPTOP | C23: In Stock | D23: =INDEX(Employee!E:E,MATCH(AK23,Employee!B:B,0)) -> #N/A | E23: =INDEX(Employee!F:F,MATCH(AK23,Employee!B:B,0)) -> #N/A | F23: =INDEX(Employee!G:G,MATCH(AK23,Employee!B:B,0)) -> #N/A | G23: HCM | I23: LAP0013 | J23: Apple | K23: Macbook Pro M1 16GB | 256GB | L23: M1 | M23: =RIGHT(K23,5) -> 256GB | N23: TRUE | O23: FALSE | P23: FVFHQ8MMQ05N | Q23: 44743 | R23: VNG | S23: 5512828 | AF23: =INDEX(Employee!C:C,MATCH(AG23,Employee!B:B,0)) -> Nguyễn Viết Khải | AG23: khainv | AH23: =INDEX(Employee!D:D,MATCH(AG23,Employee!B:B,0)) -> Lead IT Support Engineer | AI23: =INDEX(Employee!F:F,MATCH(AG23,Employee!B:B,0)) -> Tech | AJ23: =INDEX(Employee!C:C,MATCH(AK23,Employee!B:B,0)) -> #N/A | AL23: =INDEX(Employee!D:D,MATCH(AK23,Employee!B:B,0)) -> #N/A | AM23: =INDEX(Employee!F:F,MATCH(AK23,Employee!B:B,0)) -> #N/A | AN23: =INDEX(Employee!H:H,MATCH(AK23,Employee!B:B,0)) -> #N/A
A24: =IF(B24<>"",ROW()-1,"") -> 23 | B24: MOUSE | C24: Damaged | D24: =INDEX(Employee!E:E,MATCH(AK24,Employee!B:B,0)) -> Undirect IT Staff | E24: =INDEX(Employee!F:F,MATCH(AK24,Employee!B:B,0)) -> Tech | F24: =INDEX(Employee!G:G,MATCH(AK24,Employee!B:B,0)) -> Odoo | G24: HCM | H24: MOU15330 | I24: MOU0009 | J24: Logitech | K24: Logitech M221 | N24: FALSE | O24: FALSE | P24: 2345LZXET5L8 | Q24: 44727 | R24: VNG | S24: 20900 | AF24: =INDEX(Employee!C:C,MATCH(AG24,Employee!B:B,0)) -> Nguyễn Viết Khải | AG24: khainv | AH24: =INDEX(Employee!D:D,MATCH(AG24,Employee!B:B,0)) -> Lead IT Support Engineer | AI24: =INDEX(Employee!F:F,MATCH(AG24,Employee!B:B,0)) -> Tech | AJ24: =INDEX(Employee!C:C,MATCH(AK24,Employee!B:B,0)) -> Nguyễn Lâm Khánh Quỳnh | AK24: quynhnlk | AL24: =INDEX(Employee!D:D,MATCH(AK24,Employee!B:B,0)) -> Business Analyst | AM24: =INDEX(Employee!F:F,MATCH(AK24,Employee!B:B,0)) -> Tech | AN24: =INDEX(Employee!H:H,MATCH(AK24,Employee!B:B,0)) -> Dương Phạm Thành Công (congdpt)
A25: =IF(B25<>"",ROW()-1,"") -> 24 | B25: LAPTOP | C25: In Stock | D25: =INDEX(Employee!E:E,MATCH(AK25,Employee!B:B,0)) -> #N/A | E25: =INDEX(Employee!F:F,MATCH(AK25,Employee!B:B,0)) -> #N/A | F25: =INDEX(Employee!G:G,MATCH(AK25,Employee!B:B,0)) -> #N/A | G25: HCM | I25: LAP0014 | J25: Apple | K25: Macbook Pro M1 16GB | 256GB | L25: M1 | M25: =RIGHT(K25,5) -> 256GB | N25: TRUE | O25: FALSE | P25: FVFHQ8TJQ05N | Q25: 44743 | R25: VNG | S25: 5512828 | AF25: =INDEX(Employee!C:C,MATCH(AG25,Employee!B:B,0)) -> Nguyễn Viết Khải | AG25: khainv | AH25: =INDEX(Employee!D:D,MATCH(AG25,Employee!B:B,0)) -> Lead IT Support Engineer | AI25: =INDEX(Employee!F:F,MATCH(AG25,Employee!B:B,0)) -> Tech | AJ25: =INDEX(Employee!C:C,MATCH(AK25,Employee!B:B,0)) -> #N/A | AL25: =INDEX(Employee!D:D,MATCH(AK25,Employee!B:B,0)) -> #N/A | AM25: =INDEX(Employee!F:F,MATCH(AK25,Employee!B:B,0)) -> #N/A | AN25: =INDEX(Employee!H:H,MATCH(AK25,Employee!B:B,0)) -> #N/A
A26: =IF(B26<>"",ROW()-1,"") -> 25 | B26: LAPTOP | C26: In Stock | D26: =INDEX(Employee!E:E,MATCH(AK26,Employee!B:B,0)) -> #N/A | E26: =INDEX(Employee!F:F,MATCH(AK26,Employee!B:B,0)) -> #N/A | F26: =INDEX(Employee!G:G,MATCH(AK26,Employee!B:B,0)) -> #N/A | G26: HCM | H26: LAP60663 | I26: LAP0015 | J26: Lenovo | K26: Lenovo ThinkPad T14 i5 16GB | 256GB | L26: i5 | M26: =RIGHT(K26,5) -> 256GB | N26: TRUE | O26: TRUE | P26: PF2JY588 | Q26: 44272 | R26: VNG | S26: 2545300 | AF26: =INDEX(Employee!C:C,MATCH(AG26,Employee!B:B,0)) -> Nguyễn Viết Khải | AG26: khainv | AH26: =INDEX(Employee!D:D,MATCH(AG26,Employee!B:B,0)) -> Lead IT Support Engineer | AI26: =INDEX(Employee!F:F,MATCH(AG26,Employee!B:B,0)) -> Tech | AJ26: =INDEX(Employee!C:C,MATCH(AK26,Employee!B:B,0)) -> #N/A | AL26: =INDEX(Employee!D:D,MATCH(AK26,Employee!B:B,0)) -> #N/A | AM26: =INDEX(Employee!F:F,MATCH(AK26,Employee!B:B,0)) -> #N/A | AN26: =INDEX(Employee!H:H,MATCH(AK26,Employee!B:B,0)) -> #N/A
A27: =IF(B27<>"",ROW()-1,"") -> 26 | B27: LAPTOP | C27: In Use | D27: =INDEX(Employee!E:E,MATCH(AK27,Employee!B:B,0)) -> Project | E27: =INDEX(Employee!F:F,MATCH(AK27,Employee!B:B,0)) -> Tech | F27: =INDEX(Employee!G:G,MATCH(AK27,Employee!B:B,0)) -> Venture | G27: HCM | I27: LAP0016 | J27: Lenovo | K27: Lenovo ThinkPad X13 i5 16GB | 256GB | L27: i5 | M27: =RIGHT(K27,5) -> 256GB | N27: TRUE | O27: FALSE | P27: PC2CD0J9 | Q27: 44680 | R27: VNG | S27: 2916891 | AF27: =INDEX(Employee!C:C,MATCH(AG27,Employee!B:B,0)) -> Nguyễn Viết Khải | AG27: khainv | AH27: =INDEX(Employee!D:D,MATCH(AG27,Employee!B:B,0)) -> Lead IT Support Engineer | AI27: =INDEX(Employee!F:F,MATCH(AG27,Employee!B:B,0)) -> Tech | AJ27: =INDEX(Employee!C:C,MATCH(AK27,Employee!B:B,0)) -> Nguyễn Quý | AK27: quyn | AL27: =INDEX(Employee!D:D,MATCH(AK27,Employee!B:B,0)) -> Senior Software Engineer | AM27: =INDEX(Employee!F:F,MATCH(AK27,Employee!B:B,0)) -> Tech | AN27: =INDEX(Employee!H:H,MATCH(AK27,Employee!B:B,0)) -> Đoàn Nhật Duẩn (duandn)
A28: =IF(B28<>"",ROW()-1,"") -> 27 | B28: LAPTOP | C28: In Stock | D28: =INDEX(Employee!E:E,MATCH(AK28,Employee!B:B,0)) -> #N/A | E28: =INDEX(Employee!F:F,MATCH(AK28,Employee!B:B,0)) -> #N/A | F28: =INDEX(Employee!G:G,MATCH(AK28,Employee!B:B,0)) -> #N/A | G28: HCM | H28: LAP12712 | I28: LAP0017 | J28: Lenovo | K28: Lenovo ThinkPad T480 i5 16GB | 256GB | L28: i5 | M28: =RIGHT(K28,5) -> 256GB | N28: TRUE | O28: FALSE | P28: PF1GA0XV | Q28: 43448 | R28: VNG | S28: 2590300 | AF28: =INDEX(Employee!C:C,MATCH(AG28,Employee!B:B,0)) -> Nguyễn Viết Khải | AG28: khainv | AH28: =INDEX(Employee!D:D,MATCH(AG28,Employee!B:B,0)) -> Lead IT Support Engineer | AI28: =INDEX(Employee!F:F,MATCH(AG28,Employee!B:B,0)) -> Tech | AJ28: =INDEX(Employee!C:C,MATCH(AK28,Employee!B:B,0)) -> #N/A | AL28: =INDEX(Employee!D:D,MATCH(AK28,Employee!B:B,0)) -> #N/A | AM28: =INDEX(Employee!F:F,MATCH(AK28,Employee!B:B,0)) -> #N/A | AN28: =INDEX(Employee!H:H,MATCH(AK28,Employee!B:B,0)) -> #N/A
A29: =IF(B29<>"",ROW()-1,"") -> 28 | B29: LAPTOP | C29: In Use | D29: =INDEX(Employee!E:E,MATCH(AK29,Employee!B:B,0)) -> Project | E29: =INDEX(Employee!F:F,MATCH(AK29,Employee!B:B,0)) -> Tech | F29: =INDEX(Employee!G:G,MATCH(AK29,Employee!B:B,0)) -> Resource Pool | G29: HCM | I29: LAP0018 | J29: Lenovo | K29: Lenovo ThinkPad T14 i5 16GB | 256GB | L29: i5 | M29: =RIGHT(K29,5) -> 256GB | N29: TRUE | O29: FALSE | P29: PF2QD6RR | Q29: 44347 | R29: VNG | S29: 2538700 | AF29: =INDEX(Employee!C:C,MATCH(AG29,Employee!B:B,0)) -> Nguyễn Viết Khải | AG29: khainv | AH29: =INDEX(Employee!D:D,MATCH(AG29,Employee!B:B,0)) -> Lead IT Support Engineer | AI29: =INDEX(Employee!F:F,MATCH(AG29,Employee!B:B,0)) -> Tech | AJ29: =INDEX(Employee!C:C,MATCH(AK29,Employee!B:B,0)) -> Huỳnh Nguyên Phương | AK29: phuonghn | AL29: =INDEX(Employee!D:D,MATCH(AK29,Employee!B:B,0)) -> Hardware Designer | AM29: =INDEX(Employee!F:F,MATCH(AK29,Employee!B:B,0)) -> Tech | AN29: =INDEX(Employee!H:H,MATCH(AK29,Employee!B:B,0)) -> Đoàn Hải Nam
A30: =IF(B30<>"",ROW()-1,"") -> 29 | B30: LAPTOP | C30: In Stock | D30: =INDEX(Employee!E:E,MATCH(AK30,Employee!B:B,0)) -> #N/A | E30: =INDEX(Employee!F:F,MATCH(AK30,Employee!B:B,0)) -> #N/A | F30: =INDEX(Employee!G:G,MATCH(AK30,Employee!B:B,0)) -> #N/A | G30: HCM | H30: LAP12473 | I30: LAP0019 | J30: Lenovo | K30: Lenovo ThinkPad X280 i5 16GB | 256GB | L30: i5 | M30: =RIGHT(K30,5) -> 256GB | N30: TRUE | O30: FALSE | P30: PC0X2880 | Q30: 43363 | R30: VNG | S30: 2683700 | AF30: =INDEX(Employee!C:C,MATCH(AG30,Employee!B:B,0)) -> Nguyễn Viết Khải | AG30: khainv | AH30: =INDEX(Employee!D:D,MATCH(AG30,Employee!B:B,0)) -> Lead IT Support Engineer | AI30: =INDEX(Employee!F:F,MATCH(AG30,Employee!B:B,0)) -> Tech | AJ30: =INDEX(Employee!C:C,MATCH(AK30,Employee!B:B,0)) -> #N/A | AL30: =INDEX(Employee!D:D,MATCH(AK30,Employee!B:B,0)) -> #N/A | AM30: =INDEX(Employee!F:F,MATCH(AK30,Employee!B:B,0)) -> #N/A | AN30: =INDEX(Employee!H:H,MATCH(AK30,Employee!B:B,0)) -> #N/A
A31: =IF(B31<>"",ROW()-1,"") -> 30 | B31: LAPTOP | C31: Damaged | D31: =INDEX(Employee!E:E,MATCH(AK31,Employee!B:B,0)) -> #N/A | E31: =INDEX(Employee!F:F,MATCH(AK31,Employee!B:B,0)) -> #N/A | F31: =INDEX(Employee!G:G,MATCH(AK31,Employee!B:B,0)) -> #N/A | G31: HCM | I31: LAP0020 | J31: Lenovo | K31: Lenovo ThinkPad T14 i5 16GB | 256GB | L31: i5 | M31: =RIGHT(K31,5) -> 256GB | N31: TRUE | O31: FALSE | P31: PF2JY3VW | Q31: 44272 | R31: VNG | S31: 2545300 | AF31: =INDEX(Employee!C:C,MATCH(AG31,Employee!B:B,0)) -> Nguyễn Viết Khải | AG31: khainv | AH31: =INDEX(Employee!D:D,MATCH(AG31,Employee!B:B,0)) -> Lead IT Support Engineer | AI31: =INDEX(Employee!F:F,MATCH(AG31,Employee!B:B,0)) -> Tech | AJ31: =INDEX(Employee!C:C,MATCH(AK31,Employee!B:B,0)) -> #N/A | AL31: =INDEX(Employee!D:D,MATCH(AK31,Employee!B:B,0)) -> #N/A | AM31: =INDEX(Employee!F:F,MATCH(AK31,Employee!B:B,0)) -> #N/A | AN31: =INDEX(Employee!H:H,MATCH(AK31,Employee!B:B,0)) -> #N/A | AQ31: Màn hình chớp | AS31: anhnv5
A32: =IF(B32<>"",ROW()-1,"") -> 31 | B32: LAPTOP | C32: In Use | D32: =INDEX(Employee!E:E,MATCH(AK32,Employee!B:B,0)) -> 0 | E32: =INDEX(Employee!F:F,MATCH(AK32,Employee!B:B,0)) -> Tech | F32: =INDEX(Employee!G:G,MATCH(AK32,Employee!B:B,0)) -> 0 | G32: IPL | I32: LAP0021 | J32: Apple | K32: Macbook Pro M2 16GB | 256GB | L32: M2 | M32: =RIGHT(K32,5) -> 256GB | N32: FALSE | O32: FALSE | P32: WC021HQ1JJ | Q32: 44804 | R32: VNG | S32: 7342466 | AF32: =INDEX(Employee!C:C,MATCH(AG32,Employee!B:B,0)) -> Nguyễn Viết Khải | AG32: khainv | AH32: =INDEX(Employee!D:D,MATCH(AG32,Employee!B:B,0)) -> Lead IT Support Engineer | AI32: =INDEX(Employee!F:F,MATCH(AG32,Employee!B:B,0)) -> Tech | AJ32: =INDEX(Employee!C:C,MATCH(AK32,Employee!B:B,0)) -> Trần Kiên | AK32: kient | AL32: =INDEX(Employee!D:D,MATCH(AK32,Employee!B:B,0)) -> QC Engineer | AM32: =INDEX(Employee!F:F,MATCH(AK32,Employee!B:B,0)) -> Tech | AN32: =INDEX(Employee!H:H,MATCH(AK32,Employee!B:B,0)) -> Trần Triệu Dương (duongtt5)
A33: =IF(B33<>"",ROW()-1,"") -> 32 | B33: LAPTOP | C33: In Stock | D33: =INDEX(Employee!E:E,MATCH(AK33,Employee!B:B,0)) -> #N/A | E33: =INDEX(Employee!F:F,MATCH(AK33,Employee!B:B,0)) -> #N/A | F33: =INDEX(Employee!G:G,MATCH(AK33,Employee!B:B,0)) -> #N/A | G33: HCM | I33: LAP0022 | J33: Apple | K33: Macbook Pro M1 16GB | 256GB | L33: M1 | M33: =RIGHT(K33,5) -> 256GB | N33: TRUE | O33: FALSE | P33: C02H70Q6Q05N | Q33: 44807 | R33: VNG | S33: 3245455 | AF33: =INDEX(Employee!C:C,MATCH(AG33,Employee!B:B,0)) -> Nguyễn Viết Khải | AG33: khainv | AH33: =INDEX(Employee!D:D,MATCH(AG33,Employee!B:B,0)) -> Lead IT Support Engineer | AI33: =INDEX(Employee!F:F,MATCH(AG33,Employee!B:B,0)) -> Tech | AJ33: =INDEX(Employee!C:C,MATCH(AK33,Employee!B:B,0)) -> #N/A | AL33: =INDEX(Employee!D:D,MATCH(AK33,Employee!B:B,0)) -> #N/A | AM33: =INDEX(Employee!F:F,MATCH(AK33,Employee!B:B,0)) -> #N/A | AN33: =INDEX(Employee!H:H,MATCH(AK33,Employee!B:B,0)) -> #N/A
A34: =IF(B34<>"",ROW()-1,"") -> 33 | B34: LAPTOP | C34: In Stock | D34: =INDEX(Employee!E:E,MATCH(AK34,Employee!B:B,0)) -> #N/A | E34: =INDEX(Employee!F:F,MATCH(AK34,Employee!B:B,0)) -> #N/A | F34: =INDEX(Employee!G:G,MATCH(AK34,Employee!B:B,0)) -> #N/A | G34: HCM | H34: LAP15806 | I34: LAP0023 | J34: Lenovo | K34: Lenovo ThinkPad T14 i5 16GB | 256GB | L34: i5 | M34: =RIGHT(K34,5) -> 256GB | N34: TRUE | O34: FALSE | P34: PF3W4343 | Q34: 44796 | R34: VNG | S34: 5736667 | AF34: =INDEX(Employee!C:C,MATCH(AG34,Employee!B:B,0)) -> Nguyễn Viết Khải | AG34: khainv | AH34: =INDEX(Employee!D:D,MATCH(AG34,Employee!B:B,0)) -> Lead IT Support Engineer | AI34: =INDEX(Employee!F:F,MATCH(AG34,Employee!B:B,0)) -> Tech | AJ34: =INDEX(Employee!C:C,MATCH(AK34,Employee!B:B,0)) -> #N/A | AL34: =INDEX(Employee!D:D,MATCH(AK34,Employee!B:B,0)) -> #N/A | AM34: =INDEX(Employee!F:F,MATCH(AK34,Employee!B:B,0)) -> #N/A | AN34: =INDEX(Employee!H:H,MATCH(AK34,Employee!B:B,0)) -> #N/A
A35: =IF(B35<>"",ROW()-1,"") -> 34 | B35: MOUSE | C35: Damaged | D35: =INDEX(Employee!E:E,MATCH(AK35,Employee!B:B,0)) -> 0 | E35: =INDEX(Employee!F:F,MATCH(AK35,Employee!B:B,0)) -> Tech | F35: =INDEX(Employee!G:G,MATCH(AK35,Employee!B:B,0)) -> 0 | G35: HCM | H35: MOU15039 | I35: MOU0010 | J35: Logitech | K35: Logitech M221 | N35: FALSE | O35: FALSE | Q35: 44742 | R35: VNG | S35: 19500 | AF35: =INDEX(Employee!C:C,MATCH(AG35,Employee!B:B,0)) -> Nguyễn Viết Khải | AG35: khainv | AH35: =INDEX(Employee!D:D,MATCH(AG35,Employee!B:B,0)) -> Lead IT Support Engineer | AI35: =INDEX(Employee!F:F,MATCH(AG35,Employee!B:B,0)) -> Tech | AJ35: =INDEX(Employee!C:C,MATCH(AK35,Employee!B:B,0)) -> Nguyễn Hoài Nam | AK35: namnh17 | AL35: =INDEX(Employee!D:D,MATCH(AK35,Employee!B:B,0)) -> Technical Support Engineer | AM35: =INDEX(Employee!F:F,MATCH(AK35,Employee!B:B,0)) -> Tech | AN35: =INDEX(Employee!H:H,MATCH(AK35,Employee!B:B,0)) -> Nguyễn Tấn Thơ (thont2)
A36: =IF(B36<>"",ROW()-1,"") -> 35 | B36: LAPTOP | C36: In Use | D36: =INDEX(Employee!E:E,MATCH(AK36,Employee!B:B,0)) -> 0 | E36: =INDEX(Employee!F:F,MATCH(AK36,Employee!B:B,0)) -> HR | F36: =INDEX(Employee!G:G,MATCH(AK36,Employee!B:B,0)) -> 0 | G36: IPL | H36: LAP15265 | I36: LAP0024 | J36: Lenovo | K36: Lenovo ThinkPad T14 i5 16GB | 256GB | L36: i5 | M36: =RIGHT(K36,5) -> 256GB | N36: FALSE | O36: TRUE | P36: PF3HLE92 | Q36: 44642 | R36: VNG | S36: 2516700 | AF36: =INDEX(Employee!C:C,MATCH(AG36,Employee!B:B,0)) -> Nguyễn Viết Khải | AG36: khainv | AH36: =INDEX(Employee!D:D,MATCH(AG36,Employee!B:B,0)) -> Lead IT Support Engineer | AI36: =INDEX(Employee!F:F,MATCH(AG36,Employee!B:B,0)) -> Tech | AJ36: =INDEX(Employee!C:C,MATCH(AK36,Employee!B:B,0)) -> Văn Tiến Đạt | AK36: datvt10 | AL36: =INDEX(Employee!D:D,MATCH(AK36,Employee!B:B,0)) -> Senior Talent Acquisition Business Partner | AM36: =INDEX(Employee!F:F,MATCH(AK36,Employee!B:B,0)) -> HR | AN36: =INDEX(Employee!H:H,MATCH(AK36,Employee!B:B,0)) -> Aleksandar Jelic (jelica)
A37: =IF(B37<>"",ROW()-1,"") -> 36 | B37: MOUSE | C37: Damaged | D37: =INDEX(Employee!E:E,MATCH(AK37,Employee!B:B,0)) -> #N/A | E37: =INDEX(Employee!F:F,MATCH(AK37,Employee!B:B,0)) -> #N/A | F37: =INDEX(Employee!G:G,MATCH(AK37,Employee!B:B,0)) -> #N/A | G37: HCM | I37: MOU0011 | J37: Logitech | K37: Logitech M221 | N37: FALSE | O37: FALSE | P37: 233LZXHVM388 | Q37: 44742 | R37: VNG | S37: 19500 | AF37: =INDEX(Employee!C:C,MATCH(AG37,Employee!B:B,0)) -> Nguyễn Viết Khải | AG37: khainv | AH37: =INDEX(Employee!D:D,MATCH(AG37,Employee!B:B,0)) -> Lead IT Support Engineer | AI37: =INDEX(Employee!F:F,MATCH(AG37,Employee!B:B,0)) -> Tech | AJ37: =INDEX(Employee!C:C,MATCH(AK37,Employee!B:B,0)) -> #N/A | AL37: =INDEX(Employee!D:D,MATCH(AK37,Employee!B:B,0)) -> #N/A | AM37: =INDEX(Employee!F:F,MATCH(AK37,Employee!B:B,0)) -> #N/A | AN37: =INDEX(Employee!H:H,MATCH(AK37,Employee!B:B,0)) -> #N/A
A38: =IF(B38<>"",ROW()-1,"") -> 37 | B38: MOUSE | C38: Damaged | D38: =INDEX(Employee!E:E,MATCH(AK38,Employee!B:B,0)) -> Project | E38: =INDEX(Employee!F:F,MATCH(AK38,Employee!B:B,0)) -> Tech | F38: =INDEX(Employee!G:G,MATCH(AK38,Employee!B:B,0)) -> Venture | G38: HCM | I38: MOU0012 | J38: Logitech | K38: Logitech M221 | N38: FALSE | O38: FALSE | P38: 2332LZXB7YW8 | Q38: 44792 | R38: VNG | S38: 20500 | AF38: =INDEX(Employee!C:C,MATCH(AG38,Employee!B:B,0)) -> Nguyễn Viết Khải | AG38: khainv | AH38: =INDEX(Employee!D:D,MATCH(AG38,Employee!B:B,0)) -> Lead IT Support Engineer | AI38: =INDEX(Employee!F:F,MATCH(AG38,Employee!B:B,0)) -> Tech | AJ38: =INDEX(Employee!C:C,MATCH(AK38,Employee!B:B,0)) -> Trịnh Minh Toàn | AK38: toantm3 | AL38: =INDEX(Employee!D:D,MATCH(AK38,Employee!B:B,0)) -> Senior Software Engineer | AM38: =INDEX(Employee!F:F,MATCH(AK38,Employee!B:B,0)) -> Tech | AN38: =INDEX(Employee!H:H,MATCH(AK38,Employee!B:B,0)) -> Đoàn Nhật Duẩn (duandn)
A39: =IF(B39<>"",ROW()-1,"") -> 38 | B39: LAPTOP | C39: Damaged | D39: =INDEX(Employee!E:E,MATCH(AK39,Employee!B:B,0)) -> #N/A | E39: =INDEX(Employee!F:F,MATCH(AK39,Employee!B:B,0)) -> #N/A | F39: =INDEX(Employee!G:G,MATCH(AK39,Employee!B:B,0)) -> #N/A | G39: HCM | I39: LAP0025 | J39: Lenovo | K39: Lenovo ThinkPad T14 i5 16GB | 256GB | L39: i5 | M39: =RIGHT(K39,5) -> 256GB | N39: TRUE | O39: FALSE | P39: PF2GNJE7 | Q39: 44409 | R39: VNG | S39: 2543220 | AF39: =INDEX(Employee!C:C,MATCH(AG39,Employee!B:B,0)) -> Nguyễn Viết Khải | AG39: khainv | AH39: =INDEX(Employee!D:D,MATCH(AG39,Employee!B:B,0)) -> Lead IT Support Engineer | AI39: =INDEX(Employee!F:F,MATCH(AG39,Employee!B:B,0)) -> Tech | AJ39: =INDEX(Employee!C:C,MATCH(AK39,Employee!B:B,0)) -> #N/A | AL39: =INDEX(Employee!D:D,MATCH(AK39,Employee!B:B,0)) -> #N/A | AM39: =INDEX(Employee!F:F,MATCH(AK39,Employee!B:B,0)) -> #N/A | AN39: =INDEX(Employee!H:H,MATCH(AK39,Employee!B:B,0)) -> #N/A | AQ39: Màn hình chớp
A40: =IF(B40<>"",ROW()-1,"") -> 39 | B40: MOUSE | C40: In Use | D40: =INDEX(Employee!E:E,MATCH(AK40,Employee!B:B,0)) -> BO | E40: =INDEX(Employee!F:F,MATCH(AK40,Employee!B:B,0)) -> Business Support | F40: =INDEX(Employee!G:G,MATCH(AK40,Employee!B:B,0)) -> Operation Team | G40: HCM | I40: MOU0013 | J40: Logitech | K40: Logitech M221 | N40: FALSE | O40: FALSE | Q40: 45107 | R40: VNG | S40: 19300 | AF40: =INDEX(Employee!C:C,MATCH(AG40,Employee!B:B,0)) -> Nguyễn Viết Khải | AG40: khainv | AH40: =INDEX(Employee!D:D,MATCH(AG40,Employee!B:B,0)) -> Lead IT Support Engineer | AI40: =INDEX(Employee!F:F,MATCH(AG40,Employee!B:B,0)) -> Tech | AJ40: =INDEX(Employee!C:C,MATCH(AK40,Employee!B:B,0)) -> Trương Nữ Ngọc Mai | AK40: maitnn | AL40: =INDEX(Employee!D:D,MATCH(AK40,Employee!B:B,0)) -> Admin Executive | AM40: =INDEX(Employee!F:F,MATCH(AK40,Employee!B:B,0)) -> Business Support | AN40: =INDEX(Employee!H:H,MATCH(AK40,Employee!B:B,0)) -> Đoàn Hà Mi
A41: =IF(B41<>"",ROW()-1,"") -> 40 | B41: LAPTOP | C41: In Stock | D41: =INDEX(Employee!E:E,MATCH(AK41,Employee!B:B,0)) -> #N/A | E41: =INDEX(Employee!F:F,MATCH(AK41,Employee!B:B,0)) -> #N/A | F41: =INDEX(Employee!G:G,MATCH(AK41,Employee!B:B,0)) -> #N/A | G41: HCM | I41: LAP0026 | J41: Lenovo | K41: Lenovo ThinkPad T14 i5 16GB | 256GB | L41: i5 | M41: =RIGHT(K41,5) -> 256GB | N41: TRUE | O41: FALSE | P41: PF4TGZ8E | Q41: 45308 | R41: VNG | S41: 22203518 | AF41: =INDEX(Employee!C:C,MATCH(AG41,Employee!B:B,0)) -> Nguyễn Viết Khải | AG41: khainv | AH41: =INDEX(Employee!D:D,MATCH(AG41,Employee!B:B,0)) -> Lead IT Support Engineer | AI41: =INDEX(Employee!F:F,MATCH(AG41,Employee!B:B,0)) -> Tech | AJ41: =INDEX(Employee!C:C,MATCH(AK41,Employee!B:B,0)) -> #N/A | AL41: =INDEX(Employee!D:D,MATCH(AK41,Employee!B:B,0)) -> #N/A | AM41: =INDEX(Employee!F:F,MATCH(AK41,Employee!B:B,0)) -> #N/A | AN41: =INDEX(Employee!H:H,MATCH(AK41,Employee!B:B,0)) -> #N/A
A42: =IF(B42<>"",ROW()-1,"") -> 41 | B42: LAPTOP | C42: In Use | D42: =INDEX(Employee!E:E,MATCH(AK42,Employee!B:B,0)) -> BO | E42: =INDEX(Employee!F:F,MATCH(AK42,Employee!B:B,0)) -> Business Support | F42: =INDEX(Employee!G:G,MATCH(AK42,Employee!B:B,0)) -> Operation Team | G42: HCM | I42: =IF(I41="","", "LAP"&TEXT(VALUE(RIGHT(I41,4))+1,"0000")) -> LAP0027 | J42: Apple | K42: Macbook Pro M2 16GB | 256GB | L42: M2 | M42: =RIGHT(K42,5) -> 256GB | N42: TRUE | O42: FALSE | P42: L4DQY59FQM | Q42: 44844 | R42: VNG | S42: 9123288 | AF42: =INDEX(Employee!C:C,MATCH(AG42,Employee!B:B,0)) -> Nguyễn Viết Khải | AG42: khainv | AH42: =INDEX(Employee!D:D,MATCH(AG42,Employee!B:B,0)) -> Lead IT Support Engineer | AI42: =INDEX(Employee!F:F,MATCH(AG42,Employee!B:B,0)) -> Tech | AJ42: =INDEX(Employee!C:C,MATCH(AK42,Employee!B:B,0)) -> Mai Thị Cẩm Hà | AK42: hamtc | AL42: =INDEX(Employee!D:D,MATCH(AK42,Employee!B:B,0)) -> Associate GRC Analyst | AM42: =INDEX(Employee!F:F,MATCH(AK42,Employee!B:B,0)) -> Business Support | AN42: =INDEX(Employee!H:H,MATCH(AK42,Employee!B:B,0)) -> Nguyễn Thị My Sa
A43: 50 | B43: LAPTOP | C43: In Use | D43: =INDEX(Employee!E:E,MATCH(AK43,Employee!B:B,0)) -> 0 | E43: =INDEX(Employee!F:F,MATCH(AK43,Employee!B:B,0)) -> Data | F43: =INDEX(Employee!G:G,MATCH(AK43,Employee!B:B,0)) -> 0 | G43: IPL | I43: =IF(I42="","", "LAP"&TEXT(VALUE(RIGHT(I42,4))+1,"0000")) -> LAP0028 | J43: Lenovo | K43: Lenovo ThinkPad T14 i5 32GB | 256GB | L43: i5 | M43: =RIGHT(K43,5) -> 256GB | N43: FALSE | O43: FALSE | P43: PF50YGFJ | Q43: 45308 | R43: VNG | S43: 22203518 | AF43: =INDEX(Employee!C:C,MATCH(AG43,Employee!B:B,0)) -> Nguyễn Viết Khải | AG43: khainv | AH43: =INDEX(Employee!D:D,MATCH(AG43,Employee!B:B,0)) -> Lead IT Support Engineer | AI43: =INDEX(Employee!F:F,MATCH(AG43,Employee!B:B,0)) -> Tech | AJ43: =INDEX(Employee!C:C,MATCH(AK43,Employee!B:B,0)) -> Huỳnh Quốc Quân | AK43: quanhq | AL43: =INDEX(Employee!D:D,MATCH(AK43,Employee!B:B,0)) -> Senior Database Administrator | AM43: =INDEX(Employee!F:F,MATCH(AK43,Employee!B:B,0)) -> Data | AN43: =INDEX(Employee!H:H,MATCH(AK43,Employee!B:B,0)) -> Dương Huỳnh Nghĩa (nghiadh)
A44: =IF(B44<>"",ROW()-1,"") -> 43 | B44: LAPTOP | C44: In Stock | D44: =INDEX(Employee!E:E,MATCH(AK44,Employee!B:B,0)) -> #N/A | E44: =INDEX(Employee!F:F,MATCH(AK44,Employee!B:B,0)) -> #N/A | F44: =INDEX(Employee!G:G,MATCH(AK44,Employee!B:B,0)) -> #N/A | G44: HN | I44: =IF(I43="","", "LAP"&TEXT(VALUE(RIGHT(I43,4))+1,"0000")) -> LAP0029 | J44: Apple | K44: Macbook Pro M3 16GB | 512GB | L44: M3 | M44: =RIGHT(K44,5) -> 512GB | N44: TRUE | O44: FALSE | P44: C9VG4L2X6V | Q44: 45315 | R44: VNG | S44: 25551416 | AF44: =INDEX(Employee!C:C,MATCH(AG44,Employee!B:B,0)) -> Nguyễn Viết Khải | AG44: khainv | AH44: =INDEX(Employee!D:D,MATCH(AG44,Employee!B:B,0)) -> Lead IT Support Engineer | AI44: =INDEX(Employee!F:F,MATCH(AG44,Employee!B:B,0)) -> Tech | AJ44: =INDEX(Employee!C:C,MATCH(AK44,Employee!B:B,0)) -> #N/A | AL44: =INDEX(Employee!D:D,MATCH(AK44,Employee!B:B,0)) -> #N/A | AM44: =INDEX(Employee!F:F,MATCH(AK44,Employee!B:B,0)) -> #N/A | AN44: =INDEX(Employee!H:H,MATCH(AK44,Employee!B:B,0)) -> #N/A
A45: =IF(B45<>"",ROW()-1,"") -> 44 | B45: LAPTOP | C45: In Stock | D45: =INDEX(Employee!E:E,MATCH(AK45,Employee!B:B,0)) -> #N/A | E45: =INDEX(Employee!F:F,MATCH(AK45,Employee!B:B,0)) -> #N/A | F45: =INDEX(Employee!G:G,MATCH(AK45,Employee!B:B,0)) -> #N/A | G45: HCM | I45: =IF(I44="","", "LAP"&TEXT(VALUE(RIGHT(I44,4))+1,"0000")) -> LAP0030 | J45: Apple | K45: Macbook Pro i5 16GB | 256GB | L45: i5 | M45: =RIGHT(K45,5) -> 256GB | N45: TRUE | O45: FALSE | P45: FVFC31E9L414 | Q45: 43879 | R45: VNG | S45: 3727273 | AF45: =INDEX(Employee!C:C,MATCH(AG45,Employee!B:B,0)) -> Nguyễn Viết Khải | AG45: khainv | AH45: =INDEX(Employee!D:D,MATCH(AG45,Employee!B:B,0)) -> Lead IT Support Engineer | AI45: =INDEX(Employee!F:F,MATCH(AG45,Employee!B:B,0)) -> Tech | AJ45: =INDEX(Employee!C:C,MATCH(AK45,Employee!B:B,0)) -> #N/A | AL45: =INDEX(Employee!D:D,MATCH(AK45,Employee!B:B,0)) -> #N/A | AM45: =INDEX(Employee!F:F,MATCH(AK45,Employee!B:B,0)) -> #N/A | AN45: =INDEX(Employee!H:H,MATCH(AK45,Employee!B:B,0)) -> #N/A
A46: =IF(B46<>"",ROW()-1,"") -> 45 | B46: LAPTOP | C46: In Use | D46: =INDEX(Employee!E:E,MATCH(AK46,Employee!B:B,0)) -> Project | E46: =INDEX(Employee!F:F,MATCH(AK46,Employee!B:B,0)) -> Data | F46: =INDEX(Employee!G:G,MATCH(AK46,Employee!B:B,0)) -> Resource Pool | G46: HCM | I46: =IF(I45="","", "LAP"&TEXT(VALUE(RIGHT(I45,4))+1,"0000")) -> LAP0031 | J46: Apple | K46: Macbook Pro M1 16GB | 256GB | L46: M1 | M46: =RIGHT(K46,5) -> 256GB | N46: TRUE | O46: FALSE | P46: FVFHQ8Q1Q05N | Q46: 44748 | R46: VNG | S46: 6135245 | AF46: =INDEX(Employee!C:C,MATCH(AG46,Employee!B:B,0)) -> Nguyễn Viết Khải | AG46: khainv | AH46: =INDEX(Employee!D:D,MATCH(AG46,Employee!B:B,0)) -> Lead IT Support Engineer | AI46: =INDEX(Employee!F:F,MATCH(AG46,Employee!B:B,0)) -> Tech | AJ46: =INDEX(Employee!C:C,MATCH(AK46,Employee!B:B,0)) -> Phạm Bằng | AK46: bangp | AL46: =INDEX(Employee!D:D,MATCH(AK46,Employee!B:B,0)) -> Fresher Data Engineer | AM46: =INDEX(Employee!F:F,MATCH(AK46,Employee!B:B,0)) -> Data | AN46: =INDEX(Employee!H:H,MATCH(AK46,Employee!B:B,0)) -> Đoàn Hải Nam
A47: =IF(B47<>"",ROW()-1,"") -> 46 | B47: LAPTOP | C47: In Stock | D47: =INDEX(Employee!E:E,MATCH(AK47,Employee!B:B,0)) -> #N/A | E47: =INDEX(Employee!F:F,MATCH(AK47,Employee!B:B,0)) -> #N/A | F47: =INDEX(Employee!G:G,MATCH(AK47,Employee!B:B,0)) -> #N/A | G47: HCM | I47: =IF(I46="","", "LAP"&TEXT(VALUE(RIGHT(I46,4))+1,"0000")) -> LAP0032 | J47: Lenovo | K47: Lenovo ThinkPad T14 i5 16GB | 256GB | L47: i5 | M47: =RIGHT(K47,5) -> 256GB | N47: TRUE | O47: TRUE | P47: PF3HLEA1 | Q47: 44642 | R47: VNG | S47: 2512400 | AF47: =INDEX(Employee!C:C,MATCH(AG47,Employee!B:B,0)) -> Nguyễn Viết Khải | AG47: khainv | AH47: =INDEX(Employee!D:D,MATCH(AG47,Employee!B:B,0)) -> Lead IT Support Engineer | AI47: =INDEX(Employee!F:F,MATCH(AG47,Employee!B:B,0)) -> Tech | AJ47: =INDEX(Employee!C:C,MATCH(AK47,Employee!B:B,0)) -> #N/A | AL47: =INDEX(Employee!D:D,MATCH(AK47,Employee!B:B,0)) -> #N/A | AM47: =INDEX(Employee!F:F,MATCH(AK47,Employee!B:B,0)) -> #N/A | AN47: =INDEX(Employee!H:H,MATCH(AK47,Employee!B:B,0)) -> #N/A
A48: =IF(B48<>"",ROW()-1,"") -> 47 | B48: MOUSE | C48: In Stock | D48: =INDEX(Employee!E:E,MATCH(AK48,Employee!B:B,0)) -> #N/A | E48: =INDEX(Employee!F:F,MATCH(AK48,Employee!B:B,0)) -> #N/A | F48: =INDEX(Employee!G:G,MATCH(AK48,Employee!B:B,0)) -> #N/A | G48: HCM | I48: MOU0014 | J48: Logitech | K48: Logitech M221 | N48: FALSE | O48: FALSE | P48: 2514AP37FJNB | Q48: 45107 | R48: VNG | S48: 19300 | AF48: =INDEX(Employee!C:C,MATCH(AG48,Employee!B:B,0)) -> Nguyễn Viết Khải | AG48: khainv | AH48: =INDEX(Employee!D:D,MATCH(AG48,Employee!B:B,0)) -> Lead IT Support Engineer | AI48: =INDEX(Employee!F:F,MATCH(AG48,Employee!B:B,0)) -> Tech | AJ48: =INDEX(Employee!C:C,MATCH(AK48,Employee!B:B,0)) -> #N/A | AL48: =INDEX(Employee!D:D,MATCH(AK48,Employee!B:B,0)) -> #N/A | AM48: =INDEX(Employee!F:F,MATCH(AK48,Employee!B:B,0)) -> #N/A | AN48: =INDEX(Employee!H:H,MATCH(AK48,Employee!B:B,0)) -> #N/A
A49: =IF(B49<>"",ROW()-1,"") -> 48 | B49: LAPTOP | C49: In Stock | D49: =INDEX(Employee!E:E,MATCH(AK49,Employee!B:B,0)) -> #N/A | E49: =INDEX(Employee!F:F,MATCH(AK49,Employee!B:B,0)) -> #N/A | F49: =INDEX(Employee!G:G,MATCH(AK49,Employee!B:B,0)) -> #N/A | G49: HCM | I49: LAP0033 | J49: Lenovo | K49: Lenovo ThinkPad T14 i5 16GB | 256GB | L49: i5 | M49: =RIGHT(K49,5) -> 256GB | N49: TRUE | O49: TRUE | P49: PF24WRQA | Q49: 44145 | R49: VNG | S49: 2553000 | AF49: =INDEX(Employee!C:C,MATCH(AG49,Employee!B:B,0)) -> Nguyễn Viết Khải | AG49: khainv | AH49: =INDEX(Employee!D:D,MATCH(AG49,Employee!B:B,0)) -> Lead IT Support Engineer | AI49: =INDEX(Employee!F:F,MATCH(AG49,Employee!B:B,0)) -> Tech | AJ49: =INDEX(Employee!C:C,MATCH(AK49,Employee!B:B,0)) -> #N/A | AL49: =INDEX(Employee!D:D,MATCH(AK49,Employee!B:B,0)) -> #N/A | AM49: =INDEX(Employee!F:F,MATCH(AK49,Employee!B:B,0)) -> #N/A | AN49: =INDEX(Employee!H:H,MATCH(AK49,Employee!B:B,0)) -> #N/A
A50: =IF(B50<>"",ROW()-1,"") -> 49 | B50: LAPTOP | C50: In Use | D50: =INDEX(Employee!E:E,MATCH(AK50,Employee!B:B,0)) -> AM | E50: =INDEX(Employee!F:F,MATCH(AK50,Employee!B:B,0)) -> Sales | F50: =INDEX(Employee!G:G,MATCH(AK50,Employee!B:B,0)) -> Resource Pool | G50: HCM | H50: LAP16385 | I50: =IF(I49="","", "LAP"&TEXT(VALUE(RIGHT(I49,4))+1,"0000")) -> LAP0034 | J50: Lenovo | K50: Lenovo ThinkPad T14 i5 16GB | 256GB | L50: i5 | M50: =RIGHT(K50,5) -> 256GB | N50: TRUE | O50: TRUE | P50: PF50YBXD | Q50: 45420 | R50: VNG | S50: 25413973 | AF50: =INDEX(Employee!C:C,MATCH(AG50,Employee!B:B,0)) -> Nguyễn Viết Khải | AG50: khainv | AH50: =INDEX(Employee!D:D,MATCH(AG50,Employee!B:B,0)) -> Lead IT Support Engineer | AI50: =INDEX(Employee!F:F,MATCH(AG50,Employee!B:B,0)) -> Tech | AJ50: =INDEX(Employee!C:C,MATCH(AK50,Employee!B:B,0)) -> Bùi Tuấn Huy | AK50: huybt | AL50: =INDEX(Employee!D:D,MATCH(AK50,Employee!B:B,0)) -> Regional Business Manager | AM50: =INDEX(Employee!F:F,MATCH(AK50,Employee!B:B,0)) -> Sales | AN50: =INDEX(Employee!H:H,MATCH(AK50,Employee!B:B,0)) -> Đoàn Hải Nam
A51: =IF(B51<>"",ROW()-1,"") -> 50 | B51: LAPTOP | C51: Lost | D51: =INDEX(Employee!E:E,MATCH(AK51,Employee!B:B,0)) -> 0 | E51: =INDEX(Employee!F:F,MATCH(AK51,Employee!B:B,0)) -> Data | F51: =INDEX(Employee!G:G,MATCH(AK51,Employee!B:B,0)) -> 0 | G51: IPL | I51: =IF(I50="","", "LAP"&TEXT(VALUE(RIGHT(I50,4))+1,"0000")) -> LAP0035 | J51: Apple | K51: Macbook Pro M1 16GB | 256GB | L51: M1 | M51: =RIGHT(K51,5) -> 256GB | N51: FALSE | O51: FALSE | P51: C02GH244Q05N | Q51: 44495 | R51: VNG | S51: 3300000 | AF51: =INDEX(Employee!C:C,MATCH(AG51,Employee!B:B,0)) -> Nguyễn Viết Khải | AG51: khainv | AH51: =INDEX(Employee!D:D,MATCH(AG51,Employee!B:B,0)) -> Lead IT Support Engineer | AI51: =INDEX(Employee!F:F,MATCH(AG51,Employee!B:B,0)) -> Tech | AJ51: =INDEX(Employee!C:C,MATCH(AK51,Employee!B:B,0)) -> Trần Huyền Thanh | AK51: thanhth5 | AL51: =INDEX(Employee!D:D,MATCH(AK51,Employee!B:B,0)) -> Data Specialist | AM51: =INDEX(Employee!F:F,MATCH(AK51,Employee!B:B,0)) -> Data | AN51: =INDEX(Employee!H:H,MATCH(AK51,Employee!B:B,0)) -> Aleksandar Jelic (jelica)
A52: =IF(B52<>"",ROW()-1,"") -> 51 | B52: LAPTOP | C52: In Stock | D52: =INDEX(Employee!E:E,MATCH(AK52,Employee!B:B,0)) -> #N/A | E52: =INDEX(Employee!F:F,MATCH(AK52,Employee!B:B,0)) -> #N/A | F52: =INDEX(Employee!G:G,MATCH(AK52,Employee!B:B,0)) -> #N/A | G52: HCM | I52: =IF(I51="","", "LAP"&TEXT(VALUE(RIGHT(I51,4))+1,"0000")) -> LAP0036 | J52: Lenovo | K52: Lenovo ThinkPad T14 i5 16GB | 256GB | L52: i5 | M52: =RIGHT(K52,5) -> 256GB | N52: TRUE | O52: TRUE | P52: PF50Z44H | Q52: 45420 | R52: VNG | S52: 25413973 | AF52: =INDEX(Employee!C:C,MATCH(AG52,Employee!B:B,0)) -> Nguyễn Viết Khải | AG52: khainv | AH52: =INDEX(Employee!D:D,MATCH(AG52,Employee!B:B,0)) -> Lead IT Support Engineer | AI52: =INDEX(Employee!F:F,MATCH(AG52,Employee!B:B,0)) -> Tech | AJ52: =INDEX(Employee!C:C,MATCH(AK52,Employee!B:B,0)) -> #N/A | AL52: =INDEX(Employee!D:D,MATCH(AK52,Employee!B:B,0)) -> #N/A | AM52: =INDEX(Employee!F:F,MATCH(AK52,Employee!B:B,0)) -> #N/A | AN52: =INDEX(Employee!H:H,MATCH(AK52,Employee!B:B,0)) -> #N/A | AS52: doandtt
A53: =IF(B53<>"",ROW()-1,"") -> 52 | B53: LAPTOP | C53: In Stock | D53: =INDEX(Employee!E:E,MATCH(AK53,Employee!B:B,0)) -> #N/A | E53: =INDEX(Employee!F:F,MATCH(AK53,Employee!B:B,0)) -> #N/A | F53: =INDEX(Employee!G:G,MATCH(AK53,Employee!B:B,0)) -> #N/A | G53: HCM | I53: =IF(I52="","", "LAP"&TEXT(VALUE(RIGHT(I52,4))+1,"0000")) -> LAP0037 | J53: Lenovo | K53: Lenovo ThinkPad X13 i5 16GB | 256GB | L53: i5 | M53: =RIGHT(K53,5) -> 256GB | N53: TRUE | O53: TRUE | P53: PC2CKMBD | Q53: 44680 | R53: VNG | S53: 2891557 | AF53: =INDEX(Employee!C:C,MATCH(AG53,Employee!B:B,0)) -> Nguyễn Viết Khải | AG53: khainv | AH53: =INDEX(Employee!D:D,MATCH(AG53,Employee!B:B,0)) -> Lead IT Support Engineer | AI53: =INDEX(Employee!F:F,MATCH(AG53,Employee!B:B,0)) -> Tech | AJ53: =INDEX(Employee!C:C,MATCH(AK53,Employee!B:B,0)) -> #N/A | AL53: =INDEX(Employee!D:D,MATCH(AK53,Employee!B:B,0)) -> #N/A | AM53: =INDEX(Employee!F:F,MATCH(AK53,Employee!B:B,0)) -> #N/A | AN53: =INDEX(Employee!H:H,MATCH(AK53,Employee!B:B,0)) -> #N/A
A54: =IF(B54<>"",ROW()-1,"") -> 53 | B54: LAPTOP | C54: In Stock | D54: =INDEX(Employee!E:E,MATCH(AK54,Employee!B:B,0)) -> #N/A | E54: =INDEX(Employee!F:F,MATCH(AK54,Employee!B:B,0)) -> #N/A | F54: =INDEX(Employee!G:G,MATCH(AK54,Employee!B:B,0)) -> #N/A | G54: HCM | I54: =IF(I53="","", "LAP"&TEXT(VALUE(RIGHT(I53,4))+1,"0000")) -> LAP0038 | J54: Lenovo | K54: Lenovo ThinkPad T14 i5 16GB | 256GB | L54: i5 | M54: =RIGHT(K54,5) -> 256GB | N54: TRUE | O54: FALSE | P54: PF30QSZV | Q54: 44475 | R54: VNG | S54: 2508000 | AF54: =INDEX(Employee!C:C,MATCH(AG54,Employee!B:B,0)) -> Nguyễn Viết Khải | AG54: khainv | AH54: =INDEX(Employee!D:D,MATCH(AG54,Employee!B:B,0)) -> Lead IT Support Engineer | AI54: =INDEX(Employee!F:F,MATCH(AG54,Employee!B:B,0)) -> Tech | AJ54: =INDEX(Employee!C:C,MATCH(AK54,Employee!B:B,0)) -> #N/A | AL54: =INDEX(Employee!D:D,MATCH(AK54,Employee!B:B,0)) -> #N/A | AM54: =INDEX(Employee!F:F,MATCH(AK54,Employee!B:B,0)) -> #N/A | AN54: =INDEX(Employee!H:H,MATCH(AK54,Employee!B:B,0)) -> #N/A
A55: =IF(B55<>"",ROW()-1,"") -> 54 | B55: LAPTOP | C55: In Stock | D55: =INDEX(Employee!E:E,MATCH(AK55,Employee!B:B,0)) -> #N/A | E55: =INDEX(Employee!F:F,MATCH(AK55,Employee!B:B,0)) -> #N/A | F55: =INDEX(Employee!G:G,MATCH(AK55,Employee!B:B,0)) -> #N/A | G55: HCM | I55: =IF(I54="","", "LAP"&TEXT(VALUE(RIGHT(I54,4))+1,"0000")) -> LAP0039 | J55: Lenovo | K55: Lenovo ThinkPad E14 i5 16GB | 256GB | L55: i5 | M55: =RIGHT(K55,5) -> 256GB | N55: TRUE | O55: FALSE | P55: PF3SHFA1 | Q55: 44743 | R55: VNG | S55: 2988335 | AF55: =INDEX(Employee!C:C,MATCH(AG55,Employee!B:B,0)) -> Nguyễn Viết Khải | AG55: khainv | AH55: =INDEX(Employee!D:D,MATCH(AG55,Employee!B:B,0)) -> Lead IT Support Engineer | AI55: =INDEX(Employee!F:F,MATCH(AG55,Employee!B:B,0)) -> Tech | AJ55: =INDEX(Employee!C:C,MATCH(AK55,Employee!B:B,0)) -> #N/A | AL55: =INDEX(Employee!D:D,MATCH(AK55,Employee!B:B,0)) -> #N/A | AM55: =INDEX(Employee!F:F,MATCH(AK55,Employee!B:B,0)) -> #N/A | AN55: =INDEX(Employee!H:H,MATCH(AK55,Employee!B:B,0)) -> #N/A
A56: =IF(B56<>"",ROW()-1,"") -> 55 | B56: LAPTOP | C56: In Use | D56: =INDEX(Employee!E:E,MATCH(AK56,Employee!B:B,0)) -> 0 | E56: =INDEX(Employee!F:F,MATCH(AK56,Employee!B:B,0)) -> Tech | F56: =INDEX(Employee!G:G,MATCH(AK56,Employee!B:B,0)) -> 0 | G56: IPL | I56: =IF(I55="","", "LAP"&TEXT(VALUE(RIGHT(I55,4))+1,"0000")) -> LAP0040 | J56: Apple | K56: Macbook Pro M2 16GB | 256GB | L56: M2 | M56: =RIGHT(K56,5) -> 256GB | N56: FALSE | O56: FALSE | P56: J34WGQ672R | Q56: 44844 | R56: VNG | S56: 24710000 | AF56: =INDEX(Employee!C:C,MATCH(AG56,Employee!B:B,0)) -> Nguyễn Viết Khải | AG56: khainv | AH56: =INDEX(Employee!D:D,MATCH(AG56,Employee!B:B,0)) -> Lead IT Support Engineer | AI56: =INDEX(Employee!F:F,MATCH(AG56,Employee!B:B,0)) -> Tech | AJ56: =INDEX(Employee!C:C,MATCH(AK56,Employee!B:B,0)) -> Nguyễn Hải Đăng | AK56: dangnh13 | AL56: =INDEX(Employee!D:D,MATCH(AK56,Employee!B:B,0)) -> Associate QC Engineer | AM56: =INDEX(Employee!F:F,MATCH(AK56,Employee!B:B,0)) -> Tech | AN56: =INDEX(Employee!H:H,MATCH(AK56,Employee!B:B,0)) -> Trịnh Trần Minh Tuấn (tuanttm)
A57: =IF(B57<>"",ROW()-1,"") -> 56 | B57: LAPTOP | C57: In Use | D57: =INDEX(Employee!E:E,MATCH(AK57,Employee!B:B,0)) -> BO | E57: =INDEX(Employee!F:F,MATCH(AK57,Employee!B:B,0)) -> Business Support | F57: =INDEX(Employee!G:G,MATCH(AK57,Employee!B:B,0)) -> Operation Team | G57: HCM | I57: =IF(I56="","", "LAP"&TEXT(VALUE(RIGHT(I56,4))+1,"0000")) -> LAP0041 | J57: Lenovo | K57: Lenovo ThinkPad T490 i5 16GB | 256GB | L57: i5 | M57: =RIGHT(K57,5) -> 256GB | N57: TRUE | O57: TRUE | P57: PF2B1BG0 | Q57: 44800 | R57: VNG | S57: 2565000 | AF57: =INDEX(Employee!C:C,MATCH(AG57,Employee!B:B,0)) -> Nguyễn Viết Khải | AG57: khainv | AH57: =INDEX(Employee!D:D,MATCH(AG57,Employee!B:B,0)) -> Lead IT Support Engineer | AI57: =INDEX(Employee!F:F,MATCH(AG57,Employee!B:B,0)) -> Tech | AJ57: =INDEX(Employee!C:C,MATCH(AK57,Employee!B:B,0)) -> Võ Lê Nguyên Khang | AK57: khangvln | AL57: =INDEX(Employee!D:D,MATCH(AK57,Employee!B:B,0)) -> Talent Acquisition Business Partner | AM57: =INDEX(Employee!F:F,MATCH(AK57,Employee!B:B,0)) -> Business Support | AN57: =INDEX(Employee!H:H,MATCH(AK57,Employee!B:B,0)) -> Nguyễn Thị My Sa
A58: =IF(B58<>"",ROW()-1,"") -> 57 | B58: MOUSE | C58: In Use | D58: =INDEX(Employee!E:E,MATCH(AK58,Employee!B:B,0)) -> Undirect IT Staff | E58: =INDEX(Employee!F:F,MATCH(AK58,Employee!B:B,0)) -> Tech | F58: =INDEX(Employee!G:G,MATCH(AK58,Employee!B:B,0)) -> Odoo | G58: HCM | I58: MOU0015 | J58: Logitech | K58: Logitech M221 | N58: FALSE | O58: FALSE | Q58: 45107 | R58: VNG | S58: 19300 | AF58: =INDEX(Employee!C:C,MATCH(AG58,Employee!B:B,0)) -> Nguyễn Viết Khải | AG58: khainv | AH58: =INDEX(Employee!D:D,MATCH(AG58,Employee!B:B,0)) -> Lead IT Support Engineer | AI58: =INDEX(Employee!F:F,MATCH(AG58,Employee!B:B,0)) -> Tech | AJ58: =INDEX(Employee!C:C,MATCH(AK58,Employee!B:B,0)) -> Đặng Thành Thái | AK58: thaidt | AL58: =INDEX(Employee!D:D,MATCH(AK58,Employee!B:B,0)) -> Software Engineer | AM58: =INDEX(Employee!F:F,MATCH(AK58,Employee!B:B,0)) -> Tech | AN58: =INDEX(Employee!H:H,MATCH(AK58,Employee!B:B,0)) -> Dương Phạm Thành Công (congdpt)
A59: =IF(B59<>"",ROW()-1,"") -> 58 | B59: LAPTOP | C59: In Stock | D59: =INDEX(Employee!E:E,MATCH(AK59,Employee!B:B,0)) -> #N/A | E59: =INDEX(Employee!F:F,MATCH(AK59,Employee!B:B,0)) -> #N/A | F59: =INDEX(Employee!G:G,MATCH(AK59,Employee!B:B,0)) -> #N/A | G59: HCM | I59: LAP0042 | J59: Apple | K59: Macbook Pro i5 16GB | 256GB | L59: i5 | M59: =RIGHT(K59,5) -> 256GB | N59: TRUE | O59: FALSE | P59: FVFZN0NNL414 | Q59: 43597 | R59: VNG | S59: 3754546 | AF59: =INDEX(Employee!C:C,MATCH(AG59,Employee!B:B,0)) -> Nguyễn Viết Khải | AG59: khainv | AH59: =INDEX(Employee!D:D,MATCH(AG59,Employee!B:B,0)) -> Lead IT Support Engineer | AI59: =INDEX(Employee!F:F,MATCH(AG59,Employee!B:B,0)) -> Tech | AJ59: =INDEX(Employee!C:C,MATCH(AK59,Employee!B:B,0)) -> #N/A | AL59: =INDEX(Employee!D:D,MATCH(AK59,Employee!B:B,0)) -> #N/A | AM59: =INDEX(Employee!F:F,MATCH(AK59,Employee!B:B,0)) -> #N/A | AN59: =INDEX(Employee!H:H,MATCH(AK59,Employee!B:B,0)) -> #N/A
A60: =IF(B60<>"",ROW()-1,"") -> 59 | B60: LAPTOP | C60: In Use | D60: =INDEX(Employee!E:E,MATCH(AK60,Employee!B:B,0)) -> 0 | E60: =INDEX(Employee!F:F,MATCH(AK60,Employee!B:B,0)) -> Tech | F60: =INDEX(Employee!G:G,MATCH(AK60,Employee!B:B,0)) -> 0 | G60: IPL | I60: =IF(I59="","", "LAP"&TEXT(VALUE(RIGHT(I59,4))+1,"0000")) -> LAP0043 | J60: Lenovo | K60: Lenovo ThinkPad T14 i5 16GB | 256GB | L60: i5 | M60: =RIGHT(K60,5) -> 256GB | N60: FALSE | O60: TRUE | P60: PF3HMH7N | Q60: 44642 | R60: VNG | S60: 2512400 | AF60: =INDEX(Employee!C:C,MATCH(AG60,Employee!B:B,0)) -> Nguyễn Viết Khải | AG60: khainv | AH60: =INDEX(Employee!D:D,MATCH(AG60,Employee!B:B,0)) -> Lead IT Support Engineer | AI60: =INDEX(Employee!F:F,MATCH(AG60,Employee!B:B,0)) -> Tech | AJ60: =INDEX(Employee!C:C,MATCH(AK60,Employee!B:B,0)) -> Trần Hải Trình | AK60: trinhth | AL60: =INDEX(Employee!D:D,MATCH(AK60,Employee!B:B,0)) -> Cloud Engineer | AM60: =INDEX(Employee!F:F,MATCH(AK60,Employee!B:B,0)) -> Tech | AN60: =INDEX(Employee!H:H,MATCH(AK60,Employee!B:B,0)) -> Nguyễn Hữu Hỷ (hynh)
A61: =IF(B61<>"",ROW()-1,"") -> 60 | B61: LAPTOP | C61: In Use | D61: =INDEX(Employee!E:E,MATCH(AK61,Employee!B:B,0)) -> 0 | E61: =INDEX(Employee!F:F,MATCH(AK61,Employee!B:B,0)) -> OP | F61: =INDEX(Employee!G:G,MATCH(AK61,Employee!B:B,0)) -> 0 | G61: IPL | I61: =IF(I60="","", "LAP"&TEXT(VALUE(RIGHT(I60,4))+1,"0000")) -> LAP0044 | J61: Apple | K61: Macbook Pro M1 16GB | 256GB | L61: M1 | M61: =RIGHT(K61,5) -> 256GB | N61: FALSE | O61: FALSE | P61: C02G12MBQ05N | Q61: 44466 | R61: VNG | S61: 3300000 | AF61: =INDEX(Employee!C:C,MATCH(AG61,Employee!B:B,0)) -> Nguyễn Viết Khải | AG61: khainv | AH61: =INDEX(Employee!D:D,MATCH(AG61,Employee!B:B,0)) -> Lead IT Support Engineer | AI61: =INDEX(Employee!F:F,MATCH(AG61,Employee!B:B,0)) -> Tech | AJ61: =INDEX(Employee!C:C,MATCH(AK61,Employee!B:B,0)) -> Nguyễn Cao Bách | AK61: bachnc | AL61: =INDEX(Employee!D:D,MATCH(AK61,Employee!B:B,0)) -> Site Reliability Engineer | AM61: =INDEX(Employee!F:F,MATCH(AK61,Employee!B:B,0)) -> OP | AN61: =INDEX(Employee!H:H,MATCH(AK61,Employee!B:B,0)) -> Trần Triệu Dương (duongtt5)
A62: =IF(B62<>"",ROW()-1,"") -> 61 | B62: LAPTOP | C62: In Stock | D62: =INDEX(Employee!E:E,MATCH(AK62,Employee!B:B,0)) -> #N/A | E62: =INDEX(Employee!F:F,MATCH(AK62,Employee!B:B,0)) -> #N/A | F62: =INDEX(Employee!G:G,MATCH(AK62,Employee!B:B,0)) -> #N/A | G62: HCM | I62: =IF(I61="","", "LAP"&TEXT(VALUE(RIGHT(I61,4))+1,"0000")) -> LAP0045 | J62: Lenovo | K62: Lenovo ThinkPad T14 i5 32GB | 256GB | L62: i5 | M62: =RIGHT(K62,5) -> 256GB | N62: TRUE | O62: FALSE | P62: PF2W96HB | Q62: 44489 | R62: VNG | S62: 2508000 | AF62: =INDEX(Employee!C:C,MATCH(AG62,Employee!B:B,0)) -> Nguyễn Viết Khải | AG62: khainv | AH62: =INDEX(Employee!D:D,MATCH(AG62,Employee!B:B,0)) -> Lead IT Support Engineer | AI62: =INDEX(Employee!F:F,MATCH(AG62,Employee!B:B,0)) -> Tech | AJ62: =INDEX(Employee!C:C,MATCH(AK62,Employee!B:B,0)) -> #N/A | AL62: =INDEX(Employee!D:D,MATCH(AK62,Employee!B:B,0)) -> #N/A | AM62: =INDEX(Employee!F:F,MATCH(AK62,Employee!B:B,0)) -> #N/A | AN62: =INDEX(Employee!H:H,MATCH(AK62,Employee!B:B,0)) -> #N/A
A63: =IF(B63<>"",ROW()-1,"") -> 62 | B63: LAPTOP | C63: In Use | D63: =INDEX(Employee!E:E,MATCH(AK63,Employee!B:B,0)) -> CTD | E63: =INDEX(Employee!F:F,MATCH(AK63,Employee!B:B,0)) -> CTD | F63: =INDEX(Employee!G:G,MATCH(AK63,Employee!B:B,0)) -> CTD | G63: HCM | H63: LAP15378 | I63: =IF(I62="","", "LAP"&TEXT(VALUE(RIGHT(I62,4))+1,"0000")) -> LAP0046 | J63: Lenovo | K63: Lenovo ThinkPad T14 i5 16GB | 256GB | L63: i5 | M63: =RIGHT(K63,5) -> 256GB | N63: TRUE | O63: TRUE | P63: PF3M70BL | Q63: 44671 | R63: VNG | S63: 2815891 | AF63: =INDEX(Employee!C:C,MATCH(AG63,Employee!B:B,0)) -> Nguyễn Viết Khải | AG63: khainv | AH63: =INDEX(Employee!D:D,MATCH(AG63,Employee!B:B,0)) -> Lead IT Support Engineer | AI63: =INDEX(Employee!F:F,MATCH(AG63,Employee!B:B,0)) -> Tech | AJ63: =INDEX(Employee!C:C,MATCH(AK63,Employee!B:B,0)) -> Nguyễn Nhã Minh | AK63: minhnn | AL63: =INDEX(Employee!D:D,MATCH(AK63,Employee!B:B,0)) -> Intern IT | AM63: =INDEX(Employee!F:F,MATCH(AK63,Employee!B:B,0)) -> CTD | AN63: =INDEX(Employee!H:H,MATCH(AK63,Employee!B:B,0)) -> 0
A64: =IF(B64<>"",ROW()-1,"") -> 63 | B64: LAPTOP | C64: In Stock | D64: =INDEX(Employee!E:E,MATCH(AK64,Employee!B:B,0)) -> #N/A | E64: =INDEX(Employee!F:F,MATCH(AK64,Employee!B:B,0)) -> #N/A | F64: =INDEX(Employee!G:G,MATCH(AK64,Employee!B:B,0)) -> #N/A | G64: HCM | I64: =IF(I63="","", "LAP"&TEXT(VALUE(RIGHT(I63,4))+1,"0000")) -> LAP0047 | J64: Lenovo | K64: Lenovo ThinkPad X13 i5 16GB | 256GB | L64: i5 | M64: =RIGHT(K64,5) -> 256GB | N64: TRUE | O64: FALSE | P64: PF41B7MC | Q64: 45096 | R64: VNG | S64: 13449501 | AF64: =INDEX(Employee!C:C,MATCH(AG64,Employee!B:B,0)) -> Nguyễn Viết Khải | AG64: khainv | AH64: =INDEX(Employee!D:D,MATCH(AG64,Employee!B:B,0)) -> Lead IT Support Engineer | AI64: =INDEX(Employee!F:F,MATCH(AG64,Employee!B:B,0)) -> Tech | AJ64: =INDEX(Employee!C:C,MATCH(AK64,Employee!B:B,0)) -> #N/A | AL64: =INDEX(Employee!D:D,MATCH(AK64,Employee!B:B,0)) -> #N/A | AM64: =INDEX(Employee!F:F,MATCH(AK64,Employee!B:B,0)) -> #N/A | AN64: =INDEX(Employee!H:H,MATCH(AK64,Employee!B:B,0)) -> #N/A
A65: =IF(B65<>"",ROW()-1,"") -> 64 | B65: LAPTOP | C65: In Stock | D65: =INDEX(Employee!E:E,MATCH(AK65,Employee!B:B,0)) -> #N/A | E65: =INDEX(Employee!F:F,MATCH(AK65,Employee!B:B,0)) -> #N/A | F65: =INDEX(Employee!G:G,MATCH(AK65,Employee!B:B,0)) -> #N/A | G65: HCM | H65: LAP13524 | I65: =IF(I64="","", "LAP"&TEXT(VALUE(RIGHT(I64,4))+1,"0000")) -> LAP0048 | J65: Apple | K65: Macbook Pro i5 16GB | 256GB | L65: i5 | M65: =RIGHT(K65,5) -> 256GB | N65: TRUE | O65: FALSE | P65: FVFC32J8L414 | Q65: 43879 | R65: VNG | S65: 3727273 | AF65: =INDEX(Employee!C:C,MATCH(AG65,Employee!B:B,0)) -> Nguyễn Viết Khải | AG65: khainv | AH65: =INDEX(Employee!D:D,MATCH(AG65,Employee!B:B,0)) -> Lead IT Support Engineer | AI65: =INDEX(Employee!F:F,MATCH(AG65,Employee!B:B,0)) -> Tech | AJ65: =INDEX(Employee!C:C,MATCH(AK65,Employee!B:B,0)) -> #N/A | AL65: =INDEX(Employee!D:D,MATCH(AK65,Employee!B:B,0)) -> #N/A | AM65: =INDEX(Employee!F:F,MATCH(AK65,Employee!B:B,0)) -> #N/A | AN65: =INDEX(Employee!H:H,MATCH(AK65,Employee!B:B,0)) -> #N/A
A66: =IF(B66<>"",ROW()-1,"") -> 65 | B66: LAPTOP | C66: In Stock | D66: =INDEX(Employee!E:E,MATCH(AK66,Employee!B:B,0)) -> #N/A | E66: =INDEX(Employee!F:F,MATCH(AK66,Employee!B:B,0)) -> #N/A | F66: =INDEX(Employee!G:G,MATCH(AK66,Employee!B:B,0)) -> #N/A | G66: HCM | H66: LAP60809 | I66: =IF(I65="","", "LAP"&TEXT(VALUE(RIGHT(I65,4))+1,"0000")) -> LAP0049 | J66: Apple | K66: Macbook Pro M1 16GB | 256GB | L66: M1 | M66: =RIGHT(K66,5) -> 256GB | N66: TRUE | O66: FALSE | P66: FVFHQ849Q05N | Q66: 44729 | R66: VNG | S66: 6550188 | AF66: =INDEX(Employee!C:C,MATCH(AG66,Employee!B:B,0)) -> Nguyễn Viết Khải | AG66: khainv | AH66: =INDEX(Employee!D:D,MATCH(AG66,Employee!B:B,0)) -> Lead IT Support Engineer | AI66: =INDEX(Employee!F:F,MATCH(AG66,Employee!B:B,0)) -> Tech | AJ66: =INDEX(Employee!C:C,MATCH(AK66,Employee!B:B,0)) -> #N/A | AL66: =INDEX(Employee!D:D,MATCH(AK66,Employee!B:B,0)) -> #N/A | AM66: =INDEX(Employee!F:F,MATCH(AK66,Employee!B:B,0)) -> #N/A | AN66: =INDEX(Employee!H:H,MATCH(AK66,Employee!B:B,0)) -> #N/A | AS66: tungnb
A67: =IF(B67<>"",ROW()-1,"") -> 66 | B67: LAPTOP | C67: In Stock | D67: =INDEX(Employee!E:E,MATCH(AK67,Employee!B:B,0)) -> #N/A | E67: =INDEX(Employee!F:F,MATCH(AK67,Employee!B:B,0)) -> #N/A | F67: =INDEX(Employee!G:G,MATCH(AK67,Employee!B:B,0)) -> #N/A | G67: HCM | I67: =IF(I66="","", "LAP"&TEXT(VALUE(RIGHT(I66,4))+1,"0000")) -> LAP0050 | J67: Lenovo | K67: Lenovo ThinkPad X13 i5 16GB | 256GB | L67: i5 | M67: =RIGHT(K67,5) -> 256GB | N67: TRUE | O67: TRUE | P67: PC1PQEFM | Q67: 44187 | R67: VNG | S67: 2625820 | AF67: =INDEX(Employee!C:C,MATCH(AG67,Employee!B:B,0)) -> Nguyễn Viết Khải | AG67: khainv | AH67: =INDEX(Employee!D:D,MATCH(AG67,Employee!B:B,0)) -> Lead IT Support Engineer | AI67: =INDEX(Employee!F:F,MATCH(AG67,Employee!B:B,0)) -> Tech | AJ67: =INDEX(Employee!C:C,MATCH(AK67,Employee!B:B,0)) -> #N/A | AL67: =INDEX(Employee!D:D,MATCH(AK67,Employee!B:B,0)) -> #N/A | AM67: =INDEX(Employee!F:F,MATCH(AK67,Employee!B:B,0)) -> #N/A | AN67: =INDEX(Employee!H:H,MATCH(AK67,Employee!B:B,0)) -> #N/A
A68: =IF(B68<>"",ROW()-1,"") -> 67 | B68: LAPTOP | C68: In Use | D68: =INDEX(Employee!E:E,MATCH(AK68,Employee!B:B,0)) -> 0 | E68: =INDEX(Employee!F:F,MATCH(AK68,Employee!B:B,0)) -> Tech | F68: =INDEX(Employee!G:G,MATCH(AK68,Employee!B:B,0)) -> 0 | G68: IPL | I68: =IF(I67="","", "LAP"&TEXT(VALUE(RIGHT(I67,4))+1,"0000")) -> LAP0051 | J68: Lenovo | K68: Lenovo ThinkPad T14 i5 16GB | 256GB | L68: i5 | M68: =RIGHT(K68,5) -> 256GB | N68: FALSE | O68: TRUE | P68: PF50Z059 | Q68: 45491 | R68: VNG | S68: 24589167 | AF68: =INDEX(Employee!C:C,MATCH(AG68,Employee!B:B,0)) -> Nguyễn Viết Khải | AG68: khainv | AH68: =INDEX(Employee!D:D,MATCH(AG68,Employee!B:B,0)) -> Lead IT Support Engineer | AI68: =INDEX(Employee!F:F,MATCH(AG68,Employee!B:B,0)) -> Tech | AJ68: =INDEX(Employee!C:C,MATCH(AK68,Employee!B:B,0)) -> Trương Thanh Đông | AK68: dongtt | AL68: =INDEX(Employee!D:D,MATCH(AK68,Employee!B:B,0)) -> Solutions Architect | AM68: =INDEX(Employee!F:F,MATCH(AK68,Employee!B:B,0)) -> Tech | AN68: =INDEX(Employee!H:H,MATCH(AK68,Employee!B:B,0)) -> Dương Huỳnh Nghĩa (nghiadh)
A69: =IF(B69<>"",ROW()-1,"") -> 68 | B69: LAPTOP | C69: In Stock | D69: =INDEX(Employee!E:E,MATCH(AK69,Employee!B:B,0)) -> #N/A | E69: =INDEX(Employee!F:F,MATCH(AK69,Employee!B:B,0)) -> #N/A | F69: =INDEX(Employee!G:G,MATCH(AK69,Employee!B:B,0)) -> #N/A | G69: HCM | I69: =IF(I68="","", "LAP"&TEXT(VALUE(RIGHT(I68,4))+1,"0000")) -> LAP0052 | J69: Lenovo | K69: Lenovo ThinkPad T14 i5 16GB | 256GB | L69: i5 | M69: =RIGHT(K69,5) -> 256GB | N69: TRUE | O69: FALSE | P69: PF2LR2H8 | Q69: 44347 | R69: VNG | S69: 2538700 | AF69: =INDEX(Employee!C:C,MATCH(AG69,Employee!B:B,0)) -> Nguyễn Viết Khải | AG69: khainv | AH69: =INDEX(Employee!D:D,MATCH(AG69,Employee!B:B,0)) -> Lead IT Support Engineer | AI69: =INDEX(Employee!F:F,MATCH(AG69,Employee!B:B,0)) -> Tech | AJ69: =INDEX(Employee!C:C,MATCH(AK69,Employee!B:B,0)) -> #N/A | AL69: =INDEX(Employee!D:D,MATCH(AK69,Employee!B:B,0)) -> #N/A | AM69: =INDEX(Employee!F:F,MATCH(AK69,Employee!B:B,0)) -> #N/A | AN69: =INDEX(Employee!H:H,MATCH(AK69,Employee!B:B,0)) -> #N/A
A70: =IF(B70<>"",ROW()-1,"") -> 69 | B70: LAPTOP | C70: In Use | D70: =INDEX(Employee!E:E,MATCH(AK70,Employee!B:B,0)) -> Project | E70: =INDEX(Employee!F:F,MATCH(AK70,Employee!B:B,0)) -> Tech | F70: =INDEX(Employee!G:G,MATCH(AK70,Employee!B:B,0)) -> Venture | G70: HCM | I70: =IF(I69="","", "LAP"&TEXT(VALUE(RIGHT(I69,4))+1,"0000")) -> LAP0053 | J70: Apple | K70: Macbook Pro M2 16GB | 256GB | L70: M2 | M70: =RIGHT(K70,5) -> 256GB | N70: TRUE | O70: FALSE | P70: DLJY37N2RR | Q70: 45239 | R70: VNG | S70: 24710000 | AF70: =INDEX(Employee!C:C,MATCH(AG70,Employee!B:B,0)) -> Nguyễn Viết Khải | AG70: khainv | AH70: =INDEX(Employee!D:D,MATCH(AG70,Employee!B:B,0)) -> Lead IT Support Engineer | AI70: =INDEX(Employee!F:F,MATCH(AG70,Employee!B:B,0)) -> Tech | AJ70: =INDEX(Employee!C:C,MATCH(AK70,Employee!B:B,0)) -> Nguyễn Quang Hoàng | AK70: hoangnq3 | AL70: =INDEX(Employee!D:D,MATCH(AK70,Employee!B:B,0)) -> Software Engineer | AM70: =INDEX(Employee!F:F,MATCH(AK70,Employee!B:B,0)) -> Tech | AN70: =INDEX(Employee!H:H,MATCH(AK70,Employee!B:B,0)) -> Đoàn Nhật Duẩn (duandn)
A71: =IF(B71<>"",ROW()-1,"") -> 70 | B71: LAPTOP | C71: In Use | D71: =INDEX(Employee!E:E,MATCH(AK71,Employee!B:B,0)) -> 0 | E71: =INDEX(Employee!F:F,MATCH(AK71,Employee!B:B,0)) -> Tech | F71: =INDEX(Employee!G:G,MATCH(AK71,Employee!B:B,0)) -> 0 | G71: IPL | H71: LAP16407 | I71: =IF(I70="","", "LAP"&TEXT(VALUE(RIGHT(I70,4))+1,"0000")) -> LAP0054 | J71: Apple | K71: Macbook Pro M3 16GB | 512GB | L71: M3 | M71: =RIGHT(K71,5) -> 512GB | N71: FALSE | O71: FALSE | P71: LPXJ7NYKWN | Q71: 45520 | R71: VNG | S71: 32727273 | AF71: =INDEX(Employee!C:C,MATCH(AG71,Employee!B:B,0)) -> Nguyễn Viết Khải | AG71: khainv | AH71: =INDEX(Employee!D:D,MATCH(AG71,Employee!B:B,0)) -> Lead IT Support Engineer | AI71: =INDEX(Employee!F:F,MATCH(AG71,Employee!B:B,0)) -> Tech | AJ71: =INDEX(Employee!C:C,MATCH(AK71,Employee!B:B,0)) -> Nguyễn Duy Mạnh | AK71: manhnd | AL71: =INDEX(Employee!D:D,MATCH(AK71,Employee!B:B,0)) -> Software Engineer | AM71: =INDEX(Employee!F:F,MATCH(AK71,Employee!B:B,0)) -> Tech | AN71: =INDEX(Employee!H:H,MATCH(AK71,Employee!B:B,0)) -> Nguyễn Ngọc Châu Sang
A72: =IF(B72<>"",ROW()-1,"") -> 71 | B72: LAPTOP | C72: In Stock | D72: =INDEX(Employee!E:E,MATCH(AK72,Employee!B:B,0)) -> #N/A | E72: =INDEX(Employee!F:F,MATCH(AK72,Employee!B:B,0)) -> #N/A | F72: =INDEX(Employee!G:G,MATCH(AK72,Employee!B:B,0)) -> #N/A | G72: IPL | I72: =IF(I71="","", "LAP"&TEXT(VALUE(RIGHT(I71,4))+1,"0000")) -> LAP0055 | J72: Apple | K72: Macbook Pro M2 16GB | 256GB | L72: M2 | M72: =RIGHT(K72,5) -> 256GB | N72: FALSE | O72: FALSE | P72: D067T37FMC | Q72: 45252 | R72: VNG | S72: 23886334 | AF72: =INDEX(Employee!C:C,MATCH(AG72,Employee!B:B,0)) -> Nguyễn Viết Khải | AG72: khainv | AH72: =INDEX(Employee!D:D,MATCH(AG72,Employee!B:B,0)) -> Lead IT Support Engineer | AI72: =INDEX(Employee!F:F,MATCH(AG72,Employee!B:B,0)) -> Tech | AJ72: =INDEX(Employee!C:C,MATCH(AK72,Employee!B:B,0)) -> #N/A | AL72: =INDEX(Employee!D:D,MATCH(AK72,Employee!B:B,0)) -> #N/A | AM72: =INDEX(Employee!F:F,MATCH(AK72,Employee!B:B,0)) -> #N/A | AN72: =INDEX(Employee!H:H,MATCH(AK72,Employee!B:B,0)) -> #N/A
A73: =IF(B73<>"",ROW()-1,"") -> 72 | B73: LAPTOP | C73: In Stock | D73: =INDEX(Employee!E:E,MATCH(AK73,Employee!B:B,0)) -> #N/A | E73: =INDEX(Employee!F:F,MATCH(AK73,Employee!B:B,0)) -> #N/A | F73: =INDEX(Employee!G:G,MATCH(AK73,Employee!B:B,0)) -> #N/A | G73: HCM | H73: LAP16182 | I73: =IF(I72="","", "LAP"&TEXT(VALUE(RIGHT(I72,4))+1,"0000")) -> LAP0056 | J73: Lenovo | K73: Lenovo ThinkPad T14 i5 16GB | 256GB | L73: i5 | M73: =RIGHT(K73,5) -> 256GB | N73: TRUE | O73: FALSE | P73: PF4TFPQ2 | Q73: 45308 | R73: VNG | S73: 21437889 | AF73: =INDEX(Employee!C:C,MATCH(AG73,Employee!B:B,0)) -> Nguyễn Viết Khải | AG73: khainv | AH73: =INDEX(Employee!D:D,MATCH(AG73,Employee!B:B,0)) -> Lead IT Support Engineer | AI73: =INDEX(Employee!F:F,MATCH(AG73,Employee!B:B,0)) -> Tech | AJ73: =INDEX(Employee!C:C,MATCH(AK73,Employee!B:B,0)) -> #N/A | AL73: =INDEX(Employee!D:D,MATCH(AK73,Employee!B:B,0)) -> #N/A | AM73: =INDEX(Employee!F:F,MATCH(AK73,Employee!B:B,0)) -> #N/A | AN73: =INDEX(Employee!H:H,MATCH(AK73,Employee!B:B,0)) -> #N/A
A74: =IF(B74<>"",ROW()-1,"") -> 73 | B74: LAPTOP | C74: In Stock | D74: =INDEX(Employee!E:E,MATCH(AK74,Employee!B:B,0)) -> #N/A | E74: =INDEX(Employee!F:F,MATCH(AK74,Employee!B:B,0)) -> #N/A | F74: =INDEX(Employee!G:G,MATCH(AK74,Employee!B:B,0)) -> #N/A | G74: HCM | I74: =IF(I73="","", "LAP"&TEXT(VALUE(RIGHT(I73,4))+1,"0000")) -> LAP0057 | J74: Lenovo | K74: Lenovo ThinkPad X13 i5 16GB | 256GB | L74: i5 | M74: =RIGHT(K74,5) -> 256GB | N74: TRUE | O74: TRUE | P74: PC2CD0J1 | Q74: 44649 | R74: VNG | S74: 3620834 | AF74: =INDEX(Employee!C:C,MATCH(AG74,Employee!B:B,0)) -> Nguyễn Viết Khải | AG74: khainv | AH74: =INDEX(Employee!D:D,MATCH(AG74,Employee!B:B,0)) -> Lead IT Support Engineer | AI74: =INDEX(Employee!F:F,MATCH(AG74,Employee!B:B,0)) -> Tech | AJ74: =INDEX(Employee!C:C,MATCH(AK74,Employee!B:B,0)) -> #N/A | AL74: =INDEX(Employee!D:D,MATCH(AK74,Employee!B:B,0)) -> #N/A | AM74: =INDEX(Employee!F:F,MATCH(AK74,Employee!B:B,0)) -> #N/A | AN74: =INDEX(Employee!H:H,MATCH(AK74,Employee!B:B,0)) -> #N/A
A75: =IF(B75<>"",ROW()-1,"") -> 74 | B75: LAPTOP | C75: In Use | D75: =INDEX(Employee!E:E,MATCH(AK75,Employee!B:B,0)) -> BO | E75: =INDEX(Employee!F:F,MATCH(AK75,Employee!B:B,0)) -> Business Support | F75: =INDEX(Employee!G:G,MATCH(AK75,Employee!B:B,0)) -> Operation Team | G75: HCM | I75: =IF(I74="","", "LAP"&TEXT(VALUE(RIGHT(I74,4))+1,"0000")) -> LAP0058 | J75: Lenovo | K75: Lenovo ThinkPad X13 i5 16GB | 256GB | L75: i5 | M75: =RIGHT(K75,5) -> 256GB | N75: TRUE | O75: TRUE | P75: PFASDZXC | Q75: 44119 | R75: VNG | S75: 2645600 | AF75: =INDEX(Employee!C:C,MATCH(AG75,Employee!B:B,0)) -> Nguyễn Viết Khải | AG75: khainv | AH75: =INDEX(Employee!D:D,MATCH(AG75,Employee!B:B,0)) -> Lead IT Support Engineer | AI75: =INDEX(Employee!F:F,MATCH(AG75,Employee!B:B,0)) -> Tech | AJ75: =INDEX(Employee!C:C,MATCH(AK75,Employee!B:B,0)) -> Nguyễn Ngọc Nhiên | AK75: nhiennn | AL75: =INDEX(Employee!D:D,MATCH(AK75,Employee!B:B,0)) -> Accounting Intern | AM75: =INDEX(Employee!F:F,MATCH(AK75,Employee!B:B,0)) -> Business Support | AN75: =INDEX(Employee!H:H,MATCH(AK75,Employee!B:B,0)) -> Hoàng Thị Trang | AS75: hieuvt
A76: =IF(B76<>"",ROW()-1,"") -> 75 | B76: LAPTOP | C76: In Stock | D76: =INDEX(Employee!E:E,MATCH(AK76,Employee!B:B,0)) -> #N/A | E76: =INDEX(Employee!F:F,MATCH(AK76,Employee!B:B,0)) -> #N/A | F76: =INDEX(Employee!G:G,MATCH(AK76,Employee!B:B,0)) -> #N/A | G76: HCM | H76: LAP14138 | I76: =IF(I75="","", "LAP"&TEXT(VALUE(RIGHT(I75,4))+1,"0000")) -> LAP0059 | J76: Lenovo | K76: Lenovo ThinkPad T14 i5 16GB | 256GB | L76: i5 | M76: =RIGHT(K76,5) -> 256GB | N76: TRUE | O76: TRUE | P76: PF24WRQX | Q76: 44145 | R76: VNG | S76: 2553000 | AF76: =INDEX(Employee!C:C,MATCH(AG76,Employee!B:B,0)) -> Nguyễn Viết Khải | AG76: khainv | AH76: =INDEX(Employee!D:D,MATCH(AG76,Employee!B:B,0)) -> Lead IT Support Engineer | AI76: =INDEX(Employee!F:F,MATCH(AG76,Employee!B:B,0)) -> Tech | AJ76: =INDEX(Employee!C:C,MATCH(AK76,Employee!B:B,0)) -> #N/A | AL76: =INDEX(Employee!D:D,MATCH(AK76,Employee!B:B,0)) -> #N/A | AM76: =INDEX(Employee!F:F,MATCH(AK76,Employee!B:B,0)) -> #N/A | AN76: =INDEX(Employee!H:H,MATCH(AK76,Employee!B:B,0)) -> #N/A
A77: =IF(B77<>"",ROW()-1,"") -> 76 | B77: LAPTOP | C77: In Use | D77: =INDEX(Employee!E:E,MATCH(AK77,Employee!B:B,0)) -> Project | E77: =INDEX(Employee!F:F,MATCH(AK77,Employee!B:B,0)) -> Tech | F77: =INDEX(Employee!G:G,MATCH(AK77,Employee!B:B,0)) -> Venture | G77: HCM | I77: =IF(I76="","", "LAP"&TEXT(VALUE(RIGHT(I76,4))+1,"0000")) -> LAP0060 | J77: Apple | K77: Macbook Pro M3 16GB | 512GB | L77: M3 | M77: =RIGHT(K77,5) -> 512GB | N77: TRUE | O77: FALSE | P77: FTQ79J1GQ9 | Q77: 45520 | R77: VNG | S77: 32727273 | AF77: =INDEX(Employee!C:C,MATCH(AG77,Employee!B:B,0)) -> Nguyễn Viết Khải | AG77: khainv | AH77: =INDEX(Employee!D:D,MATCH(AG77,Employee!B:B,0)) -> Lead IT Support Engineer | AI77: =INDEX(Employee!F:F,MATCH(AG77,Employee!B:B,0)) -> Tech | AJ77: =INDEX(Employee!C:C,MATCH(AK77,Employee!B:B,0)) -> Đoàn Nhật Duẩn | AK77: duandn | AL77: =INDEX(Employee!D:D,MATCH(AK77,Employee!B:B,0)) -> Chief Innovation Officer | AM77: =INDEX(Employee!F:F,MATCH(AK77,Employee!B:B,0)) -> Tech | AN77: =INDEX(Employee!H:H,MATCH(AK77,Employee!B:B,0)) -> Đoàn Hải Nam
A78: =IF(B78<>"",ROW()-1,"") -> 77 | B78: LAPTOP | C78: In Use | D78: =INDEX(Employee!E:E,MATCH(AK78,Employee!B:B,0)) -> 0 | E78: =INDEX(Employee!F:F,MATCH(AK78,Employee!B:B,0)) -> Tech | F78: =INDEX(Employee!G:G,MATCH(AK78,Employee!B:B,0)) -> 0 | G78: IPL | I78: =IF(I77="","", "LAP"&TEXT(VALUE(RIGHT(I77,4))+1,"0000")) -> LAP0061 | J78: Lenovo | K78: Lenovo ThinkPad T14 i5 16GB | 256GB | L78: i5 | M78: =RIGHT(K78,5) -> 256GB | N78: FALSE | O78: TRUE | P78: PF53HQ7G | Q78: 45622 | R78: VNG | S78: 28693195 | AF78: =INDEX(Employee!C:C,MATCH(AG78,Employee!B:B,0)) -> Nguyễn Viết Khải | AG78: khainv | AH78: =INDEX(Employee!D:D,MATCH(AG78,Employee!B:B,0)) -> Lead IT Support Engineer | AI78: =INDEX(Employee!F:F,MATCH(AG78,Employee!B:B,0)) -> Tech | AJ78: =INDEX(Employee!C:C,MATCH(AK78,Employee!B:B,0)) -> Nguyễn Công Bảo | AK78: baonc3 | AL78: =INDEX(Employee!D:D,MATCH(AK78,Employee!B:B,0)) -> Business Analyst | AM78: =INDEX(Employee!F:F,MATCH(AK78,Employee!B:B,0)) -> Tech | AN78: =INDEX(Employee!H:H,MATCH(AK78,Employee!B:B,0)) -> Nguyễn Vân Anh (anhnv5)
A79: =IF(B79<>"",ROW()-1,"") -> 78 | B79: LAPTOP | C79: In Use | D79: =INDEX(Employee!E:E,MATCH(AK79,Employee!B:B,0)) -> Project | E79: =INDEX(Employee!F:F,MATCH(AK79,Employee!B:B,0)) -> Tech | F79: =INDEX(Employee!G:G,MATCH(AK79,Employee!B:B,0)) -> Venture | G79: HCM | I79: =IF(I78="","", "LAP"&TEXT(VALUE(RIGHT(I78,4))+1,"0000")) -> LAP0062 | J79: Apple | K79: Macbook Pro M2 16GB | 256GB | L79: M2 | M79: =RIGHT(K79,5) -> 256GB | N79: TRUE | O79: FALSE | P79: YQX1W3H610 | Q79: 45252 | R79: VNG | S79: 24710000 | AF79: =INDEX(Employee!C:C,MATCH(AG79,Employee!B:B,0)) -> Nguyễn Viết Khải | AG79: khainv | AH79: =INDEX(Employee!D:D,MATCH(AG79,Employee!B:B,0)) -> Lead IT Support Engineer | AI79: =INDEX(Employee!F:F,MATCH(AG79,Employee!B:B,0)) -> Tech | AJ79: =INDEX(Employee!C:C,MATCH(AK79,Employee!B:B,0)) -> Phạm Thị Trúc Linh | AK79: linhptt | AL79: =INDEX(Employee!D:D,MATCH(AK79,Employee!B:B,0)) -> Associate QC Engineer | AM79: =INDEX(Employee!F:F,MATCH(AK79,Employee!B:B,0)) -> Tech | AN79: =INDEX(Employee!H:H,MATCH(AK79,Employee!B:B,0)) -> Nguyễn Khánh Vy
A80: =IF(B80<>"",ROW()-1,"") -> 79 | B80: LAPTOP | C80: In Stock | D80: =INDEX(Employee!E:E,MATCH(AK80,Employee!B:B,0)) -> #N/A | E80: =INDEX(Employee!F:F,MATCH(AK80,Employee!B:B,0)) -> #N/A | F80: =INDEX(Employee!G:G,MATCH(AK80,Employee!B:B,0)) -> #N/A | G80: HCM | I80: =IF(I79="","", "LAP"&TEXT(VALUE(RIGHT(I79,4))+1,"0000")) -> LAP0063 | J80: Lenovo | K80: Lenovo ThinkPad T14 i5 16GB | 256GB | L80: i5 | M80: =RIGHT(K80,5) -> 256GB | N80: TRUE | O80: FALSE | P80: PF2CG3WP | Q80: 44119 | R80: VNG | S80: 2554000 | AF80: =INDEX(Employee!C:C,MATCH(AG80,Employee!B:B,0)) -> Nguyễn Viết Khải | AG80: khainv | AH80: =INDEX(Employee!D:D,MATCH(AG80,Employee!B:B,0)) -> Lead IT Support Engineer | AI80: =INDEX(Employee!F:F,MATCH(AG80,Employee!B:B,0)) -> Tech | AJ80: =INDEX(Employee!C:C,MATCH(AK80,Employee!B:B,0)) -> #N/A | AL80: =INDEX(Employee!D:D,MATCH(AK80,Employee!B:B,0)) -> #N/A | AM80: =INDEX(Employee!F:F,MATCH(AK80,Employee!B:B,0)) -> #N/A | AN80: =INDEX(Employee!H:H,MATCH(AK80,Employee!B:B,0)) -> #N/A
A81: =IF(B81<>"",ROW()-1,"") -> 80 | B81: LAPTOP | C81: In Use | D81: =INDEX(Employee!E:E,MATCH(AK81,Employee!B:B,0)) -> Project | E81: =INDEX(Employee!F:F,MATCH(AK81,Employee!B:B,0)) -> Tech | F81: =INDEX(Employee!G:G,MATCH(AK81,Employee!B:B,0)) -> Venture | G81: HCM | H81: LAP16401 | I81: =IF(I80="","", "LAP"&TEXT(VALUE(RIGHT(I80,4))+1,"0000")) -> LAP0064 | J81: Apple | K81: Macbook Pro M3 16GB | 512GB | L81: M3 | M81: =RIGHT(K81,5) -> 512GB | N81: TRUE | O81: FALSE | P81: G7YCYYXR70 | Q81: 45520 | R81: VNG | S81: 32727273 | AF81: =INDEX(Employee!C:C,MATCH(AG81,Employee!B:B,0)) -> Nguyễn Viết Khải | AG81: khainv | AH81: =INDEX(Employee!D:D,MATCH(AG81,Employee!B:B,0)) -> Lead IT Support Engineer | AI81: =INDEX(Employee!F:F,MATCH(AG81,Employee!B:B,0)) -> Tech | AJ81: =INDEX(Employee!C:C,MATCH(AK81,Employee!B:B,0)) -> Nguyễn Hồ Quốc Thịnh | AK81: thinhnhq | AL81: =INDEX(Employee!D:D,MATCH(AK81,Employee!B:B,0)) -> Senior Software Engineer, Team Leader | AM81: =INDEX(Employee!F:F,MATCH(AK81,Employee!B:B,0)) -> Tech | AN81: =INDEX(Employee!H:H,MATCH(AK81,Employee!B:B,0)) -> Đoàn Nhật Duẩn
A82: =IF(B82<>"",ROW()-1,"") -> 81 | B82: LAPTOP | C82: In Use | D82: =INDEX(Employee!E:E,MATCH(AK82,Employee!B:B,0)) -> CTD | E82: =INDEX(Employee!F:F,MATCH(AK82,Employee!B:B,0)) -> CTD | F82: =INDEX(Employee!G:G,MATCH(AK82,Employee!B:B,0)) -> CTD | G82: HCM | I82: =IF(I81="","", "LAP"&TEXT(VALUE(RIGHT(I81,4))+1,"0000")) -> LAP0065 | J82: Lenovo | K82: Lenovo ThinkPad T14 i5 16GB | 256GB | L82: i5 | M82: =RIGHT(K82,5) -> 256GB | N82: TRUE | O82: TRUE | P82: PF50YJQX | Q82: 45420 | R82: VNG | S82: 25413445 | AF82: =INDEX(Employee!C:C,MATCH(AG82,Employee!B:B,0)) -> Nguyễn Viết Khải | AG82: khainv | AH82: =INDEX(Employee!D:D,MATCH(AG82,Employee!B:B,0)) -> Lead IT Support Engineer | AI82: =INDEX(Employee!F:F,MATCH(AG82,Employee!B:B,0)) -> Tech | AJ82: =INDEX(Employee!C:C,MATCH(AK82,Employee!B:B,0)) -> Nguyễn Minh Thy | AK82: thynm | AL82: =INDEX(Employee!D:D,MATCH(AK82,Employee!B:B,0)) -> IT Operator | AM82: =INDEX(Employee!F:F,MATCH(AK82,Employee!B:B,0)) -> CTD | AN82: =INDEX(Employee!H:H,MATCH(AK82,Employee!B:B,0)) -> CTD
A83: =IF(B83<>"",ROW()-1,"") -> 82 | B83: LAPTOP | C83: In Use | D83: =INDEX(Employee!E:E,MATCH(AK83,Employee!B:B,0)) -> BO | E83: =INDEX(Employee!F:F,MATCH(AK83,Employee!B:B,0)) -> Business Support | F83: =INDEX(Employee!G:G,MATCH(AK83,Employee!B:B,0)) -> Operation Team | G83: HCM | I83: =IF(I82="","", "LAP"&TEXT(VALUE(RIGHT(I82,4))+1,"0000")) -> LAP0066 | J83: Lenovo | K83: Lenovo ThinkPad E14 i5 16GB | 256GB | L83: i5 | M83: =RIGHT(K83,5) -> 256GB | N83: TRUE | O83: FALSE | P83: PF3M4L8N | Q83: 44840 | R83: VNG | S83: 2490280 | AF83: =INDEX(Employee!C:C,MATCH(AG83,Employee!B:B,0)) -> Nguyễn Viết Khải | AG83: khainv | AH83: =INDEX(Employee!D:D,MATCH(AG83,Employee!B:B,0)) -> Lead IT Support Engineer | AI83: =INDEX(Employee!F:F,MATCH(AG83,Employee!B:B,0)) -> Tech | AJ83: =INDEX(Employee!C:C,MATCH(AK83,Employee!B:B,0)) -> Trương Nữ Ngọc Mai | AK83: maitnn | AL83: =INDEX(Employee!D:D,MATCH(AK83,Employee!B:B,0)) -> Admin Executive | AM83: =INDEX(Employee!F:F,MATCH(AK83,Employee!B:B,0)) -> Business Support | AN83: =INDEX(Employee!H:H,MATCH(AK83,Employee!B:B,0)) -> Đoàn Hà Mi
A84: =IF(B84<>"",ROW()-1,"") -> 83 | B84: LAPTOP | C84: In Stock | D84: =INDEX(Employee!E:E,MATCH(AK84,Employee!B:B,0)) -> #N/A | E84: =INDEX(Employee!F:F,MATCH(AK84,Employee!B:B,0)) -> #N/A | F84: =INDEX(Employee!G:G,MATCH(AK84,Employee!B:B,0)) -> #N/A | G84: HCM | H84: LAP15381 | I84: =IF(I83="","", "LAP"&TEXT(VALUE(RIGHT(I83,4))+1,"0000")) -> LAP0067 | J84: Lenovo | K84: Lenovo ThinkPad T14 i5 16GB | 256GB | L84: i5 | M84: =RIGHT(K84,5) -> 256GB | N84: TRUE | O84: FALSE | P84: PF3M7ZFN | Q84: 44671 | R84: VNG | S84: 2815891 | AF84: =INDEX(Employee!C:C,MATCH(AG84,Employee!B:B,0)) -> Nguyễn Viết Khải | AG84: khainv | AH84: =INDEX(Employee!D:D,MATCH(AG84,Employee!B:B,0)) -> Lead IT Support Engineer | AI84: =INDEX(Employee!F:F,MATCH(AG84,Employee!B:B,0)) -> Tech | AJ84: =INDEX(Employee!C:C,MATCH(AK84,Employee!B:B,0)) -> #N/A | AL84: =INDEX(Employee!D:D,MATCH(AK84,Employee!B:B,0)) -> #N/A | AM84: =INDEX(Employee!F:F,MATCH(AK84,Employee!B:B,0)) -> #N/A | AN84: =INDEX(Employee!H:H,MATCH(AK84,Employee!B:B,0)) -> #N/A
A85: =IF(B85<>"",ROW()-1,"") -> 84 | B85: LAPTOP | C85: In Stock | D85: =INDEX(Employee!E:E,MATCH(AK85,Employee!B:B,0)) -> BO | E85: =INDEX(Employee!F:F,MATCH(AK85,Employee!B:B,0)) -> Business Support | F85: =INDEX(Employee!G:G,MATCH(AK85,Employee!B:B,0)) -> Operation Team | G85: HCM | I85: =IF(I84="","", "LAP"&TEXT(VALUE(RIGHT(I84,4))+1,"0000")) -> LAP0068 | J85: Lenovo | K85: Lenovo ThinkPad X13 i5 16GB | 256GB | L85: i5 | M85: =RIGHT(K85,5) -> 256GB | N85: TRUE | O85: FALSE | P85: PF2CF7TN | Q85: 44119 | R85: VNG | S85: 2645600 | AF85: =INDEX(Employee!C:C,MATCH(AG85,Employee!B:B,0)) -> Nguyễn Viết Khải | AG85: khainv | AH85: =INDEX(Employee!D:D,MATCH(AG85,Employee!B:B,0)) -> Lead IT Support Engineer | AI85: =INDEX(Employee!F:F,MATCH(AG85,Employee!B:B,0)) -> Tech | AJ85: =INDEX(Employee!C:C,MATCH(AK85,Employee!B:B,0)) -> Nguyễn Việt Trung | AK85: trungnv | AL85: =INDEX(Employee!D:D,MATCH(AK85,Employee!B:B,0)) -> Internal Auditor | AM85: =INDEX(Employee!F:F,MATCH(AK85,Employee!B:B,0)) -> Business Support | AN85: =INDEX(Employee!H:H,MATCH(AK85,Employee!B:B,0)) -> Nguyễn Thị My Sa
A86: =IF(B86<>"",ROW()-1,"") -> 85 | B86: LAPTOP | C86: Sold | D86: =INDEX(Employee!E:E,MATCH(AK86,Employee!B:B,0)) -> 0 | E86: =INDEX(Employee!F:F,MATCH(AK86,Employee!B:B,0)) -> 0 | F86: =INDEX(Employee!G:G,MATCH(AK86,Employee!B:B,0)) -> 0 | G86: HCM | I86: =IF(I85="","", "LAP"&TEXT(VALUE(RIGHT(I85,4))+1,"0000")) -> LAP0069 | J86: Lenovo | K86: Lenovo ThinkPad T14 i5 16GB | 256GB | L86: i5 | M86: =RIGHT(K86,5) -> 256GB | N86: FALSE | O86: FALSE | P86: PF3HMEV9 | Q86: 44642 | R86: VNG | S86: 3472640 | AF86: =INDEX(Employee!C:C,MATCH(AG86,Employee!B:B,0)) -> Nguyễn Viết Khải | AG86: khainv | AH86: =INDEX(Employee!D:D,MATCH(AG86,Employee!B:B,0)) -> Lead IT Support Engineer | AI86: =INDEX(Employee!F:F,MATCH(AG86,Employee!B:B,0)) -> Tech | AJ86: =INDEX(Employee!C:C,MATCH(AK86,Employee!B:B,0)) -> Kiết Văn | AK86: vank | AL86: =INDEX(Employee!D:D,MATCH(AK86,Employee!B:B,0)) -> 0 | AM86: =INDEX(Employee!F:F,MATCH(AK86,Employee!B:B,0)) -> 0 | AN86: =INDEX(Employee!H:H,MATCH(AK86,Employee!B:B,0)) -> 0
A87: =IF(B87<>"",ROW()-1,"") -> 86 | B87: LAPTOP | C87: In Stock | D87: =INDEX(Employee!E:E,MATCH(AK87,Employee!B:B,0)) -> #N/A | E87: =INDEX(Employee!F:F,MATCH(AK87,Employee!B:B,0)) -> #N/A | F87: =INDEX(Employee!G:G,MATCH(AK87,Employee!B:B,0)) -> #N/A | G87: HCM | H87: LAP13005 | I87: =IF(I86="","", "LAP"&TEXT(VALUE(RIGHT(I86,4))+1,"0000")) -> LAP0070 | J87: Lenovo | K87: Lenovo ThinkPad T480 i5 16GB | 256GB | L87: i5 | M87: =RIGHT(K87,5) -> 256GB | N87: TRUE | O87: FALSE | P87: PF1NEMT7 | Q87: 43587 | R87: VNG | S87: 2562800 | AF87: =INDEX(Employee!C:C,MATCH(AG87,Employee!B:B,0)) -> Nguyễn Viết Khải | AG87: khainv | AH87: =INDEX(Employee!D:D,MATCH(AG87,Employee!B:B,0)) -> Lead IT Support Engineer | AI87: =INDEX(Employee!F:F,MATCH(AG87,Employee!B:B,0)) -> Tech | AJ87: =INDEX(Employee!C:C,MATCH(AK87,Employee!B:B,0)) -> #N/A | AL87: =INDEX(Employee!D:D,MATCH(AK87,Employee!B:B,0)) -> #N/A | AM87: =INDEX(Employee!F:F,MATCH(AK87,Employee!B:B,0)) -> #N/A | AN87: =INDEX(Employee!H:H,MATCH(AK87,Employee!B:B,0)) -> #N/A | AQ87: Spec yếu I5 - Pin rời
A88: =IF(B88<>"",ROW()-1,"") -> 87 | B88: MOUSE | C88: In Stock | D88: =INDEX(Employee!E:E,MATCH(AK88,Employee!B:B,0)) -> #N/A | E88: =INDEX(Employee!F:F,MATCH(AK88,Employee!B:B,0)) -> #N/A | F88: =INDEX(Employee!G:G,MATCH(AK88,Employee!B:B,0)) -> #N/A | G88: HCM | I88: MOU0016 | J88: Logitech | K88: Logitech M221 | N88: FALSE | O88: FALSE | P88: 2332LZX94R48 | Q88: 45233 | R88: VNG | S88: 20182 | AF88: =INDEX(Employee!C:C,MATCH(AG88,Employee!B:B,0)) -> Nguyễn Viết Khải | AG88: khainv | AH88: =INDEX(Employee!D:D,MATCH(AG88,Employee!B:B,0)) -> Lead IT Support Engineer | AI88: =INDEX(Employee!F:F,MATCH(AG88,Employee!B:B,0)) -> Tech | AJ88: =INDEX(Employee!C:C,MATCH(AK88,Employee!B:B,0)) -> #N/A | AL88: =INDEX(Employee!D:D,MATCH(AK88,Employee!B:B,0)) -> #N/A | AM88: =INDEX(Employee!F:F,MATCH(AK88,Employee!B:B,0)) -> #N/A | AN88: =INDEX(Employee!H:H,MATCH(AK88,Employee!B:B,0)) -> #N/A
A89: =IF(B89<>"",ROW()-1,"") -> 88 | B89: MOUSE | C89: Damaged | D89: =INDEX(Employee!E:E,MATCH(AK89,Employee!B:B,0)) -> #N/A | E89: =INDEX(Employee!F:F,MATCH(AK89,Employee!B:B,0)) -> #N/A | F89: =INDEX(Employee!G:G,MATCH(AK89,Employee!B:B,0)) -> #N/A | G89: HCM | I89: MOU0017 | J89: Logitech | K89: Logitech M221 | N89: FALSE | O89: FALSE | P89: 2332LZXLK218 | Q89: 45233 | R89: VNG | S89: 20182 | AF89: =INDEX(Employee!C:C,MATCH(AG89,Employee!B:B,0)) -> Nguyễn Viết Khải | AG89: khainv | AH89: =INDEX(Employee!D:D,MATCH(AG89,Employee!B:B,0)) -> Lead IT Support Engineer | AI89: =INDEX(Employee!F:F,MATCH(AG89,Employee!B:B,0)) -> Tech | AJ89: =INDEX(Employee!C:C,MATCH(AK89,Employee!B:B,0)) -> #N/A | AL89: =INDEX(Employee!D:D,MATCH(AK89,Employee!B:B,0)) -> #N/A | AM89: =INDEX(Employee!F:F,MATCH(AK89,Employee!B:B,0)) -> #N/A | AN89: =INDEX(Employee!H:H,MATCH(AK89,Employee!B:B,0)) -> #N/A
A90: =IF(B90<>"",ROW()-1,"") -> 89 | B90: MOUSE | C90: In Stock | D90: =INDEX(Employee!E:E,MATCH(AK90,Employee!B:B,0)) -> #N/A | E90: =INDEX(Employee!F:F,MATCH(AK90,Employee!B:B,0)) -> #N/A | F90: =INDEX(Employee!G:G,MATCH(AK90,Employee!B:B,0)) -> #N/A | G90: HCM | I90: MOU0018 | J90: Logitech | K90: Logitech M221 | N90: FALSE | O90: FALSE | P90: 2333LZXHUUK8 | Q90: 45233 | R90: VNG | S90: 20182 | AF90: =INDEX(Employee!C:C,MATCH(AG90,Employee!B:B,0)) -> Nguyễn Viết Khải | AG90: khainv | AH90: =INDEX(Employee!D:D,MATCH(AG90,Employee!B:B,0)) -> Lead IT Support Engineer | AI90: =INDEX(Employee!F:F,MATCH(AG90,Employee!B:B,0)) -> Tech | AJ90: =INDEX(Employee!C:C,MATCH(AK90,Employee!B:B,0)) -> #N/A | AL90: =INDEX(Employee!D:D,MATCH(AK90,Employee!B:B,0)) -> #N/A | AM90: =INDEX(Employee!F:F,MATCH(AK90,Employee!B:B,0)) -> #N/A | AN90: =INDEX(Employee!H:H,MATCH(AK90,Employee!B:B,0)) -> #N/A
A91: =IF(B91<>"",ROW()-1,"") -> 90 | B91: MOUSE | C91: In Stock | D91: =INDEX(Employee!E:E,MATCH(AK91,Employee!B:B,0)) -> Project | E91: =INDEX(Employee!F:F,MATCH(AK91,Employee!B:B,0)) -> Tech | F91: =INDEX(Employee!G:G,MATCH(AK91,Employee!B:B,0)) -> Resource Pool | G91: HCM | I91: MOU0019 | J91: Logitech | K91: Logitech M221 | N91: FALSE | O91: FALSE | P91: 2431ZE06EFD8 | Q91: 45233 | R91: VNG | S91: 20182 | AF91: =INDEX(Employee!C:C,MATCH(AG91,Employee!B:B,0)) -> Nguyễn Viết Khải | AG91: khainv | AH91: =INDEX(Employee!D:D,MATCH(AG91,Employee!B:B,0)) -> Lead IT Support Engineer | AI91: =INDEX(Employee!F:F,MATCH(AG91,Employee!B:B,0)) -> Tech | AJ91: =INDEX(Employee!C:C,MATCH(AK91,Employee!B:B,0)) -> Nguyễn Lê Thanh Trúc | AK91: trucnlt | AL91: =INDEX(Employee!D:D,MATCH(AK91,Employee!B:B,0)) -> Fresher QC Engineer | AM91: =INDEX(Employee!F:F,MATCH(AK91,Employee!B:B,0)) -> Tech | AN91: =INDEX(Employee!H:H,MATCH(AK91,Employee!B:B,0)) -> Đoàn Hải Nam
A92: =IF(B92<>"",ROW()-1,"") -> 91 | B92: MOUSE | C92: In Use | D92: =INDEX(Employee!E:E,MATCH(AK92,Employee!B:B,0)) -> BO | E92: =INDEX(Employee!F:F,MATCH(AK92,Employee!B:B,0)) -> Business Support | F92: =INDEX(Employee!G:G,MATCH(AK92,Employee!B:B,0)) -> Operation Team | G92: IPL | I92: MOU0020 | J92: Logitech | K92: Logitech M221 | N92: FALSE | O92: FALSE | P92: 2333LZXLJGR8 | Q92: 45233 | R92: VNG | S92: 20182 | AF92: =INDEX(Employee!C:C,MATCH(AG92,Employee!B:B,0)) -> Nguyễn Viết Khải | AG92: khainv | AH92: =INDEX(Employee!D:D,MATCH(AG92,Employee!B:B,0)) -> Lead IT Support Engineer | AI92: =INDEX(Employee!F:F,MATCH(AG92,Employee!B:B,0)) -> Tech | AJ92: =INDEX(Employee!C:C,MATCH(AK92,Employee!B:B,0)) -> Lê Quý Vân Anh | AK92: anhlqv | AL92: =INDEX(Employee!D:D,MATCH(AK92,Employee!B:B,0)) -> Senior C&B Specialist | AM92: =INDEX(Employee!F:F,MATCH(AK92,Employee!B:B,0)) -> Business Support | AN92: =INDEX(Employee!H:H,MATCH(AK92,Employee!B:B,0)) -> Nguyễn Thị My Sa
A93: =IF(B93<>"",ROW()-1,"") -> 92 | B93: MOUSE | C93: In Use | D93: =INDEX(Employee!E:E,MATCH(AK93,Employee!B:B,0)) -> Project | E93: =INDEX(Employee!F:F,MATCH(AK93,Employee!B:B,0)) -> Tech | F93: =INDEX(Employee!G:G,MATCH(AK93,Employee!B:B,0)) -> Venture | G93: HCM | I93: MOU0021 | J93: Logitech | K93: Logitech M221 | N93: FALSE | O93: FALSE | P93: 2445ZEW5H0K8 | Q93: 45233 | R93: VNG | S93: 20182 | AF93: =INDEX(Employee!C:C,MATCH(AG93,Employee!B:B,0)) -> Nguyễn Viết Khải | AG93: khainv | AH93: =INDEX(Employee!D:D,MATCH(AG93,Employee!B:B,0)) -> Lead IT Support Engineer | AI93: =INDEX(Employee!F:F,MATCH(AG93,Employee!B:B,0)) -> Tech | AJ93: =INDEX(Employee!C:C,MATCH(AK93,Employee!B:B,0)) -> Phạm Thị Trúc Linh | AK93: linhptt | AL93: =INDEX(Employee!D:D,MATCH(AK93,Employee!B:B,0)) -> Associate QC Engineer | AM93: =INDEX(Employee!F:F,MATCH(AK93,Employee!B:B,0)) -> Tech | AN93: =INDEX(Employee!H:H,MATCH(AK93,Employee!B:B,0)) -> Nguyễn Khánh Vy
A94: =IF(B94<>"",ROW()-1,"") -> 93 | B94: MOUSE | C94: Damaged | D94: =INDEX(Employee!E:E,MATCH(AK94,Employee!B:B,0)) -> #N/A | E94: =INDEX(Employee!F:F,MATCH(AK94,Employee!B:B,0)) -> #N/A | F94: =INDEX(Employee!G:G,MATCH(AK94,Employee!B:B,0)) -> #N/A | G94: HCM | I94: MOU0022 | J94: Logitech | K94: Logitech M221 | N94: FALSE | O94: FALSE | P94: 2333LZXLJZ7S | Q94: 45233 | R94: VNG | S94: 20182 | AF94: =INDEX(Employee!C:C,MATCH(AG94,Employee!B:B,0)) -> Nguyễn Viết Khải | AG94: khainv | AH94: =INDEX(Employee!D:D,MATCH(AG94,Employee!B:B,0)) -> Lead IT Support Engineer | AI94: =INDEX(Employee!F:F,MATCH(AG94,Employee!B:B,0)) -> Tech | AJ94: =INDEX(Employee!C:C,MATCH(AK94,Employee!B:B,0)) -> #N/A | AL94: =INDEX(Employee!D:D,MATCH(AK94,Employee!B:B,0)) -> #N/A | AM94: =INDEX(Employee!F:F,MATCH(AK94,Employee!B:B,0)) -> #N/A | AN94: =INDEX(Employee!H:H,MATCH(AK94,Employee!B:B,0)) -> #N/A
A95: =IF(B95<>"",ROW()-1,"") -> 94 | B95: MOUSE | C95: Damaged | D95: =INDEX(Employee!E:E,MATCH(AK95,Employee!B:B,0)) -> #N/A | E95: =INDEX(Employee!F:F,MATCH(AK95,Employee!B:B,0)) -> #N/A | F95: =INDEX(Employee!G:G,MATCH(AK95,Employee!B:B,0)) -> #N/A | G95: HCM | I95: MOU0023 | J95: Logitech | K95: Logitech M221 | N95: FALSE | O95: FALSE | P95: 2333LZXLJ858 | Q95: 45279 | R95: VNG | S95: 20182 | AF95: =INDEX(Employee!C:C,MATCH(AG95,Employee!B:B,0)) -> Nguyễn Viết Khải | AG95: khainv | AH95: =INDEX(Employee!D:D,MATCH(AG95,Employee!B:B,0)) -> Lead IT Support Engineer | AI95: =INDEX(Employee!F:F,MATCH(AG95,Employee!B:B,0)) -> Tech | AJ95: =INDEX(Employee!C:C,MATCH(AK95,Employee!B:B,0)) -> #N/A | AL95: =INDEX(Employee!D:D,MATCH(AK95,Employee!B:B,0)) -> #N/A | AM95: =INDEX(Employee!F:F,MATCH(AK95,Employee!B:B,0)) -> #N/A | AN95: =INDEX(Employee!H:H,MATCH(AK95,Employee!B:B,0)) -> #N/A
A96: =IF(B96<>"",ROW()-1,"") -> 95 | B96: MOUSE | C96: In Use | D96: =INDEX(Employee!E:E,MATCH(AK96,Employee!B:B,0)) -> 0 | E96: =INDEX(Employee!F:F,MATCH(AK96,Employee!B:B,0)) -> Tech | F96: =INDEX(Employee!G:G,MATCH(AK96,Employee!B:B,0)) -> 0 | G96: IPL | I96: MOU0024 | J96: Logitech | K96: Logitech M221 | N96: FALSE | O96: FALSE | P96: 2417LZX3HCX8 | Q96: 45279 | R96: VNG | S96: 20182 | AF96: =INDEX(Employee!C:C,MATCH(AG96,Employee!B:B,0)) -> Nguyễn Viết Khải | AG96: khainv | AH96: =INDEX(Employee!D:D,MATCH(AG96,Employee!B:B,0)) -> Lead IT Support Engineer | AI96: =INDEX(Employee!F:F,MATCH(AG96,Employee!B:B,0)) -> Tech | AJ96: =INDEX(Employee!C:C,MATCH(AK96,Employee!B:B,0)) -> Đinh Hiểu Văn | AK96: vandh | AL96: =INDEX(Employee!D:D,MATCH(AK96,Employee!B:B,0)) -> Software Engineer | AM96: =INDEX(Employee!F:F,MATCH(AK96,Employee!B:B,0)) -> Tech | AN96: =INDEX(Employee!H:H,MATCH(AK96,Employee!B:B,0)) -> Trần Triệu Dương (duongtt5)
A97: =IF(B97<>"",ROW()-1,"") -> 96 | B97: MOUSE | C97: Damaged | D97: =INDEX(Employee!E:E,MATCH(AK97,Employee!B:B,0)) -> #N/A | E97: =INDEX(Employee!F:F,MATCH(AK97,Employee!B:B,0)) -> #N/A | F97: =INDEX(Employee!G:G,MATCH(AK97,Employee!B:B,0)) -> #N/A | G97: HCM | I97: MOU0025 | J97: Logitech | K97: Logitech M221 | N97: FALSE | O97: FALSE | P97: 2333LZXFST08 | Q97: 45279 | R97: VNG | S97: 20182 | AF97: =INDEX(Employee!C:C,MATCH(AG97,Employee!B:B,0)) -> Nguyễn Viết Khải | AG97: khainv | AH97: =INDEX(Employee!D:D,MATCH(AG97,Employee!B:B,0)) -> Lead IT Support Engineer | AI97: =INDEX(Employee!F:F,MATCH(AG97,Employee!B:B,0)) -> Tech | AJ97: =INDEX(Employee!C:C,MATCH(AK97,Employee!B:B,0)) -> #N/A | AL97: =INDEX(Employee!D:D,MATCH(AK97,Employee!B:B,0)) -> #N/A | AM97: =INDEX(Employee!F:F,MATCH(AK97,Employee!B:B,0)) -> #N/A | AN97: =INDEX(Employee!H:H,MATCH(AK97,Employee!B:B,0)) -> #N/A
A98: =IF(B98<>"",ROW()-1,"") -> 97 | B98: MOUSE | C98: Damaged | D98: =INDEX(Employee!E:E,MATCH(AK98,Employee!B:B,0)) -> #N/A | E98: =INDEX(Employee!F:F,MATCH(AK98,Employee!B:B,0)) -> #N/A | F98: =INDEX(Employee!G:G,MATCH(AK98,Employee!B:B,0)) -> #N/A | G98: HCM | I98: MOU0026 | J98: Logitech | K98: Logitech M221 | N98: FALSE | O98: FALSE | P98: 2212LZM6V928 | Q98: 45279 | R98: VNG | S98: 20182 | AF98: =INDEX(Employee!C:C,MATCH(AG98,Employee!B:B,0)) -> Nguyễn Viết Khải | AG98: khainv | AH98: =INDEX(Employee!D:D,MATCH(AG98,Employee!B:B,0)) -> Lead IT Support Engineer | AI98: =INDEX(Employee!F:F,MATCH(AG98,Employee!B:B,0)) -> Tech | AJ98: =INDEX(Employee!C:C,MATCH(AK98,Employee!B:B,0)) -> #N/A | AL98: =INDEX(Employee!D:D,MATCH(AK98,Employee!B:B,0)) -> #N/A | AM98: =INDEX(Employee!F:F,MATCH(AK98,Employee!B:B,0)) -> #N/A | AN98: =INDEX(Employee!H:H,MATCH(AK98,Employee!B:B,0)) -> #N/A
A99: =IF(B99<>"",ROW()-1,"") -> 98 | B99: MOUSE | C99: Damaged | D99: =INDEX(Employee!E:E,MATCH(AK99,Employee!B:B,0)) -> #N/A | E99: =INDEX(Employee!F:F,MATCH(AK99,Employee!B:B,0)) -> #N/A | F99: =INDEX(Employee!G:G,MATCH(AK99,Employee!B:B,0)) -> #N/A | G99: HCM | I99: MOU0027 | J99: Logitech | K99: Logitech M221 | N99: FALSE | O99: FALSE | P99: 2333LZXLJJ58 | Q99: 45279 | R99: VNG | S99: 20182 | AF99: =INDEX(Employee!C:C,MATCH(AG99,Employee!B:B,0)) -> Nguyễn Viết Khải | AG99: khainv | AH99: =INDEX(Employee!D:D,MATCH(AG99,Employee!B:B,0)) -> Lead IT Support Engineer | AI99: =INDEX(Employee!F:F,MATCH(AG99,Employee!B:B,0)) -> Tech | AJ99: =INDEX(Employee!C:C,MATCH(AK99,Employee!B:B,0)) -> #N/A | AL99: =INDEX(Employee!D:D,MATCH(AK99,Employee!B:B,0)) -> #N/A | AM99: =INDEX(Employee!F:F,MATCH(AK99,Employee!B:B,0)) -> #N/A | AN99: =INDEX(Employee!H:H,MATCH(AK99,Employee!B:B,0)) -> #N/A
A100: =IF(B100<>"",ROW()-1,"") -> 99 | B100: MOUSE | C100: Damaged | D100: =INDEX(Employee!E:E,MATCH(AK100,Employee!B:B,0)) -> #N/A | E100: =INDEX(Employee!F:F,MATCH(AK100,Employee!B:B,0)) -> #N/A | F100: =INDEX(Employee!G:G,MATCH(AK100,Employee!B:B,0)) -> #N/A | G100: HCM | I100: MOU0028 | J100: Logitech | K100: Logitech M221 | N100: FALSE | O100: FALSE | P100: 2333LZXLJET8 | Q100: 45279 | R100: VNG | S100: 20182 | AF100: =INDEX(Employee!C:C,MATCH(AG100,Employee!B:B,0)) -> Nguyễn Viết Khải | AG100: khainv | AH100: =INDEX(Employee!D:D,MATCH(AG100,Employee!B:B,0)) -> Lead IT Support Engineer | AI100: =INDEX(Employee!F:F,MATCH(AG100,Employee!B:B,0)) -> Tech | AJ100: =INDEX(Employee!C:C,MATCH(AK100,Employee!B:B,0)) -> #N/A | AL100: =INDEX(Employee!D:D,MATCH(AK100,Employee!B:B,0)) -> #N/A | AM100: =INDEX(Employee!F:F,MATCH(AK100,Employee!B:B,0)) -> #N/A | AN100: =INDEX(Employee!H:H,MATCH(AK100,Employee!B:B,0)) -> #N/A
...

Sheet Employee
A1: Danh sách user VSOL hiện tại
A2: No | B2: Account | C2: Name | D2: Job Title | E2: Business unit | F2: Job Family | G2: Project | H2: Line Manager | I2: Line Manager. Domain | J2: Onboard date | K2: Last date | L2: Status | M2: Location | N2: Note
A3: 1 | B3: antg | C3: Trần Gia Ân | D3: SAP Intern | E3: CTD | F3: CTD | G3: CTD | H3: CTD
A4: 2 | B4: maitnn | C4: Trương Nữ Ngọc Mai | D4: Admin Executive | E4: BO | F4: Business Support | G4: Operation Team | H4: Đoàn Hà Mi | L4: Active | M4: HCM
A5: 3 | B5: thynm | C5: Nguyễn Minh Thy | D5: IT Operator | E5: CTD | F5: CTD | G5: CTD | H5: CTD
A6: 4 | B6: namdh02 | C6: Đoàn Hải Nam | D6: CIO | E6: CTD | F6: CTD | G6: CTD | H6: CTD
A7: 5 | B7: IT | C7: IT Dept CTD | D7: CTD | E7: CTD | F7: CTD | G7: CTD | H7: CTD
A8: 6 | B8: server | C8: P.Datacenter F9 | D8: CTD | E8: CTD | F8: CTD | G8: CTD | H8: CTD
A9: 7 | B9: recep | C9: Reception | D9: IPL | F9: IPL | H9: IPL
A10: 8 | B10: vsol | C10: Vsol Meeting Room | D10: VSOL | F10: VSOL | H10: VSOL
A11: 9 | B11: ipl | C11: IPL Meeting Room | D11: IPL | F11: IPL | H11: IPL
A12: 10 | B12: nguyennvc | C12: Nguyễn Văn Cao Nguyên | D12: Senior Site Reliability Engineer | F12: Tech | H12: Nguyễn Ngọc Châu Sang
A13: 11 | B13: thoaidd | C13: Đào Duy Thoại | D13: Head of IT | E13: CTD | F13: CTD | G13: CTD | H13: CTD
A14: 12 | B14: santm | C14: Nguyễn Thị My Sa | D14: HR Business Partner | E14: CTD | F14: CTD | G14: CTD | H14: Nguyễn Trình Thùy Trang
A15: 13 | B15: anhth | C15: Trần Hoàng Anh | D15: Senior Machine Learning Engineer | E15: Project | F15: Data | G15: Venture | H15: Đoàn Nhật Duẩn | I15: duandn
A16: 14 | B16: hoangpnt | C16: Phạm Ngô Triệu Hoàng | D16: Associate Business Analyst | F16: Tech | H16: Nguyễn Vân Anh
A17: 15 | B17: hannt | C17: Nguyễn Thị Thu Hà | D17: Talent Acquisition Business Partner | F17: HR | H17: Võ Ngọc Trâm
A18: 16 | B18: hoanglm | C18: Lương Minh Hoàng | D18: Lead Software Engineer | F18: Tech | H18: Nguyễn Ngọc Châu Sang
A19: 17 | B19: manhnd | C19: Nguyễn Duy Mạnh | D19: Software Engineer | F19: Tech | H19: Nguyễn Ngọc Châu Sang
A20: 18 | B20: thold | C20: Lê Đình Thọ | D20: Lead QC Engineer | F20: Tech | H20: Nguyễn Ngọc Châu Sang
A21: 19 | B21: tuanda | C21: Đỗ Anh Tuấn | D21: Software Engineer | F21: Tech | H21: Trần Triệu Dương (duongtt5)
A22: 20 | B22: vyhnt | C22: Huỳnh Ngọc Tường Vy | D22: Associate NOC Engineer | F22: Tech | H22: Nguyễn Thị Việt Hà
A23: 21 | B23: diemht | C23: Huỳnh Thúy Diễm | D23: Fresher Business Analyst | E23: Project | F23: Tech | G23: Venture | H23: Nguyễn Khánh Vy | I23: vynk2
A24: 22 | B24: trinm | C24: Nguyễn Minh Trí | D24: SRE Lead | F24: Tech | H24: Dương Huỳnh Nghĩa (nghiadh)
A25: 23 | B25: nhiennn | C25: Nguyễn Ngọc Nhiên | D25: Accounting Intern | E25: BO | F25: Business Support | G25: Operation Team | H25: Hoàng Thị Trang | I25: tranght
A26: 24 | B26: natv | C26: NATV | D26: NATV | F26: IT
A27: 25 | B27: mtr | C27: Meeting Room | D27: Meeting Room | F27: IT
A28: 26 | B28: kient | C28: Trần Kiên | D28: QC Engineer | F28: Tech | H28: Trần Triệu Dương (duongtt5)
A29: 27 | B29: vank | C29: Kiết Văn
A30: 28 | B30: bangp | C30: Phạm Bằng | D30: Fresher Data Engineer | E30: Project | F30: Data | G30: Resource Pool | H30: Đoàn Hải Nam | I30: namdh02
A31: 29 | B31: anhphq | C31: Phạm Hồng Quốc Anh | D31: Lead Software Engineer | F31: Tech | H31: Trần Triệu Dương (duongtt5)
A32: 30 | B32: vannt | C32: Nguyễn Trí Văn | D32: Site Reliability Engineer | F32: OP | H32: Chu Văn Toàn (ToanCV)
A33: 31 | B33: minhdh | C33: Đặng Hoàng Minh | D33: QC Engineer | F33: Tech | H33: Dương Phạm Thành Công (congdpt)
A34: 32 | B34: tranght | C34: Hoàng Thị Trang | D34: Accounting Manager | E34: BO | F34: Business Support | G34: Operation Team | H34: Nguyễn Thị Thủy | I34: thuynt03
A35: 33 | B35: totq | C35: Trần Quốc Tố | D35: Associate Technical Support Engineer | F35: OP | H35: Chu Văn Toàn (ToanCV)
A36: 34 | B36: khanhnv | C36: Nguyễn Văn Khánh | D36: Fresher Software Engineer | F36: Tech | H36: Đặng Hồng Phong
A37: 35 | B37: hientm | C37: Tăng Minh Hiển | D37: Fresher Data Engineer | F37: Tech | H37: Đào Đức Dũng
A38: 36 | B38: duyennm | C38: Nguyễn Mỹ Duyên | D38: HR Intern | F38: HR | H38: Vòng Bảo Nhi
A39: 37 | B39: ngoclhb | C39: Lê Hoài Bảo Ngọc | D39: Talent Acquisition Intern | F39: HR | H39: Vòng Bảo Nhi
A40: 38 | B40: huythq | C40: Trần Hữu Quốc Huy | D40: Fresher Software Engineer | F40: Tech | H40: Nguyễn Đình Thái
A41: 39 | B41: datn | C41: Nguyễn Đạt | D41: Associate NOC Engineer | F41: OP | H41: Nguyễn Thị Việt Hà
A42: 40 | B42: ivan | C42: Ivan
A43: 41 | B43: huynhmc | C43: Mã Cát Huỳnh | D43: Fresher Software Engineer | F43: Tech | H43: Dương Phạm Thành Công (congdpt)
A44: 42 | B44: trungnq | C44: Nguyễn Quốc Trung | D44: Fresher Software Engineer | E44: Undirect IT Staff | F44: Tech | G44: Odoo | H44: Dương Phạm Thành Công (congdpt) | I44: congdpt
A45: 43 | B45: trinhnn | C45: Nguyễn Ngọc Trinh | D45: Fresher QC Engineer | E45: Undirect IT Staff | F45: Tech | G45: Odoo | H45: Dương Phạm Thành Công (congdpt)
A46: 44 | B46: trucnlt | C46: Nguyễn Lê Thanh Trúc | D46: Fresher QC Engineer | E46: Project | F46: Tech | G46: Resource Pool | H46: Đoàn Hải Nam | I46: namdh02
A47: 45 | B47: quymx | C47: Mai Xuân Quý | D47: Fresher Software Engineer | F47: Tech | H47: Nguyễn Văn Bình | I47: binhnv5
A48: 46 | B48: khanhnq | C48: Nguyễn Quốc Khánh | D48: Fresher Software Engineer | F48: Tech | H48: Phùng Thanh Huy (huypt3)
A49: 47 | B49: huyennvn | C49: Nguyễn Vũ Ngọc Huyền | D49: Accountant Intern | F49: FA | H49: Hồ Thu Dung (dunght)
A50: 48 | B50: huybt | C50: Bùi Tuấn Huy | D50: Regional Business Manager | E50: AM | F50: Sales | G50: Resource Pool | H50: Đoàn Hải Nam | I50: namdh02
A51: 49 | B51: nhannt | C51: Nguyễn Thiện Nhân | D51: Senior Software Engineer | E51: Project | F51: Tech | G51: Resource Pool | H51: Đoàn Hải Nam | I51: namdh02
A52: 50 | B52: quangtt | C52: Trần Thanh Quang | D52: Senior Site Reliability Engineer | F52: Tech | H52: Trần Triệu Dương (duongtt5)
A53: 51 | B53: vinhtt | C53: Trần Thanh Vinh | D53: Cloud Senior Engineer | F53: Tech | H53: Trần Triệu Dương (duongtt5)
A54: 52 | B54: vuongtx | C54: Trịnh Xuân Vượng | D54: Solutions Architect | F54: Tech | H54: Dương Huỳnh Nghĩa (nghiadh)
A55: 53 | B55: haunc | C55: Nguyễn Công Hậu | D55: Lead Data Engineer | F55: Tech | H55: Dương Huỳnh Nghĩa (nghiadh)
A56: 54 | B56: thaibq | C56: Bùi Quốc Thái | D56: Associate QC Engineer | E56: Project | F56: Tech | G56: Venture | H56: Nguyễn Khánh Vy | I56: vynk2 | J56: 30/07/2025 | L56: Active | M56: HCM
A57: 55 | B57: binhkg | C57: Khổng Gia Bình | D57: Software Engineer | F57: Tech | H57: Trần Triệu Dương (duongtt5)
A58: 56 | B58: baonq | C58: Nguyễn Quốc Bảo | D58: DevOps Engineer | F58: Tech | H58: Trần Triệu Dương (duongtt5)
A59: 57 | B59: phuctv | C59: Trần Vĩnh Phúc | D59: Senior IT Engineer | F59: Tech | H59: Trần Triệu Dương (duongtt5) | I59: duongtt5 | J59: 28/7/2025 | L59: Active | M59: HCM | N59: Part-time
A60: 58 | B60: haodcs | C60: Dương Chung Sĩ Hào | D60: Software Engineer | F60: Tech | H60: Trần Triệu Dương (duongtt5) | I60: duongtt5
A61: 59 | B61: vandh | C61: Đinh Hiểu Văn | D61: Software Engineer | F61: Tech | H61: Trần Triệu Dương (duongtt5) | I61: duongtt5 | J61: 28/7/2025 | L61: Active | M61: HCM
A62: 60 | B62: quangnd | C62: Nguyễn Đăng Quang | D62: Cloud Security Engineer | F62: Tech | H62: Trần Triệu Dương (duongtt5) | I62: duongtt5 | L62: Active | M62: HCM
A63: 61 | B63: tutmt | C63: Trần Mạch Thanh Tú | D63: Senior Software Engineer | F63: Tech | H63: Trần Triệu Dương (duongtt5) | I63: duongtt5 | J63: 28/7/2025 | L63: Active | M63: HCM
A64: 62 | B64: phuchh | C64: Huỳnh Hồng Phúc | D64: Accountant Intern | F64: FA | H64: Trần Triệu Dương (duongtt5) | I64: duongtt5 | J64: 28/7/2025 | L64: Active | M64: HCM
A65: 63 | B65: thunqg | C65: Nguyễn Quỳnh Gia Thư | D65: QC Engineer | F65: Tech | H65: Dương Phạm Thành Công (congdpt) | I65: congdpt | J65: 28/7/2025 | L65: Active | M65: HCM
A66: 64 | B66: linhptt | C66: Phạm Thị Trúc Linh | D66: Associate QC Engineer | E66: Project | F66: Tech | G66: Venture | H66: Nguyễn Khánh Vy | I66: vynk2 | J66: 28/7/2025 | L66: Active | M66: HCM
A67: 65 | B67: thupa | C67: Phan Anh Thư | D67: Associate Accounting Manager | F67: Sales | H67: Trần Huyền Thanh (thanhth5) | I67: thanhth5 | J67: 28/7/2025 | L67: Active | M67: HCM
A68: 66 | B68: tramvn | C68: Võ Ngọc Trâm | D68: CFO | F68: CFO | H68: Hồ Thành Nghĩa (nghiaht4) | I68: nghiaht4 | J68: 28/7/2025 | L68: Active | M68: HCM
A69: 67 | B69: khainv | C69: Nguyễn Viết Khải | D69: Lead IT Support Engineer | E69: Undirect IT Staff | F69: Tech | G69: Operation Team | H69: Đoàn Hải Nam | I69: namdh02 | J69: 28/7/2025 | L69: Active | M69: HCM
A70: 68 | B70: tuandtb | C70: Đinh Trương Bảo Tuấn | D70: Lead Engineer | F70: Tech | H70: Trần Triệu Dương (duongtt5) | I70: duongtt5 | J70: 28/7/2025 | L70: Active | M70: HCM
A71: 69 | B71: trungnv | C71: Nguyễn Việt Trung | D71: Internal Auditor | E71: BO | F71: Business Support | G71: Operation Team | H71: Nguyễn Thị My Sa | I71: santm | J71: 21/7/2025 | L71: Active | M71: HCM
A72: 70 | B72: khamnc | C72: Nguyễn Chí Khâm | D72: Software Engineer | F72: Tech | H72: Trần Triệu Dương (duongtt5) | I72: duongtt5 | J72: 21/7/2025 | K72: 23/7/2025 | L72: Inactive | M72: HCM
A73: 71 | B73: lannv | C73: Nguyễn Văn Lân | D73: Software Engineer | F73: Tech | H73: Trần Triệu Dương (duongtt5) | I73: duongtt5 | J73: 45845 | L73: Active | M73: HCM
A74: 72 | B74: baong5 | C74: Nguyễn Gia Bảo | D74: Software Engineer | F74: Tech | H74: Trần Triệu Dương (duongtt5) | I74: duongtt5 | J74: 45845 | K74: 45968 | L74: Inactive | M74: HCM
A75: 73 | B75: anhlqv | C75: Lê Quý Vân Anh | D75: Senior C&B Specialist | E75: BO | F75: Business Support | G75: Operation Team | H75: Nguyễn Thị My Sa | I75: santm | J75: 45695 | L75: Active | M75: HCM
A76: 74 | B76: hamtc | C76: Mai Thị Cẩm Hà | D76: Associate GRC Analyst | E76: BO | F76: Business Support | G76: Operation Team | H76: Nguyễn Thị My Sa | I76: santm | J76: 45695 | L76: Active | M76: HCM
A77: 75 | B77: alim | C77: Ali Mustafa | D77: Data Solution Architect | H77: Aleksandar Jelic (jelica) | I77: jelica | J77: 30/06/2025 | L77: Active | M77: UAE
A78: 76 | B78: thangdv2 | C78: Dư Vi Thăng | D78: Senior IT Engineer | F78: Tech | H78: Trần Triệu Dương (duongtt5) | I78: duongtt5 | J78: 23/06/2025 | K78: 45754 | L78: Inactive | M78: HCM | N78: Replace
A79: 77 | B79: tungdx2 | C79: Đào Xuân Tùng | D79: Software Engineer | F79: Tech | H79: Trần Triệu Dương (duongtt5) | I79: duongtt5 | J79: 18/06/2025 | L79: Active | M79: HCM
A80: 78 | B80: thinhln | C80: Lê Nhựt Thịnh | D80: Software Engineer | F80: Tech | H80: Trần Triệu Dương (duongtt5) | I80: duongtt5 | J80: 45817 | L80: Active | M80: HCM
A81: 79 | B81: hantv | C81: Nguyễn Thị Việt Hà | D81: Incident Manager | F81: OP | H81: Chu Văn Toàn (ToanCV) | I81: ToanCV | J81: 45817 | L81: Active | M81: HCM
A82: 80 | B82: toantm3 | C82: Trịnh Minh Toàn | D82: Senior Software Engineer | E82: Project | F82: Tech | G82: Venture | H82: Đoàn Nhật Duẩn (duandn) | I82: duandn | J82: 45812 | L82: Active | M82: HCM
A83: 81 | B83: manth4 | C83: Trần Hữu Mẫn | D83: Senior Project Manager | F83: Tech | H83: Aleksandar Jelic (jelica) | I83: jelica | J83: 45812 | L83: Active | M83: HCM
A84: 82 | B84: hoant | C84: Nguyễn Thị Hoa | D84: Senior C&B Specialist | F84: Business Support | H84: Aleksandar Jelic (jelica) | I84: jelica | J84: 27/05/2025 | L84: Active | M84: HCM
A85: 83 | B85: chidu | C85: Dương Uyên Chi | D85: Trainer and Knowledge Manager | F85: OP | H85: Chu Văn Toàn (ToanCV) | I85: ToanCV | J85: 26/05/2025 | L85: Active | M85: HCM
A86: 84 | B86: lamdbn | C86: Dương Bảo Nhật Lam | D86: Associate NOC Engineer | F86: OP | H86: Nguyễn Tấn Anh Khoa (khoanta) | I86: khoanta | J86: 14/05/2025 | L86: Active | M86: HCM
A87: 85 | B87: locthc | C87: Trần Huỳnh Công Lộc | D87: DevOps Engineer | F87: Tech | H87: Nguyễn Hữu Hỷ (hynh) | I87: hynh | J87: 45996 | L87: Active | M87: HCM
A88: 86 | B88: doandtt | C88: Đinh Thị Thục Đoan | D88: Talent Acquisition and Development Manager | F88: Business Support | H88: Aleksandar Jelic (jelica) | I88: jelica | J88: 45782 | L88: Active | M88: HCM
A89: 87 | B89: thienndp | C89: Nguyễn Dư Phước Thiện | D89: Site Reliability Engineer | F89: Tech | H89: Trần Triệu Dương (duongtt5) | I89: duongtt5 | J89: 28/04/2025 | K89: 26/06/2025 | L89: Active | M89: HCM | N89: Replace
A90: 88 | B90: trunglm8 | C90: Lê Minh Trung | D90: Service Delivery Manager | F90: OP | H90: Chu Văn Toàn (ToanCV) | I90: ToanCV | J90: 28/04/2025 | L90: Active | M90: HCM
A91: 89 | B91: thangpq | C91: Phan Quốc Thắng | D91: Associate IT Operations Engineer | F91: OP | H91: Nguyễn Tấn Anh Khoa (khoanta) | I91: khoanta | J91: 28/04/2025 | L91: Active | M91: HCM
A92: 90 | B92: trungnt15 | C92: Nguyễn Thành Trung | D92: IT Service Management Specialist II | F92: OP | H92: Chu Văn Toàn (ToanCV) | I92: ToanCV | J92: 16/04/2025 | L92: Active | M92: HCM
A93: 91 | B93: bachnc | C93: Nguyễn Cao Bách | D93: Site Reliability Engineer | F93: OP | H93: Trần Triệu Dương (duongtt5) | I93: duongtt5 | J93: 14/04/2025 | L93: Active | M93: HCM
A94: 92 | B94: khoapd4 | C94: Phan Đăng Khoa | D94: Site Reliability Engineer | F94: Tech | H94: Nguyễn Tấn Anh Khoa (khoanta) | I94: khoanta | J94: 14/04/2025 | L94: Active | M94: HCM
A95: 93 | B95: nhubtt2 | C95: Bùi Thị Tuyết Như | D95: Finance Executive | F95: FA | H95: Hồ Thành Nghĩa (nghiaht4) | I95: nghiaht4 | J95: 14/04/2025 | L95: Active | M95: HCM
A96: 94 | B96: tuhc2 | C96: Huỳnh Cẩm Tú | D96: Technical Support Engineer | F96: OP | H96: Nguyễn Tấn Anh Khoa (khoanta) | I96: khoanta | J96: 45904 | L96: Active | M96: HCM
A97: 95 | B97: dunght2 | C97: Hồ Thu Dung | D97: General Accountant, Executive | F97: FA | H97: Hồ Thành Nghĩa (nghiaht4) | I97: nghiaht4 | J97: 45692 | L97: Active | M97: HCM
A98: 96 | B98: thainv3 | C98: Nguyễn Vũ Thái | D98: Senior Software Engineer | F98: Tech | H98: Trần Vĩnh Phúc (phuctv2) | I98: phuctv2 | J98: 45692 | K98: 45692 | L98: Inactive | M98: HCM | N98: Replace
A99: 97 | B99: toancv | C99: Chu Văn Toàn | D99: Change And Release Manager | F99: OP | H99: Dương Huỳnh Nghĩa (nghiadh) | I99: nghiadh | J99: 31/03/2025 | L99: Active | M99: HCM
A100: 98 | B100: hanhntm5 | C100: Nguyễn Thị Mỹ Hạnh | D100: HR Operations Manager | F100: Business Support | H100: Aleksandar Jelic (jelica) | I100: jelica | J100: 31/03/2025 | K100: 25/04/2025 | L100: Inactive | M100: HCM
...

Sheet FA Laptop Tracking
A1: No | B1: Label | C1: Description | D1: SN | E1: Employee Name | F1: Employee ID | G1: Business Unit | H1: Job Family | I1: Project | J1: Location | K1: Condition
A2: {=IFERROR(_xlfn._xlws.FILTER(Detail!A2:A532,(Detail!B2:B532="LAPTOP")*((Detail!C2:C532="In Use")+(Detail!C2:C532="In Stock")+(Detail!C2:C532="Damaged")+(Detail!C2:C532="Sold")+(Detail!C2:C532="Lost")+(Detail!C2:C532="Warranty"))*((Detail!G2:G532="HCM")+(Detail!G2:G532="HN")+(Detail!G2:G532="UAE")),""),"")} -> 1 | B2: {=IFERROR(_xlfn._xlws.FILTER(Detail!I2:I532,(Detail!B2:B532="LAPTOP")*((Detail!C2:C532="In Use")+(Detail!C2:C532="In Stock")+(Detail!C2:C532="Damaged")+(Detail!C2:C532="Sold")+(Detail!C2:C532="Lost")+(Detail!C2:C532="Warranty"))*((Detail!G2:G532="HCM")+(Detail!G2:G532="HN")+(Detail!G2:G532="UAE")),""),"")} -> LAP0001 | C2: {=IFERROR(_xlfn._xlws.FILTER(Detail!K2:K532,(Detail!B2:B532="LAPTOP")*((Detail!C2:C532="In Use")+(Detail!C2:C532="In Stock")+(Detail!C2:C532="Damaged")+(Detail!C2:C532="Sold")+(Detail!C2:C532="Lost")+(Detail!C2:C532="Warranty"))*((Detail!G2:G532="HCM")+(Detail!G2:G532="HN")+(Detail!G2:G532="UAE")),""),"")} -> Macbook Pro M2 16GB | 256GB | D2: {=IFERROR(_xlfn._xlws.FILTER(Detail!P2:P532,(Detail!B2:B532="LAPTOP")*((Detail!C2:C532="In Use")+(Detail!C2:C532="In Stock")+(Detail!C2:C532="Damaged")+(Detail!C2:C532="Sold")+(Detail!C2:C532="Lost")+(Detail!C2:C532="Warranty"))*((Detail!G2:G532="HCM")+(Detail!G2:G532="HN")+(Detail!G2:G532="UAE")),""),"")} -> GVXHT9W54J | E2: {=IFERROR(_xlfn._xlws.FILTER(Detail!AJ2:AJ532,(Detail!B2:B532="LAPTOP")*((Detail!C2:C532="In Use")+(Detail!C2:C532="In Stock")+(Detail!C2:C532="Damaged")+(Detail!C2:C532="Sold")+(Detail!C2:C532="Lost")+(Detail!C2:C532="Warranty"))*((Detail!G2:G532="HCM")+(Detail!G2:G532="HN")+(Detail!G2:G532="UAE")),""),"")} -> Bùi Quốc Thái | F2: {=IFERROR(_xlfn._xlws.FILTER(Detail!AK2:AK532,(Detail!B2:B532="LAPTOP")*((Detail!C2:C532="In Use")+(Detail!C2:C532="In Stock")+(Detail!C2:C532="Damaged")+(Detail!C2:C532="Sold")+(Detail!C2:C532="Lost")+(Detail!C2:C532="Warranty"))*((Detail!G2:G532="HCM")+(Detail!G2:G532="HN")+(Detail!G2:G532="UAE")),""),"")} -> thaibq | G2: {=IFERROR(_xlfn._xlws.FILTER(Detail!D2:D532,(Detail!B2:B532="LAPTOP")*((Detail!C2:C532="In Use")+(Detail!C2:C532="In Stock")+(Detail!C2:C532="Damaged")+(Detail!C2:C532="Sold")+(Detail!C2:C532="Lost")+(Detail!C2:C532="Warranty"))*((Detail!G2:G532="HCM")+(Detail!G2:G532="HN")+(Detail!G2:G532="UAE")),""),"")} -> Project | H2: {=IFERROR(_xlfn._xlws.FILTER(Detail!E2:E532,(Detail!B2:B532="LAPTOP")*((Detail!C2:C532="In Use")+(Detail!C2:C532="In Stock")+(Detail!C2:C532="Damaged")+(Detail!C2:C532="Sold")+(Detail!C2:C532="Lost")+(Detail!C2:C532="Warranty"))*((Detail!G2:G532="HCM")+(Detail!G2:G532="HN")+(Detail!G2:G532="UAE")),""),"")} -> Tech | I2: {=IFERROR(_xlfn._xlws.FILTER(Detail!F2:F532,(Detail!B2:B532="LAPTOP")*((Detail!C2:C532="In Use")+(Detail!C2:C532="In Stock")+(Detail!C2:C532="Damaged")+(Detail!C2:C532="Sold")+(Detail!C2:C532="Lost")+(Detail!C2:C532="Warranty"))*((Detail!G2:G532="HCM")+(Detail!G2:G532="HN")+(Detail!G2:G532="UAE")),""),"")} -> Venture | J2: {=IFERROR(_xlfn._xlws.FILTER(Detail!G2:G532,(Detail!B2:B532="LAPTOP")*((Detail!C2:C532="In Use")+(Detail!C2:C532="In Stock")+(Detail!C2:C532="Damaged")+(Detail!C2:C532="Sold")+(Detail!C2:C532="Lost")+(Detail!C2:C532="Warranty"))*((Detail!G2:G532="HCM")+(Detail!G2:G532="HN")+(Detail!G2:G532="UAE")),""),"")} -> HCM | K2: {=IFERROR(_xlfn._xlws.FILTER(Detail!C2:C532,(Detail!B2:B532="LAPTOP")*((Detail!C2:C532="In Use")+(Detail!C2:C532="In Stock")+(Detail!C2:C532="Damaged")+(Detail!C2:C532="Sold")+(Detail!C2:C532="Lost")+(Detail!C2:C532="Warranty"))*((Detail!G2:G532="HCM")+(Detail!G2:G532="HN")+(Detail!G2:G532="UAE")),""),"")} -> In Use
A3: 4 | B3: LAP0002 | C3: Lenovo Thinkpad X390 i5 16GB | 256GB | D3: PF1FUUQ0 | F3: 0 | J3: HCM | K3: In Stock
A4: 7 | B4: LAP0004 | C4: Macbook Pro M1 16GB | 256GB | D4: C02HC0JVQ05N | F4: 0 | J4: HCM | K4: In Stock
A5: 9 | B5: LAP0005 | C5: Macbook Pro M1 16GB | 256GB | D5: C02G12P8Q05N | E5: Huỳnh Thúy Diễm | F5: diemht | G5: Project | H5: Tech | I5: Venture | J5: HCM | K5: In Use
A6: 11 | B6: LAP0007 | C6: Lenovo ThinkPad X13 i5 16GB | 256GB | D6: PC1MHDDG | F6: 0 | J6: HCM | K6: In Stock
A7: 15 | B7: LAP0009 | C7: Lenovo ThinkPad X13 i5 16GB | 256GB | D7: PC1ZJRVM | F7: 0 | J7: HCM | K7: In Stock
A8: 19 | B8: LAP0011 | C8: Lenovo ThinkPad T490 i5 16GB | 256GB | D8: PF2B20VE | E8: Huỳnh Nguyên Phương | F8: phuonghn | G8: Project | H8: Tech | I8: Resource Pool | J8: HCM | K8: In Use
A9: 20 | B9: LAP0012 | C9: Lenovo ThinkPad T14 i5 16GB | 256GB | D9: PF2GP2ZD | F9: 0 | J9: HCM | K9: Damaged
A10: 22 | B10: LAP0013 | C10: Macbook Pro M1 16GB | 256GB | D10: FVFHQ8MMQ05N | F10: 0 | J10: HCM | K10: In Stock
A11: 24 | B11: LAP0014 | C11: Macbook Pro M1 16GB | 256GB | D11: FVFHQ8TJQ05N | F11: 0 | J11: HCM | K11: In Stock
A12: 25 | B12: LAP0015 | C12: Lenovo ThinkPad T14 i5 16GB | 256GB | D12: PF2JY588 | F12: 0 | J12: HCM | K12: In Stock
A13: 26 | B13: LAP0016 | C13: Lenovo ThinkPad X13 i5 16GB | 256GB | D13: PC2CD0J9 | E13: Nguyễn Quý | F13: quyn | G13: Project | H13: Tech | I13: Venture | J13: HCM | K13: In Use
A14: 27 | B14: LAP0017 | C14: Lenovo ThinkPad T480 i5 16GB | 256GB | D14: PF1GA0XV | F14: 0 | J14: HCM | K14: In Stock
A15: 28 | B15: LAP0018 | C15: Lenovo ThinkPad T14 i5 16GB | 256GB | D15: PF2QD6RR | E15: Huỳnh Nguyên Phương | F15: phuonghn | G15: Project | H15: Tech | I15: Resource Pool | J15: HCM | K15: In Use
A16: 29 | B16: LAP0019 | C16: Lenovo ThinkPad X280 i5 16GB | 256GB | D16: PC0X2880 | F16: 0 | J16: HCM | K16: In Stock
A17: 30 | B17: LAP0020 | C17: Lenovo ThinkPad T14 i5 16GB | 256GB | D17: PF2JY3VW | F17: 0 | J17: HCM | K17: Damaged
A18: 32 | B18: LAP0022 | C18: Macbook Pro M1 16GB | 256GB | D18: C02H70Q6Q05N | F18: 0 | J18: HCM | K18: In Stock
A19: 33 | B19: LAP0023 | C19: Lenovo ThinkPad T14 i5 16GB | 256GB | D19: PF3W4343 | F19: 0 | J19: HCM | K19: In Stock
A20: 38 | B20: LAP0025 | C20: Lenovo ThinkPad T14 i5 16GB | 256GB | D20: PF2GNJE7 | F20: 0 | J20: HCM | K20: Damaged
A21: 40 | B21: LAP0026 | C21: Lenovo ThinkPad T14 i5 16GB | 256GB | D21: PF4TGZ8E | F21: 0 | J21: HCM | K21: In Stock
A22: 41 | B22: LAP0027 | C22: Macbook Pro M2 16GB | 256GB | D22: L4DQY59FQM | E22: Mai Thị Cẩm Hà | F22: hamtc | G22: BO | H22: Business Support | I22: Operation Team | J22: HCM | K22: In Use
A23: 43 | B23: LAP0029 | C23: Macbook Pro M3 16GB | 512GB | D23: C9VG4L2X6V | F23: 0 | J23: HN | K23: In Stock
A24: 44 | B24: LAP0030 | C24: Macbook Pro i5 16GB | 256GB | D24: FVFC31E9L414 | F24: 0 | J24: HCM | K24: In Stock
A25: 45 | B25: LAP0031 | C25: Macbook Pro M1 16GB | 256GB | D25: FVFHQ8Q1Q05N | E25: Phạm Bằng | F25: bangp | G25: Project | H25: Data | I25: Resource Pool | J25: HCM | K25: In Use
A26: 46 | B26: LAP0032 | C26: Lenovo ThinkPad T14 i5 16GB | 256GB | D26: PF3HLEA1 | F26: 0 | J26: HCM | K26: In Stock
A27: 48 | B27: LAP0033 | C27: Lenovo ThinkPad T14 i5 16GB | 256GB | D27: PF24WRQA | F27: 0 | J27: HCM | K27: In Stock
A28: 49 | B28: LAP0034 | C28: Lenovo ThinkPad T14 i5 16GB | 256GB | D28: PF50YBXD | E28: Bùi Tuấn Huy | F28: huybt | G28: AM | H28: Sales | I28: Resource Pool | J28: HCM | K28: In Use
A29: 51 | B29: LAP0036 | C29: Lenovo ThinkPad T14 i5 16GB | 256GB | D29: PF50Z44H | F29: 0 | J29: HCM | K29: In Stock
A30: 52 | B30: LAP0037 | C30: Lenovo ThinkPad X13 i5 16GB | 256GB | D30: PC2CKMBD | F30: 0 | J30: HCM | K30: In Stock
A31: 53 | B31: LAP0038 | C31: Lenovo ThinkPad T14 i5 16GB | 256GB | D31: PF30QSZV | F31: 0 | J31: HCM | K31: In Stock
A32: 54 | B32: LAP0039 | C32: Lenovo ThinkPad E14 i5 16GB | 256GB | D32: PF3SHFA1 | F32: 0 | J32: HCM | K32: In Stock
A33: 56 | B33: LAP0041 | C33: Lenovo ThinkPad T490 i5 16GB | 256GB | D33: PF2B1BG0 | E33: Võ Lê Nguyên Khang | F33: khangvln | G33: BO | H33: Business Support | I33: Operation Team | J33: HCM | K33: In Use
A34: 58 | B34: LAP0042 | C34: Macbook Pro i5 16GB | 256GB | D34: FVFZN0NNL414 | F34: 0 | J34: HCM | K34: In Stock
A35: 61 | B35: LAP0045 | C35: Lenovo ThinkPad T14 i5 32GB | 256GB | D35: PF2W96HB | F35: 0 | J35: HCM | K35: In Stock
A36: 62 | B36: LAP0046 | C36: Lenovo ThinkPad T14 i5 16GB | 256GB | D36: PF3M70BL | E36: Nguyễn Nhã Minh | F36: minhnn | G36: CTD | H36: CTD | I36: CTD | J36: HCM | K36: In Use
A37: 63 | B37: LAP0047 | C37: Lenovo ThinkPad X13 i5 16GB | 256GB | D37: PF41B7MC | F37: 0 | J37: HCM | K37: In Stock
A38: 64 | B38: LAP0048 | C38: Macbook Pro i5 16GB | 256GB | D38: FVFC32J8L414 | F38: 0 | J38: HCM | K38: In Stock
A39: 65 | B39: LAP0049 | C39: Macbook Pro M1 16GB | 256GB | D39: FVFHQ849Q05N | F39: 0 | J39: HCM | K39: In Stock
A40: 66 | B40: LAP0050 | C40: Lenovo ThinkPad X13 i5 16GB | 256GB | D40: PC1PQEFM | F40: 0 | J40: HCM | K40: In Stock
A41: 68 | B41: LAP0052 | C41: Lenovo ThinkPad T14 i5 16GB | 256GB | D41: PF2LR2H8 | F41: 0 | J41: HCM | K41: In Stock
A42: 69 | B42: LAP0053 | C42: Macbook Pro M2 16GB | 256GB | D42: DLJY37N2RR | E42: Nguyễn Quang Hoàng | F42: hoangnq3 | G42: Project | H42: Tech | I42: Venture | J42: HCM | K42: In Use
A43: 72 | B43: LAP0056 | C43: Lenovo ThinkPad T14 i5 16GB | 256GB | D43: PF4TFPQ2 | F43: 0 | J43: HCM | K43: In Stock
A44: 73 | B44: LAP0057 | C44: Lenovo ThinkPad X13 i5 16GB | 256GB | D44: PC2CD0J1 | F44: 0 | J44: HCM | K44: In Stock
A45: 74 | B45: LAP0058 | C45: Lenovo ThinkPad X13 i5 16GB | 256GB | D45: PFASDZXC | E45: Nguyễn Ngọc Nhiên | F45: nhiennn | G45: BO | H45: Business Support | I45: Operation Team | J45: HCM | K45: In Use
A46: 75 | B46: LAP0059 | C46: Lenovo ThinkPad T14 i5 16GB | 256GB | D46: PF24WRQX | F46: 0 | J46: HCM | K46: In Stock
A47: 76 | B47: LAP0060 | C47: Macbook Pro M3 16GB | 512GB | D47: FTQ79J1GQ9 | E47: Đoàn Nhật Duẩn | F47: duandn | G47: Project | H47: Tech | I47: Venture | J47: HCM | K47: In Use
A48: 78 | B48: LAP0062 | C48: Macbook Pro M2 16GB | 256GB | D48: YQX1W3H610 | E48: Phạm Thị Trúc Linh | F48: linhptt | G48: Project | H48: Tech | I48: Venture | J48: HCM | K48: In Use
A49: 79 | B49: LAP0063 | C49: Lenovo ThinkPad T14 i5 16GB | 256GB | D49: PF2CG3WP | F49: 0 | J49: HCM | K49: In Stock
A50: 80 | B50: LAP0064 | C50: Macbook Pro M3 16GB | 512GB | D50: G7YCYYXR70 | E50: Nguyễn Hồ Quốc Thịnh | F50: thinhnhq | G50: Project | H50: Tech | I50: Venture | J50: HCM | K50: In Use
A51: 81 | B51: LAP0065 | C51: Lenovo ThinkPad T14 i5 16GB | 256GB | D51: PF50YJQX | E51: Nguyễn Minh Thy | F51: thynm | G51: CTD | H51: CTD | I51: CTD | J51: HCM | K51: In Use
A52: 82 | B52: LAP0066 | C52: Lenovo ThinkPad E14 i5 16GB | 256GB | D52: PF3M4L8N | E52: Trương Nữ Ngọc Mai | F52: maitnn | G52: BO | H52: Business Support | I52: Operation Team | J52: HCM | K52: In Use
A53: 83 | B53: LAP0067 | C53: Lenovo ThinkPad T14 i5 16GB | 256GB | D53: PF3M7ZFN | F53: 0 | J53: HCM | K53: In Stock
A54: 84 | B54: LAP0068 | C54: Lenovo ThinkPad X13 i5 16GB | 256GB | D54: PF2CF7TN | E54: Nguyễn Việt Trung | F54: trungnv | G54: BO | H54: Business Support | I54: Operation Team | J54: HCM | K54: In Stock
A55: 85 | B55: LAP0069 | C55: Lenovo ThinkPad T14 i5 16GB | 256GB | D55: PF3HMEV9 | E55: Kiết Văn | F55: vank | G55: 0 | H55: 0 | I55: 0 | J55: HCM | K55: Sold
A56: 86 | B56: LAP0070 | C56: Lenovo ThinkPad T480 i5 16GB | 256GB | D56: PF1NEMT7 | F56: 0 | J56: HCM | K56: In Stock
A57: 100 | B57: LAP0071 | C57: Lenovo ThinkPad T490 i5 16GB | 256GB | D57: PF1VRCB1 | F57: 0 | J57: HCM | K57: In Stock
A58: 101 | B58: LAP0072 | C58: Macbook Pro i5 16GB | 256GB | D58: FVFC61XCL414 | F58: 0 | J58: HCM | K58: In Stock
A59: 102 | B59: LAP0073 | C59: Macbook Pro M1 16GB | 256GB | D59: C02G12P5Q05N | E59: Đoàn Hà Mi | F59: midh | G59: BO | H59: Business Support | I59: Operation Team | J59: HCM | K59: In Use
A60: 103 | B60: LAP0074 | C60: Lenovo ThinkPad X13 i5 16GB | 256GB | D60: PC2CKMAP | E60: Hoàng Thị Trang | F60: tranght | G60: BO | H60: Business Support | I60: Operation Team | J60: HCM | K60: In Use
A61: 104 | B61: LAP0075 | C61: Lenovo ThinkPad T480 i5 No RAM | 256GB | D61: PF1NEFQR | F61: 0 | J61: HCM | K61: In Stock
A62: 106 | B62: LAP0076 | C62: Lenovo ThinkPad X1 carbon i7 16GB | 512GB | D62: PF3Z9LM6 | E62: Gary Robert Charles Mckinnon | F62: garym | G62: 0 | H62: CEO | I62: 0 | J62: HCM | K62: Sold
A63: 191 | B63: LAP0078 | C63: Macbook Pro M1 16GB | 256GB | D63: C02DW9GDQ05N | E63: Nguyễn Quốc Trung | F63: trungnq | G63: Undirect IT Staff | H63: Tech | I63: Odoo | J63: HCM | K63: In Use
A64: 192 | B64: LAP0079 | C64: Macbook Pro M1 16GB | 256GB | D64: C02H72GFQ05N | F64: 0 | J64: HCM | K64: Damaged
A65: 193 | B65: LAP0080 | C65: Macbook Pro M1 16GB | 256GB | D65: C02H72FHQ05N | E65: Nguyễn Ngọc Trinh | F65: trinhnn | G65: Undirect IT Staff | H65: Tech | I65: Odoo | J65: HCM | K65: In Stock
A66: 194 | B66: LAP0081 | C66: Macbook Pro M1 16GB | 256GB | D66: C02H70QRQ05N | E66: Nguyễn Lê Thanh Trúc | F66: trucnlt | G66: Project | H66: Tech | I66: Resource Pool | J66: HCM | K66: In Use
A67: 195 | B67: LAP0082 | C67: Macbook Pro Intel 16GB | 256GB | D67: FVFC61WWL414 | F67: 0 | J67: HCM | K67: In Stock
A68: 197 | B68: LAP0084 | C68: Macbook Pro M1 16GB | 256GB | D68: FVFHQ8N4Q05N | F68: 0 | J68: HCM | K68: In Stock
A69: 291 | B69: LAP0085 | C69: Macbook Pro M2 16GB | 256GB | D69: YD403FQGW6 | E69: Đào Duy Thoại | F69: thoaidd | G69: CTD | H69: CTD | I69: CTD | J69: HCM | K69: In Use
A70: 292 | B70: LAP0086 | C70: Lenovo ThinkPad E14 i5 16GB | 256GB | D70: PF3S5HGW | E70: Nguyễn Ngọc Lân | F70: lannn | G70: Project | H70: Tech | I70: Venture | J70: HCM | K70: In Use
A71: 293 | B71: LAP0087 | C71: Macbook Pro M1 16GB | 256GB | D71: C02GT1P2Q05N | F71: 0 | J71: HCM | K71: In Stock
A72: 294 | B72: LAP0088 | C72: Lenovo ThinkPad T14 i5 16GB | 256GB | D72: PF3HMCM4 | E72: Ivan | F72: Ivan | G72: 0 | H72: 0 | I72: 0 | J72: HCM | K72: Lost
A73: 295 | B73: LAP0089 | C73: Lenovo ThinkPad T14 i5 16GB | 256GB | D73: PF4TGN3B | E73: Ali Mustafa | F73: alim | G73: 0 | H73: 0 | I73: 0 | J73: HCM | K73: Lost
A74: 296 | B74: LAP0090 | C74: Lenovo ThinkPad T14 i5 16GB | 256GB | D74: PF4TFKEF | E74: Trần Gia Ân | F74: antg | G74: CTD | H74: CTD | I74: CTD | J74: HCM | K74: In Use
A75: 315 | B75: LAP0091 | C75: Macbook Pro M4 16GB | 512GB | D75: SKVWYWVVP79 | F75: 0 | J75: HCM | K75: Warranty
A76: 319 | B76: LAP0095 | C76: Macbook Pro M4 16GB | 512GB | D76: SCVY94FHJ97 | E76: Dương Phạm Thành Công | F76: congdpt | G76: Undirect IT Staff | H76: Tech | I76: Odoo | J76: HCM | K76: In Use
A77: 320 | B77: LAP0096 | C77: Macbook Pro M4 16GB | 512GB | D77: SHQXVQ73MFJ | E77: Nguyễn Ngọc Trinh | F77: trinhnn | G77: Undirect IT Staff | H77: Tech | I77: Odoo | J77: HCM | K77: In Use
A78: 321 | B78: LAP0097 | C78: Macbook Pro M4 16GB | 512GB | D78: SF7FL62XW9F | E78: Trịnh Minh Toàn | F78: toantm3 | G78: Project | H78: Tech | I78: Venture | J78: HCM | K78: In Use
A79: 323 | B79: LAP0099 | C79: Macbook Pro M4 16GB | 512GB | D79: SD4RQM4JX7D | E79: Phùng Thanh Huy | F79: huypt3 | G79: Project | H79: Tech | I79: Venture | J79: HCM | K79: In Use
A80: 324 | B80: LAP0100 | C80: Macbook Pro M4 16GB | 512GB | D80: SG9159NH25G | E80: Ngô Khánh Vy | F80: vynk2 | G80: Project | H80: Tech | I80: Venture | J80: HCM | K80: In Use
A81: 325 | B81: LAP0101 | C81: Macbook Pro M4 16GB | 512GB | D81: SD00NC3F0Y0 | E81: Trần Hoàng Anh | F81: anhth | G81: Project | H81: Data | I81: Venture | J81: HCM | K81: In Use
A82: 326 | B82: LAP0102 | C82: Macbook Pro M4 16GB | 512GB | D82: SCLGQ5W5QDH | E82: Đặng Thành Thái | F82: thaidt | G82: Undirect IT Staff | H82: Tech | I82: Odoo | J82: HCM | K82: In Use
A83: 327 | B83: LAP0103 | C83: Macbook Pro M4 16GB | 512GB | D83: SMQYTXVHY39 | E83: Nguyễn Quý | F83: quyn | G83: Project | H83: Tech | I83: Venture | J83: HCM | K83: In Use
A84: 333 | B84: LAP0109 | C84: Macbook Pro M4 16GB | 512GB | D84: SLDXG3DD2LY | E84: Võ Thành Nhơn | F84: nhonvt | G84: Project | H84: Tech | I84: Venture | J84: HCM | K84: In Use
A85: 334 | B85: LAP0110 | C85: Macbook Pro M4 16GB | 512GB | D85: SJ9WVM6XCXM | F85: 0 | J85: HCM | K85: Warranty
A86: 336 | B86: LAP0112 | C86: Macbook Pro M4 24GB | 1TB | D86: SJ6D370RF9L | E86: Đinh Vũ Tiến | F86: tiendv2 | G86: BO | H86: Marketing | I86: Operation Team | J86: HCM | K86: In Use
A87: 340 | B87: LAP0116 | C87: Macbook Pro M4 16GB | 512GB | D87: SL2P00X9GJ6 | E87: Lại Thế Cường | F87: cuonglt8 | G87: Project | H87: Tech | I87: Venture | J87: HCM | K87: In Use
A88: 341 | B88: LAP0117 | C88: Macbook Pro M4 16GB | 512GB | D88: SCW59VQ0QTR | E88: Nguyễn Hoàng Tâm | F88: tamnh8 | G88: Project | H88: Tech | I88: Venture | J88: HCM | K88: In Use
A89: 342 | B89: LAP0118 | C89: Macbook Pro M4 16GB | 512GB | D89: SGHXPF2JQQW | E89: Nguyễn Trung Kiên | F89: kiennt8 | G89: Project | H89: Data | I89: Venture | J89: HN | K89: In Use
A90: 343 | B90: LAP0119 | C90: Macbook Pro M4 16GB | 512GB | D90: SHYX7M72MR6 | E90: Lê Cao Long Nhật | F90: nhatlcl | G90: Project | H90: Tech | I90: Venture | J90: HCM | K90: In Use
A91: 344 | B91: LAP0120 | C91: Macbook Pro M4 16GB | 512GB | D91: SK99963QMGW | E91: Nguyễn Văn Bình | F91: binhnv5 | G91: Project | H91: Tech | I91: Venture | J91: HCM | K91: In Use
A92: 345 | B92: LAP0121 | C92: Macbook Pro M4 16GB | 512GB | D92: SJ12KTW6DKL | E92: Nguyễn Thiện Nhân | F92: nhannt | G92: Project | H92: Tech | I92: Resource Pool | J92: HCM | K92: In Use
A93: 349 | B93: LAP0125 | C93: Macbook Pro M4 16GB | 512GB | D93: L7G57MMFPM | E93: Đoàn Hải Nam | F93: namdh02 | G93: CTD | H93: CTD | I93: CTD | J93: HCM | K93: In Use
A94: 350 | B94: LAP0126 | C94: Macbook Pro M4 24GB | 1TB | D94: HD2H0W34WG | E94: Nguyễn Viết Khải | F94: khainv | G94: Undirect IT Staff | H94: Tech | I94: Operation Team | J94: HCM | K94: In Stock
A95: 509 | B95: LAP0132 | C95: Lenovo ThinkPad T14 i7 16GB | 512GB | D95: PF5K4CZ8 | E95: Lê Quý Vân Anh | F95: anhlqv | G95: BO | H95: Business Support | I95: Operation Team | J95: HCM | K95: In Stock
A96: 510 | B96: LAP0133 | C96: Lenovo ThinkPad T14 i7 16GB | 512GB | D96: PF5K4D0J | E96: Lê Thị Kim Anh | F96: anhltk | G96: BO | H96: Business Support | I96: Operation Team | J96: HCM | K96: In Stock
A97: 511 | B97: LAP0134 | C97: Lenovo ThinkPad T14 i7 16GB | 512GB | D97: PF5K4D1L | E97: IT Dept CTD | F97: IT | G97: CTD | H97: CTD | I97: CTD | J97: HCM | K97: In Use
A98: 512 | B98: LAP0135 | C98: Lenovo ThinkPad T14 i7 16GB | 512GB | D98: PF5K4D2K | E98: Đoàn Hà Mi | F98: midh | G98: BO | H98: Business Support | I98: Operation Team | J98: HCM | K98: In Use
A99: 513 | B99: LAP0136 | C99: Lenovo ThinkPad T14 i7 16GB | 512GB | D99: PF5K4D48 | F99: 0 | J99: HCM | K99: In Stock
A100: 514 | B100: LAP0137 | C100: Lenovo ThinkPad T14 i7 16GB | 512GB | D100: PF5K4D5G | E100: Hoàng Thị Trang | F100: tranght | G100: BO | H100: Business Support | I100: Operation Team | J100: HCM | K100: In Use
...

Sheet FA Monitor Tracking
A1: No | B1: Label | C1: Description | D1: SN | E1: Employee Name | F1: Employee ID | G1: Business Unit | H1: Job Family | I1: Project | J1: Location | K1: Condition
A2: {=IFERROR(_xlfn._xlws.FILTER(Detail!A2:A532,(Detail!B2:B532="MONITOR")*((Detail!C2:C532="In Use")+(Detail!C2:C532="In Stock")+(Detail!C2:C532="Damaged")+(Detail!C2:C532="Sold")+(Detail!C2:C532="Lost")+(Detail!C2:C532="Warranty"))*((Detail!G2:G532="HCM")+(Detail!G2:G532="HN")),""),"")} -> 2 | B2: {=IFERROR(_xlfn._xlws.FILTER(Detail!I2:I532,(Detail!B2:B532="MONITOR")*((Detail!C2:C532="In Use")+(Detail!C2:C532="In Stock")+(Detail!C2:C532="Damaged")+(Detail!C2:C532="Sold")+(Detail!C2:C532="Lost")+(Detail!C2:C532="Warranty"))*((Detail!G2:G532="HCM")+(Detail!G2:G532="HN")),""),"")} -> MON0001 | C2: {=IFERROR(_xlfn._xlws.FILTER(Detail!K2:K532,(Detail!B2:B532="MONITOR")*((Detail!C2:C532="In Use")+(Detail!C2:C532="In Stock")+(Detail!C2:C532="Damaged")+(Detail!C2:C532="Sold")+(Detail!C2:C532="Lost")+(Detail!C2:C532="Warranty"))*((Detail!G2:G532="HCM")+(Detail!G2:G532="HN")),""),"")} -> Dell P2425H 24 inches | D2: {=IFERROR(_xlfn._xlws.FILTER(Detail!P2:P532,(Detail!B2:B532="MONITOR")*((Detail!C2:C532="In Use")+(Detail!C2:C532="In Stock")+(Detail!C2:C532="Damaged")+(Detail!C2:C532="Sold")+(Detail!C2:C532="Lost")+(Detail!C2:C532="Warranty"))*((Detail!G2:G532="HCM")+(Detail!G2:G532="HN")),""),"")} -> 331PK34 | E2: {=IFERROR(_xlfn._xlws.FILTER(Detail!AJ2:AJ532,(Detail!B2:B532="MONITOR")*((Detail!C2:C532="In Use")+(Detail!C2:C532="In Stock")+(Detail!C2:C532="Damaged")+(Detail!C2:C532="Sold")+(Detail!C2:C532="Lost")+(Detail!C2:C532="Warranty"))*((Detail!G2:G532="HCM")+(Detail!G2:G532="HN")),""),"")} -> Bùi Quốc Thái | F2: {=IFERROR(_xlfn._xlws.FILTER(Detail!AK2:AK532,(Detail!B2:B532="MONITOR")*((Detail!C2:C532="In Use")+(Detail!C2:C532="In Stock")+(Detail!C2:C532="Damaged")+(Detail!C2:C532="Sold")+(Detail!C2:C532="Lost")+(Detail!C2:C532="Warranty"))*((Detail!G2:G532="HCM")+(Detail!G2:G532="HN")),""),"")} -> thaibq | G2: {=IFERROR(_xlfn._xlws.FILTER(Detail!D2:D532,(Detail!B2:B532="MONITOR")*((Detail!C2:C532="In Use")+(Detail!C2:C532="In Stock")+(Detail!C2:C532="Damaged")+(Detail!C2:C532="Sold")+(Detail!C2:C532="Lost")+(Detail!C2:C532="Warranty"))*((Detail!G2:G532="HCM")+(Detail!G2:G532="HN")),""),"")} -> Project | H2: {=IFERROR(_xlfn._xlws.FILTER(Detail!E2:E532,(Detail!B2:B532="MONITOR")*((Detail!C2:C532="In Use")+(Detail!C2:C532="In Stock")+(Detail!C2:C532="Damaged")+(Detail!C2:C532="Sold")+(Detail!C2:C532="Lost")+(Detail!C2:C532="Warranty"))*((Detail!G2:G532="HCM")+(Detail!G2:G532="HN")),""),"")} -> Tech | I2: {=IFERROR(_xlfn._xlws.FILTER(Detail!F2:F532,(Detail!B2:B532="MONITOR")*((Detail!C2:C532="In Use")+(Detail!C2:C532="In Stock")+(Detail!C2:C532="Damaged")+(Detail!C2:C532="Sold")+(Detail!C2:C532="Lost")+(Detail!C2:C532="Warranty"))*((Detail!G2:G532="HCM")+(Detail!G2:G532="HN")),""),"")} -> Venture | J2: {=IFERROR(_xlfn._xlws.FILTER(Detail!G2:G532,(Detail!B2:B532="MONITOR")*((Detail!C2:C532="In Use")+(Detail!C2:C532="In Stock")+(Detail!C2:C532="Damaged")+(Detail!C2:C532="Sold")+(Detail!C2:C532="Lost")+(Detail!C2:C532="Warranty"))*((Detail!G2:G532="HCM")+(Detail!G2:G532="HN")),""),"")} -> HCM | K2: {=IFERROR(_xlfn._xlws.FILTER(Detail!C2:C532,(Detail!B2:B532="MONITOR")*((Detail!C2:C532="In Use")+(Detail!C2:C532="In Stock")+(Detail!C2:C532="Damaged")+(Detail!C2:C532="Sold")+(Detail!C2:C532="Lost")+(Detail!C2:C532="Warranty"))*((Detail!G2:G532="HCM")+(Detail!G2:G532="HN")),""),"")} -> In Use
A3: 109 | B3: MON0003 | C3: Dell P2425H 24 inches | D3: CF68104 | F3: 0 | J3: HCM | K3: In Stock
A4: 110 | B4: MON0004 | C4: Dell P2422H 24 inches | D4: DY4B0K3 | E4: Huỳnh Nguyên Phương | F4: phuonghn | G4: Project | H4: Tech | I4: Resource Pool | J4: HCM | K4: In Use
A5: 111 | B5: MON0005 | C5: Dell P2422H 24 inches | D5: 95J38M3 | E5: Trần Hoàng Anh | F5: anhth | G5: Project | H5: Data | I5: Venture | J5: HCM | K5: In Use
A6: 112 | B6: MON0006 | C6: Dell P2422H 24 inches | D6: 438T8M3 | E6: IT Dept CTD | F6: IT | G6: CTD | H6: CTD | I6: CTD | J6: HCM | K6: In Use
A7: 113 | B7: MON0007 | C7: Dell P2422H 24 inches | D7: FKW90K3 | E7: IT Dept CTD | F7: IT | G7: CTD | H7: CTD | I7: CTD | J7: HCM | K7: In Use
A8: 115 | B8: MON0009 | C8: Dell Ultrasharp U2520D 25 inches | D8: 6JS9923 | E8: Trịnh Minh Toàn | F8: toantm3 | G8: Project | H8: Tech | I8: Venture | J8: HCM | K8: In Use
A9: 124 | B9: MON0018 | C9: Dell Ultrasharp U2520D 25 inches | D9: DNQJ923 | E9: Nguyễn Hồ Quốc Thịnh | F9: thinhnhq | G9: Project | H9: Tech | I9: Venture | J9: HCM | K9: In Use
A10: 126 | B10: MON0020 | C10: Dell Ultrasharp U2520D 25 inches | D10: 4GQJ923 | E10: Đoàn Nhật Duẩn | F10: duandn | G10: Project | H10: Tech | I10: Venture | J10: HCM | K10: In Use
A11: 130 | B11: MON0024 | C11: Dell Ultrasharp U2520D 25 inches | D11: JHQJ923 | E11: Võ Lê Nguyên Khang | F11: khangvln | G11: BO | H11: Business Support | I11: Operation Team | J11: HCM | K11: In Use
A12: 131 | B12: MON0025 | C12: Dell Ultrasharp U2520D 25 inches | D12: BXQJ923 | E12: Phùng Thanh Huy | F12: huypt3 | G12: Project | H12: Tech | I12: Venture | J12: HCM | K12: In Use
A13: 132 | B13: MON0026 | C13: Dell Ultrasharp U2520D 25 inches | D13: 5YQJ923 | E13: Lê Cao Long Nhật | F13: nhatlcl | G13: Project | H13: Tech | I13: Venture | J13: HCM | K13: In Use
A14: 134 | B14: MON0028 | C14: Dell Ultrasharp U2520D 25 inches | D14: 2HQJ923 | E14: Nguyễn Viết Khải | F14: khainv | G14: Undirect IT Staff | H14: Tech | I14: Operation Team | J14: HCM | K14: In Use
A15: 135 | B15: MON0029 | C15: Dell Ultrasharp U2520D 25 inches | D15: DDQJ923 | E15: Nguyễn Thiện Nhân | F15: nhannt | G15: Project | H15: Tech | I15: Resource Pool | J15: HCM | K15: In Use
... A26: 149 | B26: MON0043 | C26: Dell P2425H 24 inches | D26: 3K9QK34 | E26: Huỳnh Thúy Diễm | F26: diemht | G26: Project | H26: Tech | I26: Venture | J26: HCM | K26: In Use
A27: 150 | B27: MON0044 | C27: Dell P2425H 24 inches | D27: 2W82L34 | F27: 0 | J27: HCM | K27: In Stock
A28: 151 | B28: MON0045 | C28: Dell P2425H 24 inches | D28: 2WRPK34 | F28: 0 | J28: HCM | K28: In Stock
A29: 153 | B29: MON0047 | C29: Dell P2425H 24 inches | D29: 31F2L34 | F29: 0 | J29: HCM | K29: In Stock
A30: 154 | B30: MON0048 | C30: Dell P2425H 24 inches | D30: 32RNK34 | E30: Nguyễn Thị My Sa | F30: santm | G30: CTD | H30: CTD | I30: CTD | J30: HCM | K30: In Use
A31: 155 | B31: MON0050 | C31: Dell P2425H 24 inches | D31: 33VPK34 | E31: Đoàn Hà Mi | F31: midh | G31: BO | H31: Business Support | I31: Operation Team | J31: HCM | K31: In Use
A32: 157 | B32: MON0052 | C32: Dell P2425H 24 inches | D32: 8BF2L34 | E32: Phạm Thị Trúc Linh | F32: linhptt | G32: Project | H32: Tech | I32: Venture | J32: HCM | K32: In Use
A33: 159 | B33: MON0054 | C33: Dell P2217H 22 inches | D33: 5Y4SLB2 | E33: Nguyễn Ngọc Trinh | F33: trinhnn | G33: Undirect IT Staff | H33: Tech | I33: Odoo | J33: HCM | K33: In Stock
A34: 160 | B34: MON0055 | C34: Dell P2217H 22 inches | D34: 8Y4SLB2 | F34: 0 | J34: HCM | K34: In Stock
A35: 161 | B35: MON0056 | C35: Dell P2422H 24 inches | D35: 2PY90K3 | E35: Đặng Thành Thái | F35: thaidt | G35: Undirect IT Staff | H35: Tech | I35: Odoo | J35: HCM | K35: In Use
A36: 162 | B36: MON0057 | C36: Dell P2422H 24 inches | D36: 6GY90K3 | E36: Nguyễn Quốc Trung | F36: trungnq | G36: Undirect IT Staff | H36: Tech | I36: Odoo | J36: HCM | K36: In Use
A37: 163 | B37: MON0058 | C37: Dell P2422H 24 inches | D37: 8M4B0K3 | E37: Nguyễn Quý | F37: quyn | G37: Project | H37: Tech | I37: Venture | J37: HCM | K37: In Use
A38: 166 | B38: MON0061 | C38: Dell P2422H 24 inches | D38: 3TDH7N3 | E38: Nguyễn Nhã Minh | F38: minhnn | G38: CTD | H38: CTD | I38: CTD | J38: HCM | K38: In Use
A39: 167 | B39: MON0062 | C39: Dell P2219H 22 inches | D39: 27GRV23 | E39: Trương Nữ Ngọc Mai | F39: maitnn | G39: BO | H39: Business Support | I39: Operation Team | J39: HCM | K39: In Use
A40: 171 | B40: MON0066 | C40: Dell P2422H 24 inches | D40: 67SJMQ3 | E40: Phùng Thanh Huy | F40: huypt3 | G40: Project | H40: Tech | I40: Venture | J40: HCM | K40: In Use
A41: 173 | B41: MON0068 | C41: Dell P2422H 24 inches | D41: 7R1QDQ3 | E41: Nguyễn Hoàng Tâm | F41: tamnh8 | G41: Project | H41: Tech | I41: Venture | J41: HCM | K41: In Use
A42: 174 | B42: MON0069 | C42: Dell P2422H 24 inches | D42: 89J38M3 | E42: Hoàng Thị Trang | F42: tranght | G42: BO | H42: Business Support | I42: Operation Team | J42: HCM | K42: In Use
A43: 175 | B43: MON0070 | C43: Dell P2217H 22 inches | D43: 8DY5FJ2 | F43: 0 | J43: HCM | K43: In Stock
A44: 176 | B44: MON0071 | C44: Dell P2422H 24 inches | D44: B7FB0K3 | E44: Ngô Khánh Vy | F44: vynk2 | G44: Project | H44: Tech | I44: Venture | J44: HCM | K44: In Use
A45: 177 | B45: MON0072 | C45: Dell P2219H 22 inches | D45: BHCN6W2 | E45: Dương Phạm Thành Công | F45: congdpt | G45: Undirect IT Staff | H45: Tech | I45: Odoo | J45: HCM | K45: In Use
A46: 179 | B46: MON0074 | C46: Dell Ultrasharp U2520D 25 inches | D46: BOTT823 | E46: Lại Thế Cường | F46: cuonglt8 | G46: Project | H46: Tech | I46: Venture | J46: HCM | K46: In Use
A47: 180 | B47: MON0075 | C47: Dell P2419H 24 inches | D47: DLHKF53 | F47: 0 | J47: HCM | K47: In Stock
A48: 181 | B48: MON0076 | C48: Dell P2217H 22 inches | D48: DWQBGN2 | E48: Nguyễn Ngọc Nhiên | F48: nhiennn | G48: BO | H48: Business Support | I48: Operation Team | J48: HCM | K48: In Use
A49: 182 | B49: MON0077 | C49: Dell Ultrasharp U2520D 25 inches | D49: G89Q823 | E49: Võ Thành Nhơn | F49: nhonvt | G49: Project | H49: Tech | I49: Venture | J49: HCM | K49: In Use
A50: 183 | B50: MON0078 | C50: Dell P2217H 22 inches | D50: GBTTTL2 | E50: Nguyễn Quý | F50: quyn | G50: Project | H50: Tech | I50: Venture | J50: HCM | K50: In Use
A51: 184 | B51: MON0079 | C51: Dell P2217H 22 inches | D51: J7VTTL2 | F51: 0 | J51: HCM | K51: In Stock
A52: 185 | B52: MON0080 | C52: Dell P2217H 22 inches | D52: JHSTTL2 | F52: 0 | J52: HCM | K52: In Stock
A53: 186 | B53: MON0081 | C53: Dell P2425H 24 inches | D53: GZB3944 | E53: Nguyễn Ngọc Lân | F53: lannn | G53: Project | H53: Tech | I53: Venture | J53: HCM | K53: In Use
A54: 187 | B54: MON0082 | C54: Dell P2219H 22 inches | D54: HF3QPP2 | E54: Trịnh Minh Toàn | F54: toantm3 | G54: Project | H54: Tech | I54: Venture | J54: HCM | K54: In Use
A55: 188 | B55: MON0083 | C55: Dell Ultrasharp U2518D 25 inches | D55: 9J0HPS2 | E55: Bùi Tuấn Huy | F55: huybt | G55: AM | H55: Sales | I55: Resource Pool | J55: HCM | K55: In Use
A56: 198 | B56: MON0085 | C56: Dell Ultrasharp U2520D 25 inches | D56: 6QQJ923 | F56: 0 | J56: HCM | K56: Damaged
A57: 200 | B57: MON0087 | C57: Dell P2417H 24 inches | D57: HNYN372 | F57: 0 | J57: HN | K57: In Stock
A58: 201 | B58: MON0088 | C58: Dell P2217H 22 inches | D58: FTG8L82 | F58: 0 | J58: HN | K58: In Stock
A59: 202 | B59: MON0089 | C59: Dell P2217H 22 inches | D59: 1HTTTL2 | F59: 0 | J59: HN | K59: In Stock
A60: 386 | B60: MON0097 | C60: Dell P2425H 24 inches | D60: 622VY74 | F60: 0 | J60: HCM | K60: In Stock
A61: 392 | B61: MON0103 | C61: Dell P2425H 24 inches | D61: J22VY74 | F61: 0 | J61: HCM | K61: In Stock
A62: 420 | B62: MON0131 | C62: Dell P2425H 24 inches | D62: F9JZK34 | F62: 0 | J62: HCM | K62: In Stock
A63: 424 | B63: MON0135 | C63: Dell P2425H 24 inches | D63: 35Y1874 | F63: 0 | J63: HCM | K63: In Stock
A64: 425 | B64: MON0136 | C64: Dell P2425H 24 inches | D64: G22VY74 | F64: 0 | J64: HCM | K64: In Stock
A65: 431 | B65: MON0142 | C65: Dell P2425H 24 inches | D65: GB2SK34 | F65: 0 | J65: HCM | K65: In Stock
A66: 432 | B66: MON0143 | C66: Dell P2425H 24 inches | D66: F6TQK34 | F66: 0 | J66: HCM | K66: In Stock
A67: 435 | B67: MON0146 | C67: Dell P2425H 24 inches | D67: CTRYK34 | F67: 0 | J67: HCM | K67: In Stock
A68: 437 | B68: MON0148 | C68: Dell U2723QE 27 inches | D68: D2HP734 | E68: Đào Duy Thoại | F68: thoaidd | G68: CTD | H68: CTD | I68: CTD | J68: HCM | K68: In Use
A69: 438 | B69: MON0149 | C69: Dell U2723QE 27 inches | D69: B16Y734 | E69: Đinh Vũ Tiến | F69: tiendv2 | G69: BO | H69: Marketing | I69: Operation Team | J69: HCM | K69: In Use

Sheet FA IPAD-SPH-PRN-RTR-CPUTracking
A1: No | B1: Label | C1: Description | D1: SN | E1: Employee Name | F1: Employee ID | G1: Business Unit | H1: Job Family | I1: Project | J1: Location | K1: Condition
